Workbook

Sheet Analyse des plats
A1: Nom du plat | B1: Principes de Pat utilisés | C1: Résultat de l'analyse | D1: Type de plat | E1: Prix (€) | F1: Meilleur vin de la carte | G1: Note
A2: Carpaccio de bœuf Holstein, huile d'olive, parmesan, roquette | B2: • n°1 · Les points d'ancrage • n°30 · L'amertume du plat s'additionne à celle du vin • n°28 · Le sel adoucit le vin • n°20 · L'équilibre des intensités : le vin pèse autant que le plat • n°37 · Le fromage accessoire ne dicte pas seul l'accord • n°21 · Le tanin aime le gras et le saignant de la viande rouge | C2: Ancrages : bœuf cru maigre, amertume de la roquette, sel du parmesan, huile d'olive (n°1). Profil : rouge léger, jeune et fruité, peu tannique, acidité vive, sans bois. La roquette additionne son amertume à celle d'un tanin appuyé : le tanin doit rester fin. Le parmesan salé assouplit un peu le vin, ce qui autorise un rouge plutôt qu'un blanc. Plat léger : vin léger (n°30, n°28, n°20, n°37, n°21). Cépages : Pinot noir, Gamay, Frappato, Cabernet franc, Nerello mascalese. À éviter : rouge jeune tannique ou boisé (amer sur la roquette), rouge puissant et alcooleux qui écrase la viande crue (n°19, n°30, n°20). Service : rouge léger servi frais, 13-14 °C (n°26). | D2: Entrée | E2: 26 | F2: =INDEX('Matrice des notes'!$B$6:$B$81,MATCH(G2,'Matrice des notes'!$D$6:$D$81,0)) -> L-R01 · Chiroubles Domaine Piron 2024 | G2: =MAX('Matrice des notes'!$D$6:$D$81) -> 5
A3: Émincé de bar, huile d'olive, citron vert | B3: • n°1 · Les points d'ancrage • n°24 · La sauce et la cuisson priment sur la protéine • n°23 · L'acidité du plat impose l'acidité du vin • n°7 · Agrumes seuls = incompatibles, agrumes adoucis = possibles • n°19 · Le bois couvre la finesse et amplifie l'amertume • n°9 · Anchois et iodés salins ↔ acidité littorale • n°41 · Effervescents : le cépage et le dosage dictent la table • n°35 · Un élément réfractaire plafonne l'accord | C3: Ancrages : poisson cru, citron vert, huile d'olive (n°1). Profil : blanc sec très tendu, jeune, sans bois, peu aromatique, salin. Le cru appelle un blanc tendu ; l'acidité du vin doit au moins égaler celle du citron vert, sinon il paraît mou. Le citron vert nature reste un élément difficile : un assaisonnement mesuré en cuisine améliore l'accord (n°24, n°23, n°7, n°19, n°9, n°41). Plafond : le citron vert nature est réfractaire, aucun vin ne dépasse 4 (n°35, n°7). Hypothèse : les vins de Loire, Sancerre compris, comptent comme « proches d'un fleuve » (n°9, question ouverte). Cépages : Sauvignon blanc, Albariño, Assyrtiko, Riesling sec, Grüner Veltliner. À éviter : blanc boisé ou rond, blanc peu acide, tout rouge (n°19). Service : 8-10 °C (n°26). | D3: Entrée | E3: 26 | F3: =INDEX('Matrice des notes'!$B$6:$B$81,MATCH(G3,'Matrice des notes'!$E$6:$E$81,0)) -> L-B01 · IGP Val de Loire Sauvignon Le Petit Bourgeois 2024 | G3: =MAX('Matrice des notes'!$E$6:$E$81) -> 4
A4: Scampis en tempura, sauce tartare | B4: • n°1 · Les points d'ancrage • n°34 · La friture appelle la bulle et l'acidité • n°41 · Effervescents : le cépage et le dosage dictent la table • n°23 · L'acidité du plat impose l'acidité du vin • n°10 · Œufs : difficiles partout, sauf l'œuf en meurette • n°35 · Un élément réfractaire plafonne l'accord | C4: Ancrages : friture légère et croustillante, chair sucrée du crustacé, sauce tartare (émulsion à l'œuf, câpres, cornichons) (n°1). Profil : effervescent brut de méthode traditionnelle, style blanc de blancs, ou blanc sec très tendu ; jeune, sans bois. La bulle et l'acidité nettoient le gras de la friture ; les câpres et cornichons imposent une acidité au moins égale. L'émulsion à l'œuf déstabilise un peu le vin : accord très bon sur le scampi, un cran en dessous sur la sauce (n°34, n°41, n°23, n°10, n°35). Plafond : la sauce tartare est une émulsion à l'œuf, aucun vin ne dépasse 4 (n°35, n°10, émulsion traitée comme l'œuf : question ouverte). Cépages : Chardonnay (effervescent blanc de blancs), Chenin blanc, Xarel·lo, Riesling sec, Albariño. À éviter : rouge tannique (amer sur la panure), blanc boisé ou rond qui double le gras (n°19). Service : 8-10 °C (n°26). | D4: Entrée | E4: 24 | F4: =INDEX('Matrice des notes'!$B$6:$B$81,MATCH(G4,'Matrice des notes'!$F$6:$F$81,0)) -> L-B01 · IGP Val de Loire Sauvignon Le Petit Bourgeois 2024 | G4: =MAX('Matrice des notes'!$F$6:$F$81) -> 4
A5: Cuisses de grenouilles meunières à l'ail et au persil | B5: • n°1 · Les points d'ancrage • n°24 · La sauce et la cuisson priment sur la protéine • n°3 · Acidité ↔ gras • n°19 · Le bois couvre la finesse et amplifie l'amertume • n°20 · L'équilibre des intensités : le vin pèse autant que le plat • n°39 · L'élevage sur lies donne de la chair sans le bois | C5: Ancrages : cuisson meunière (beurre noisette), ail, persil, chair fine et délicate (n°1). Profil : blanc sec de poids moyen, acidité nette, sans bois (un élevage sur lies est bienvenu), jeune. La sauce et la cuisson priment : le beurre noisette demande une acidité qui coupe le gras et un peu de chair pour lui répondre, sans que le bois couvre la finesse de la chair (n°24, n°3, n°19, n°20, n°39). Cépages : Chardonnay non boisé, Chenin blanc, Pinot blanc, Sauvignon blanc, Grüner Veltliner. À éviter : blanc boisé, blanc musqué exubérant, rouge tannique (n°19). Service : 10-11 °C (n°26). | D5: Entrée | E5: 24 | F5: =INDEX('Matrice des notes'!$B$6:$B$81,MATCH(G5,'Matrice des notes'!$G$6:$G$81,0)) -> L-B03 · Pouilly-Fumé de Ladoucette 2024 | G5: =MAX('Matrice des notes'!$G$6:$G$81) -> 5
A6: Assiette d'huîtres Utah Beach n°3, pain, beurre, échalote, vinaigre – 6 pièces | B6: • n°1 · Les points d'ancrage • n°9 · Anchois et iodés salins ↔ acidité littorale • n°41 · Effervescents : le cépage et le dosage dictent la table • n°11 · Vinaigrette et moutarde franche ↔ incompatibles avec le vin • n°19 · Le bois couvre la finesse et amplifie l'amertume • n°35 · Un élément réfractaire plafonne l'accord | C6: Ancrages : iode et salinité de l'huître, vinaigre à l'échalote, beurre salé (n°1). Profil : blanc sec très tendu, salin, jeune, sans bois, idéalement de sols proches de la mer ; ou effervescent extra-brut / brut nature de style blanc de blancs. Le vinaigre à l'échalote est incompatible avec la plupart des vins : seul un vin très acide ou un effervescent peu dosé partage le terrain. Conseiller de l'utiliser avec parcimonie (n°9, n°41, n°11, n°19, n°35). Plafond : le vinaigre à l'échalote joue le rôle d'une vinaigrette, aucun vin ne dépasse 4 (n°35, n°11). Hypothèse : Sancerre « proche d'un fleuve » (n°9, question ouverte). Cépages : Chardonnay (effervescent blanc de blancs, peu dosé), Albariño, Assyrtiko, Picpoul, Sauvignon blanc. À éviter : blanc boisé ou rond, effervescent dosé, tout rouge (n°19). Service : 8-10 °C (n°26). | D6: Entrée | E6: 32 | F6: =INDEX('Matrice des notes'!$B$6:$B$81,MATCH(G6,'Matrice des notes'!$H$6:$H$81,0)) -> L-B01 · IGP Val de Loire Sauvignon Le Petit Bourgeois 2024 | G6: =MAX('Matrice des notes'!$H$6:$H$81) -> 4
A7: Belles moules au beurre à l'ail et aux herbes – 12 pièces | B7: • n°1 · Les points d'ancrage • n°3 · Acidité ↔ gras • n°9 · Anchois et iodés salins ↔ acidité littorale • n°19 · Le bois couvre la finesse et amplifie l'amertume • n°20 · L'équilibre des intensités : le vin pèse autant que le plat | C7: Ancrages : beurre persillé à l'ail (gras chaud), iode de la moule, herbes (n°1). Profil : blanc sec tendu, vif, salin, jeune, sans bois. L'acidité coupe le beurre, la salinité répond à l'iode. Plat de poids moyen : un blanc léger à moyen suffit (n°3, n°9, n°19, n°20). Hypothèse : les vins de Loire, Sancerre compris, comptent comme « proches d'un fleuve » (n°9, question ouverte). Cépages : Sauvignon blanc, Picpoul, Albariño, Vermentino, Aligoté. À éviter : blanc boisé, blanc musqué, rouge (n°19). Service : 8-10 °C (n°26). | D7: Entrée | E7: 28 | F7: =INDEX('Matrice des notes'!$B$6:$B$81,MATCH(G7,'Matrice des notes'!$I$6:$I$81,0)) -> L-B01 · IGP Val de Loire Sauvignon Le Petit Bourgeois 2024 | G7: =MAX('Matrice des notes'!$I$6:$I$81) -> 5
A8: Croquettes au fromage, persil frit – 1 pièce / 2 pièces | B8: • n°1 · Les points d'ancrage • n°34 · La friture appelle la bulle et l'acidité • n°5 · Le fromage repousse de facto le tanin • n°3 · Acidité ↔ gras | C8: Ancrages : friture croustillante, béchamel au fromage (gras, sel, umami), persil frit (n°1). Profil : effervescent brut de méthode traditionnelle ou blanc sec tendu, jeune, sans bois. La bulle et l'acidité coupent le gras de la friture et du fromage. Le fromage étant l'ingrédient principal, il repousse le tanin : pas de rouge (n°34, n°5, n°3). Fromage ingrédient principal : le n°5 s'applique pleinement, aucun rouge. Cépages : Chardonnay (effervescent), Chenin blanc, Riesling sec, Pinot blanc, Savagnin ouillé. À éviter : rouge tannique, blanc boisé ou rond (n°19, n°5). Service : 8-10 °C (n°26). | D8: Entrée | E8: 12 / 22 | F8: =INDEX('Matrice des notes'!$B$6:$B$81,MATCH(G8,'Matrice des notes'!$J$6:$J$81,0)) -> L-E02 · Champagne R de Ruinart Brut NM · 37,5 cl | G8: =MAX('Matrice des notes'!$J$6:$J$81) -> 5
A9: Croquettes aux crevettes grises, persil frit – 1 pièce / 2 pièces | B9: • n°1 · Les points d'ancrage • n°34 · La friture appelle la bulle et l'acidité • n°9 · Anchois et iodés salins ↔ acidité littorale • n°41 · Effervescents : le cépage et le dosage dictent la table • n°42 · Sans vin du terroir du plat, chercher le même climat | C9: Ancrages : friture croustillante, crevette grise (iode, douceur), béchamel (n°1). Profil : effervescent brut de style blanc de blancs ou blanc sec très tendu et salin, jeune, sans bois. La bulle nettoie la friture ; l'acidité et la salinité répondent à l'iode de la crevette (n°34, n°9, n°41, n°42). Terroir : cuisine de la mer du Nord sans vin du terroir du plat : chercher le même climat, un vin septentrional de climat frais, tendu (n°42). Cépages : Chardonnay (effervescent blanc de blancs), Riesling sec, Chenin blanc, Sauvignon blanc, Pinot blanc. À éviter : rouge tannique, blanc boisé ou rond (n°19). Service : 8-10 °C (n°26). | D9: Entrée | E9: 15 / 27 | F9: =INDEX('Matrice des notes'!$B$6:$B$81,MATCH(G9,'Matrice des notes'!$K$6:$K$81,0)) -> L-E02 · Champagne R de Ruinart Brut NM · 37,5 cl | G9: =MAX('Matrice des notes'!$K$6:$K$81) -> 5
A10: Escargots magnifiques de Bourgogne – 6 pièces | B10: • n°1 · Les points d'ancrage • n°2 · La résonance des sols et des terroirs • n°3 · Acidité ↔ gras • n°20 · L'équilibre des intensités : le vin pèse autant que le plat • n°29 · L'umami durcit le vin | C10: Ancrages : beurre d'escargot (ail, persil), chair terreuse et umami de l'escargot (n°1). Profil : blanc sec tendu de poids moyen, sans bois ou très peu, jeune ou légèrement patiné ; à défaut, rouge léger peu tannique. L'acidité coupe le beurre persillé ; un vin trop léger disparaîtrait derrière l'ail (n°2, n°3, n°20, n°29). Le n°2 ne vaut que si l'escargot vient bien de la région : à vérifier. Terroir : un vin issu de la même région que le produit, idéalement de sols calcaires (à confirmer : « de Bourgogne » peut désigner l'espèce d'escargot plutôt que son origine) (n°2). Cépages : Chardonnay non boisé, Aligoté, Pinot blanc, Sauvignon blanc ; en rouge : Pinot noir léger. À éviter : blanc boisé marqué, rouge tannique (n°19, n°29). Service : blanc 10-11 °C ; rouge léger 13-14 °C (n°26). | D10: Entrée | E10: 25 | F10: =INDEX('Matrice des notes'!$B$6:$B$81,MATCH(G10,'Matrice des notes'!$L$6:$L$81,0)) -> L-B05 · Petit Chablis Pas Si Petit 2023 | G10: =MAX('Matrice des notes'!$L$6:$L$81) -> 5
A11: Nems délicieux, salade, sauce aigre-douce | B11: • n°1 · Les points d'ancrage • n°22 · Le sucre du plat impose un vin au moins aussi sucré • n°34 · La friture appelle la bulle et l'acidité • n°23 · L'acidité du plat impose l'acidité du vin | C11: Ancrages : friture, sauce aigre-douce (sucre + vinaigre), herbes fraîches de la salade (n°1). Profil : blanc demi-sec aromatique, acidité vive, peu alcoolisé, sans bois ; ou effervescent demi-sec. Le sucre de la sauce impose un vin au moins aussi sucré, son vinaigre une acidité au moins égale ; la bulle ou l'acidité nettoie la friture (n°22, n°34, n°23). La carte n'a aucun vin demi-sec : le meilleur accord reste « correct » (n°22). Cépages : Riesling demi-sec, Chenin blanc demi-sec, Gewurztraminer, Muscat, Pinot gris. À éviter : rouge tannique, blanc sec maigre (paraît acide et dur), vin boisé ou alcooleux (n°19, n°22, n°20). Service : 8-10 °C (n°26). | D11: Entrée | E11: 22 | F11: =INDEX('Matrice des notes'!$B$6:$B$81,MATCH(G11,'Matrice des notes'!$M$6:$M$81,0)) -> L-E01 · Valdobbiadene Prosecco Superiore Col de l'Utia NM | G11: =MAX('Matrice des notes'!$M$6:$M$81) -> 3
A12: Fraîcheur de tourteau, sucrine, Granny Smith, mayonnaise curry | B12: • n°1 · Les points d'ancrage • n°23 · L'acidité du plat impose l'acidité du vin • n°6 · Plats épicés ↔ jamais de rouge jeune tannique • n°10 · Œufs : difficiles partout, sauf l'œuf en meurette • n°19 · Le bois couvre la finesse et amplifie l'amertume • n°9 · Anchois et iodés salins ↔ acidité littorale • n°31 · L'alcool attise le piment • n°35 · Un élément réfractaire plafonne l'accord | C12: Ancrages : chair sucrée du crabe, pomme verte acidulée, mayonnaise au curry (émulsion + épice) (n°1). Profil : blanc sec à acidité vive, légèrement aromatique, jeune, sans bois ; une pointe de sucre résiduel aide à envelopper le curry. La Granny Smith impose une acidité au moins égale ; l'épice exclut le rouge. La mayonnaise plafonne un peu l'accord (n°23, n°6, n°10, n°19, n°9, n°31). Plafond : la mayonnaise est une émulsion à l'œuf, aucun vin ne dépasse 4 (n°35, n°10, question ouverte). Cépages : Riesling (sec à demi-sec), Chenin blanc, Grüner Veltliner, Albariño, Pinot gris. À éviter : rouge, blanc boisé (couvre la finesse du crabe), vin alcooleux (n°19, n°6). Service : 8-10 °C (n°26). | D12: Entrée | E12: 34 | F12: =INDEX('Matrice des notes'!$B$6:$B$81,MATCH(G12,'Matrice des notes'!$N$6:$N$81,0)) -> L-B01 · IGP Val de Loire Sauvignon Le Petit Bourgeois 2024 | G12: =MAX('Matrice des notes'!$N$6:$N$81) -> 4
A13: Belle tranche de foie gras de canard, brioche toastée | B13: • n°1 · Les points d'ancrage • n°4 · Sucre ↔ sel : l'accord d'opposition classique • n°3 · Acidité ↔ gras • n°20 · L'équilibre des intensités : le vin pèse autant que le plat | C13: Ancrages : gras fondant, sel, brioche toastée (sucrée et grillée) (n°1). Profil : blanc moelleux à liquoreux (botrytisé ou vendanges tardives) à acidité vive ; jeune ou légèrement évolué. Le sucre du vin répond au sel du foie gras (opposition sucre ↔ sel) ; l'acidité coupe le gras et évite l'effet lourd. Alternative plus légère : un blanc demi-sec tendu (n°4, n°3, n°20). Le seul liquoreux de la carte est servi au verre (n°4). Cépages : Sémillon, Petit manseng, Chenin blanc, Riesling, Furmint. À éviter : rouge tannique, blanc sec maigre, liquoreux lourd sans acidité (n°20). Service : 8-10 °C (n°26). | D13: Entrée | E13: 29 | F13: =INDEX('Matrice des notes'!$B$6:$B$81,MATCH(G13,'Matrice des notes'!$O$6:$O$81,0)) -> L-D01 · Sauternes Château Lange-Réglat (au verre) | G13: =MAX('Matrice des notes'!$O$6:$O$81) -> 5
A14: Ravioles de homard, bisque crémeuse | B14: • n°1 · Les points d'ancrage • n°24 · La sauce et la cuisson priment sur la protéine • n°39 · L'élevage sur lies donne de la chair sans le bois • n°20 · L'équilibre des intensités : le vin pèse autant que le plat • n°3 · Acidité ↔ gras • n°41 · Effervescents : le cépage et le dosage dictent la table | C14: Ancrages : bisque crémeuse (crustacé réduit, crème, notes torréfiées), chair du homard, pâte (n°1). Profil : blanc sec ample, élevé sur lies, acidité nette, bois discret ou absent ; ou effervescent vineux à dominante pinot noir / pinot meunier. La sauce prime : sa crème demande une acidité qui la coupe et une chair qui répond à son poids (n°24, n°39, n°20, n°3, n°41). Cépages : Chardonnay élevé sur lies, Chenin blanc, Roussanne ; en effervescent : Pinot noir, Pinot meunier. À éviter : blanc maigre (écrasé par la bisque), bois neuf marqué, rouge tannique (n°19, n°20). Service : 11-12 °C (n°26). | D14: Entrée | E14: 28 | F14: =INDEX('Matrice des notes'!$B$6:$B$81,MATCH(G14,'Matrice des notes'!$P$6:$P$81,0)) -> L-B03 · Pouilly-Fumé de Ladoucette 2024 | G14: =MAX('Matrice des notes'!$P$6:$P$81) -> 5
A15: Filet de bar rôti, légumes de saison, purée, sauce vierge | B15: • n°1 · Les points d'ancrage • n°24 · La sauce et la cuisson priment sur la protéine • n°23 · L'acidité du plat impose l'acidité du vin • n°27 · Rouge et poisson : possible si le poisson est charnu et le rouge peu tannique • n°25 · L'accord de miroir : faire résonner un arôme commun • n°35 · Un élément réfractaire plafonne l'accord • n°11 · Vinaigrette et moutarde franche ↔ incompatibles avec le vin | C15: Ancrages : bar rôti (peau croustillante), sauce vierge (huile d'olive, tomate, citron, herbes) (n°1). Profil : blanc sec tendu, aux notes d'herbes, jeune, sans bois. La sauce vierge prime : tomate et citron imposent une acidité au moins égale. Le bar rôti étant charnu, un rouge très léger, peu tannique et servi frais est possible (n°24, n°23, n°27, n°25, n°35, n°11). Plafond : la sauce vierge est acidulée au citron, rattachée au n°11 (question ouverte) ; aucun vin ne dépasse 4 (n°35). Cépages : Vermentino, Sauvignon blanc, Assyrtiko, Albariño ; en rouge : Pinot noir léger. À éviter : tanin appuyé (métallique sur la tomate et la chair iodée), blanc boisé (n°19). Service : blanc 8-10 °C ; rouge léger 13-14 °C (n°26). | D15: Plat principal | E15: 36 | F15: =INDEX('Matrice des notes'!$B$6:$B$81,MATCH(G15,'Matrice des notes'!$Q$6:$Q$81,0)) -> L-B01 · IGP Val de Loire Sauvignon Le Petit Bourgeois 2024 | G15: =MAX('Matrice des notes'!$Q$6:$Q$81) -> 4
A16: Tataki de thon, broccolini, riz aux saveurs d'Asie | B16: • n°1 · Les points d'ancrage • n°27 · Rouge et poisson : possible si le poisson est charnu et le rouge peu tannique • n°29 · L'umami durcit le vin • n°30 · L'amertume du plat s'additionne à celle du vin • n°24 · La sauce et la cuisson priment sur la protéine • n°26 · La température de service modifie l'accord | C16: Ancrages : thon saisi à cœur cru (chair rouge), marinade de type soja / sésame / gingembre (umami), amertume du broccolini (n°1). Profil : rouge léger, fruité, peu tannique, jeune, sans bois, servi frais ; ou blanc aromatique sec. Le thon charnu accepte le rouge si le tanin est discret ; l'umami et l'amertume du broccolini durciraient un tanin appuyé (n°27, n°29, n°30, n°24, n°26). Cépages : Pinot noir, Gamay, Frappato, Zweigelt ; en blanc : Riesling sec. À éviter : rouge jeune tannique ou boisé ; vin alcooleux si le riz est pimenté (n°19, n°27). Service : rouge léger 13-14 °C ; blanc 8-10 °C (n°26). | D16: Plat principal | E16: 37 | F16: =INDEX('Matrice des notes'!$B$6:$B$81,MATCH(G16,'Matrice des notes'!$R$6:$R$81,0)) -> L-R01 · Chiroubles Domaine Piron 2024 | G16: =MAX('Matrice des notes'!$R$6:$R$81) -> 5
A17: Cabillaud, crevettes grises, purée, sauce mousseline | B17: • n°1 · Les points d'ancrage • n°24 · La sauce et la cuisson priment sur la protéine • n°39 · L'élevage sur lies donne de la chair sans le bois • n°10 · Œufs : difficiles partout, sauf l'œuf en meurette • n°42 · Sans vin du terroir du plat, chercher le même climat • n°3 · Acidité ↔ gras • n°35 · Un élément réfractaire plafonne l'accord | C17: Ancrages : sauce mousseline (émulsion beurre-œuf, crème fouettée, citron), cabillaud nacré, crevettes grises iodées (n°1). Profil : blanc sec de poids moyen, élevé sur lies, acidité nette, sans bois ou très discret. La sauce prime : l'élevage sur lies donne la chair qui répond à la mousseline, l'acidité la coupe. L'émulsion à l'œuf plafonne légèrement l'accord (n°24, n°39, n°10, n°42, n°3, n°35). Plafond : la mousseline est une émulsion beurre-œuf-citron, aucun vin ne dépasse 4 (n°35, n°10, question ouverte). Terroir : cuisine de la mer du Nord sans vin du terroir du plat : chercher le même climat, un vin septentrional de climat frais, tendu (n°42). Cépages : Chardonnay élevé sur lies, Chenin blanc, Pinot blanc, Riesling sec, Auxerrois. À éviter : bois neuf, blanc maigre, rouge (n°19, n°20). Service : 10-12 °C (n°26). | D17: Plat principal | E17: 42 | F17: =INDEX('Matrice des notes'!$B$6:$B$81,MATCH(G17,'Matrice des notes'!$S$6:$S$81,0)) -> L-B01 · IGP Val de Loire Sauvignon Le Petit Bourgeois 2024 | G17: =MAX('Matrice des notes'!$S$6:$S$81) -> 4
A18: Solettes meunière, épinards, purée | B18: • n°1 · Les points d'ancrage • n°24 · La sauce et la cuisson priment sur la protéine • n°3 · Acidité ↔ gras • n°19 · Le bois couvre la finesse et amplifie l'amertume • n°42 · Sans vin du terroir du plat, chercher le même climat • n°39 · L'élevage sur lies donne de la chair sans le bois • n°11 · Vinaigrette et moutarde franche ↔ incompatibles avec le vin | C18: Ancrages : cuisson meunière (beurre noisette, citron), chair fine de la sole, épinards (n°1). Profil : blanc sec fin et tendu, jeune, sans bois ; un léger gras (élevage sur lies) est bienvenu. L'acidité coupe le beurre noisette ; aucun bois pour préserver la finesse de la sole (n°24, n°3, n°19, n°42, n°39, n°11). Le trait de citron de la meunière est traité comme un assaisonnement, pas comme une sauce acidulée au sens du n°11 (hypothèse). Terroir : cuisine de la mer du Nord sans vin du terroir du plat : chercher le même climat, un vin septentrional de climat frais, tendu (n°42). Cépages : Chardonnay non boisé, Chenin blanc, Riesling sec, Sauvignon blanc, Pinot blanc. À éviter : blanc boisé, blanc aromatique exubérant, rouge (n°19). Service : 10-11 °C (n°26). | D18: Plat principal | E18: 45 | F18: =INDEX('Matrice des notes'!$B$6:$B$81,MATCH(G18,'Matrice des notes'!$T$6:$T$81,0)) -> L-B01 · IGP Val de Loire Sauvignon Le Petit Bourgeois 2024 | G18: =MAX('Matrice des notes'!$T$6:$T$81) -> 5
A19: Tartare de thon façon Américain, frites et salade | B19: • n°1 · Les points d'ancrage • n°23 · L'acidité du plat impose l'acidité du vin • n°10 · Œufs : difficiles partout, sauf l'œuf en meurette • n°27 · Rouge et poisson : possible si le poisson est charnu et le rouge peu tannique • n°36 · Les garnitures neutres ne sont pas des points d'ancrage • n°35 · Un élément réfractaire plafonne l'accord | C19: Ancrages : thon cru, sauce façon américain (mayonnaise, câpres, cornichons, condiments). Frites et salade : garnitures neutres (n°1, n°36). Profil : blanc sec très tendu, jeune, sans bois ; ou rosé sec. Câpres et cornichons imposent une acidité au moins égale ; la base mayonnaise plafonne un peu l'accord. Le rouge n'est envisageable que très léger et peu tannique. Servir la vinaigrette de la salade à part ou légère (n°23, n°10, n°27, n°35). Plafond : la base mayonnaise plafonne l'accord à 4 (n°35, n°10, question ouverte). Cépages : Sauvignon blanc, Grüner Veltliner, Albariño, Riesling sec ; en rosé : Grenache. À éviter : rouge tannique (métallique sur le thon cru), blanc boisé (n°19, n°27). Service : 8-10 °C (n°26). | D19: Plat principal | E19: 38 | F19: =INDEX('Matrice des notes'!$B$6:$B$81,MATCH(G19,'Matrice des notes'!$U$6:$U$81,0)) -> L-B01 · IGP Val de Loire Sauvignon Le Petit Bourgeois 2024 | G19: =MAX('Matrice des notes'!$U$6:$U$81) -> 4
A20: Risotto aux champignons des bois, parmesan | B20: • n°1 · Les points d'ancrage • n°25 · L'accord de miroir : faire résonner un arôme commun • n°29 · L'umami durcit le vin • n°40 · L'âge du vin oriente le plat • n°39 · L'élevage sur lies donne de la chair sans le bois • n°37 · Le fromage accessoire ne dicte pas seul l'accord | C20: Ancrages : champignons des bois (sous-bois, umami), parmesan, onctuosité du risotto (n°1). Profil : rouge évolué aux tanins fondus et notes tertiaires de sous-bois (accord de miroir) ; ou blanc ample élevé sur lies, légèrement patiné. L'umami des champignons et du parmesan durcit un rouge jeune : il faut un vin patiné (n°25, n°29, n°40, n°39, n°37). Parmesan minoritaire : le n°37 s'applique, seul le rouge jeune et tannique est exclu. Cépages : Pinot noir patiné, Nebbiolo évolué, Sangiovese évolué ; en blanc : Chardonnay élevé sur lies, Savagnin ouillé. À éviter : rouge jeune tannique, blanc maigre (n°29, n°20). Service : rouge évolué 14-16 °C ; blanc 11-12 °C (n°26). | D20: Plat principal | E20: 36 | F20: =INDEX('Matrice des notes'!$B$6:$B$81,MATCH(G20,'Matrice des notes'!$V$6:$V$81,0)) -> L-B08 · Puligny-Montrachet 1er Cru Champ Gain 2019 | G20: =MAX('Matrice des notes'!$V$6:$V$81) -> 5
A21: Belle assiette de légumes du marché laqués au miso | B21: • n°1 · Les points d'ancrage • n°29 · L'umami durcit le vin • n°22 · Le sucre du plat impose un vin au moins aussi sucré • n°14 · notes caramélisées - richesse alcoolique • n°30 · L'amertume du plat s'additionne à celle du vin • n°25 · L'accord de miroir : faire résonner un arôme commun | C21: Ancrages : laque au miso (umami salé-sucré, caramélisation), légumes de saison (amertume possible) (n°1). Profil : blanc rond, aromatique, avec une pointe de sucre et une acidité vive ; ou vin sec élevé sous voile, qui répond à l'umami. La laque sucrée impose un vin au moins aussi sucré ; ses notes caramélisées aiment une certaine richesse alcoolique ; l'umami et l'amertume excluent le rouge tannique (n°29, n°22, n°14, n°30, n°25). La carte n'a ni vin demi-sec ni vin sous voile complet : le meilleur accord reste « correct » (n°22). Cépages : Riesling demi-sec, Pinot gris, Chenin blanc, Gewurztraminer, Savagnin (sous voile). À éviter : rouge jeune tannique, blanc sec maigre (n°29, n°22, n°20). Service : 10-12 °C (n°26). | D21: Plat principal | E21: 30 | F21: =INDEX('Matrice des notes'!$B$6:$B$81,MATCH(G21,'Matrice des notes'!$W$6:$W$81,0)) -> L-B14 · Châteauneuf-du-Pape blanc Renaissance 2024 | G21: =MAX('Matrice des notes'!$W$6:$W$81) -> 3
A22: Tagliolini, beurre sauge, citron et parmesan | B22: • n°1 · Les points d'ancrage • n°3 · Acidité ↔ gras • n°23 · L'acidité du plat impose l'acidité du vin • n°25 · L'accord de miroir : faire résonner un arôme commun • n°20 · L'équilibre des intensités : le vin pèse autant que le plat • n°35 · Un élément réfractaire plafonne l'accord • n°11 · Vinaigrette et moutarde franche ↔ incompatibles avec le vin • n°37 · Le fromage accessoire ne dicte pas seul l'accord | C22: Ancrages : beurre à la sauge, citron, parmesan ; les pâtes sont neutres (n°1, n°36). Profil : blanc sec léger à moyen, acidité vive, légèrement herbacé, sans bois. L'acidité coupe le beurre et doit égaler celle du citron ; les notes herbacées du vin font miroir à la sauge (n°3, n°23, n°25, n°20, n°35, n°11). Plafond : sauce acidulée au citron rattachée au n°11 (question ouverte) ; aucun vin ne dépasse 4 (n°35). Parmesan minoritaire (n°37). Cépages : Vermentino, Sauvignon blanc, Garganega, Fiano, Chenin blanc. À éviter : blanc boisé ou lourd, rouge tannique (n°19, n°20). Service : 9-11 °C (n°26). | D22: Plat principal | E22: 26 | F22: =INDEX('Matrice des notes'!$B$6:$B$81,MATCH(G22,'Matrice des notes'!$X$6:$X$81,0)) -> L-B01 · IGP Val de Loire Sauvignon Le Petit Bourgeois 2024 | G22: =MAX('Matrice des notes'!$X$6:$X$81) -> 4
A23: Volaille, sauce morilles, chiconettes, purée | B23: • n°1 · Les points d'ancrage • n°25 · L'accord de miroir : faire résonner un arôme commun • n°39 · L'élevage sur lies donne de la chair sans le bois • n°30 · L'amertume du plat s'additionne à celle du vin • n°19 · Le bois couvre la finesse et amplifie l'amertume • n°41 · Effervescents : le cépage et le dosage dictent la table | C23: Ancrages : sauce crémée aux morilles (sous-bois, umami), amertume des chiconettes, volaille (n°1). Profil : blanc ample élevé sur lies, légèrement patiné ; un bois fondu est acceptable sur ce plat riche et crémé. Alternative : vin sec élevé sous voile (miroir des morilles) ou rouge léger évolué peu tannique. L'amertume des chiconettes exclut le tanin appuyé (n°25, n°39, n°30, n°19, n°41). Cépages : Chardonnay (sur lies, bois fondu), Savagnin, Chenin blanc, Roussanne ; en rouge : Pinot noir évolué. À éviter : rouge tannique (amertume du chicon + tanin), blanc maigre (n°30, n°20). Service : blanc 11-12 °C ; rouge léger 13-14 °C (n°26). | D23: Plat principal | E23: 39 | F23: =INDEX('Matrice des notes'!$B$6:$B$81,MATCH(G23,'Matrice des notes'!$Y$6:$Y$81,0)) -> L-B08 · Puligny-Montrachet 1er Cru Champ Gain 2019 | G23: =MAX('Matrice des notes'!$Y$6:$Y$81) -> 5
A24: Vol-au-vent volaille et ris de veau, mousseline, frites | B24: • n°1 · Les points d'ancrage • n°39 · L'élevage sur lies donne de la chair sans le bois • n°41 · Effervescents : le cépage et le dosage dictent la table • n°42 · Sans vin du terroir du plat, chercher le même climat | C24: Ancrages : sauce blanche crémée (volaille, champignons), feuilletage beurré, ris de veau fondant. Frites et mousseline : garnitures neutres (si « mousseline » désigne la purée) (n°1, n°36). Profil : blanc sec ample élevé sur lies, acidité nette, bois discret ou absent ; ou effervescent vineux à dominante pinot noir / pinot meunier, taillé pour les plats de brasserie. La crème appelle chair et acidité (n°39, n°41, n°42). Terroir : cuisine de la mer du Nord sans vin du terroir du plat : chercher le même climat, un vin septentrional de climat frais, tendu (n°42). Cépages : Chardonnay élevé sur lies, Chenin blanc, Pinot blanc ; en effervescent : Pinot meunier, Pinot noir. À éviter : rouge tannique, blanc maigre (n°20). Service : 10-12 °C (n°26). | D24: Plat principal | E24: 39 | F24: =INDEX('Matrice des notes'!$B$6:$B$81,MATCH(G24,'Matrice des notes'!$Z$6:$Z$81,0)) -> L-B03 · Pouilly-Fumé de Ladoucette 2024 | G24: =MAX('Matrice des notes'!$Z$6:$Z$81) -> 5
A25: Ris de veau laqué, garniture automnale, purée | B25: • n°1 · Les points d'ancrage • n°24 · La sauce et la cuisson priment sur la protéine • n°14 · notes caramélisées - richesse alcoolique • n°40 · L'âge du vin oriente le plat • n°19 · Le bois couvre la finesse et amplifie l'amertume | C25: Ancrages : laquage (jus réduit, brillant, caramélisé), texture fondante du ris de veau, garniture automnale (n°1, n°36). Profil : rouge souple, légèrement évolué, tanins fondus, avec une richesse alcoolique qui développe les notes caramélisées de la laque ; bois fondu possible. Alternative : blanc riche élevé en fût, patiné. Viande blanche fondante : pas de tanin appuyé (n°24, n°14, n°40, n°19). Cépages : Pinot noir, Grenache, Mencía, Nebbiolo évolué ; en blanc : Chardonnay élevé. À éviter : rouge jeune tannique, blanc maigre (n°20). Service : rouge 14-16 °C ; blanc 11-12 °C (n°26). | D25: Plat principal | E25: 46 | F25: =INDEX('Matrice des notes'!$B$6:$B$81,MATCH(G25,'Matrice des notes'!$AA$6:$AA$81,0)) -> L-R03 · Moulin-à-Vent Les Michelons 2014 | G25: =MAX('Matrice des notes'!$AA$6:$AA$81) -> 5
A26: Tartare de bœuf préparé minute, frites | B26: • n°1 · Les points d'ancrage • n°23 · L'acidité du plat impose l'acidité du vin • n°21 · Le tanin aime le gras et le saignant de la viande rouge • n°10 · Œufs : difficiles partout, sauf l'œuf en meurette • n°36 · Les garnitures neutres ne sont pas des points d'ancrage • n°35 · Un élément réfractaire plafonne l'accord | C26: Ancrages : bœuf cru maigre, assaisonnement (câpres, cornichons, échalote, émulsion à l'œuf, condiments). Frites : garniture neutre (n°1, n°36). Profil : rouge juteux, jeune, tanins fins, acidité vive, sans bois marqué, servi frais ; ou rosé sec de structure. Les condiments acides imposent une acidité au moins égale ; la viande crue et maigre demande des tanins fins, pas un rouge structuré. L'émulsion plafonne légèrement l'accord (n°23, n°21, n°10, n°35). Plafond : l'émulsion à l'œuf de l'assaisonnement plafonne l'accord à 4 (n°35, n°10, question ouverte). Cépages : Gamay, Pinot noir, Cabernet franc, Barbera, Blaufränkisch. À éviter : rouge puissant, tannique ou boisé ; vin alcooleux si l'assaisonnement est pimenté (n°19, n°21). Service : 13-14 °C (n°26). | D26: Plat principal | E26: 29 | F26: =INDEX('Matrice des notes'!$B$6:$B$81,MATCH(G26,'Matrice des notes'!$AB$6:$AB$81,0)) -> L-R01 · Chiroubles Domaine Piron 2024 | G26: =MAX('Matrice des notes'!$AB$6:$AB$81) -> 4
A27: Filet pur de bœuf Simmental, sauce poivre vert, frites et salade | B27: • n°1 · Les points d'ancrage • n°13 · Poivre + viande ↔ tanins fondus et trame acide • n°21 · Le tanin aime le gras et le saignant de la viande rouge • n°24 · La sauce et la cuisson priment sur la protéine • n°25 · L'accord de miroir : faire résonner un arôme commun • n°43 · Aérer le rouge jeune avant de juger l'accord | C27: Ancrages : sauce au poivre vert (piquant, crème), filet saignant tendre et maigre (n°1). Profil : rouge structuré aux tanins fondus et à la trame acide, légèrement évolué, bois fondu. Le poivre demande des tanins fondus et de l'acidité pour faire le pont entre le gras de la sauce et le piquant ; le filet, maigre, préfère des tanins fins à un rouge massif (n°13, n°21, n°24, n°25, n°43). Cépages : Syrah, Pinot noir évolué, Nebbiolo, Tempranillo, Grenache. À éviter : rouge jeune très tannique (durci par le poivre), blanc (n°13). Service : 16-17 °C ; carafer 1 h si le vin est jeune (n°26, n°43). | D27: Plat principal | E27: 44 | F27: =INDEX('Matrice des notes'!$B$6:$B$81,MATCH(G27,'Matrice des notes'!$AC$6:$AC$81,0)) -> L-R03 · Moulin-à-Vent Les Michelons 2014 | G27: =MAX('Matrice des notes'!$AC$6:$AC$81) -> 5
A28: Filet pur de bœuf Simmental, sauce morilles, frites et salade | B28: • n°1 · Les points d'ancrage • n°25 · L'accord de miroir : faire résonner un arôme commun • n°40 · L'âge du vin oriente le plat • n°29 · L'umami durcit le vin • n°43 · Aérer le rouge jeune avant de juger l'accord | C28: Ancrages : sauce crémée aux morilles (sous-bois, umami), filet saignant tendre (n°1). Profil : rouge évolué aux tanins fondus et notes tertiaires (sous-bois, champignon), en miroir des morilles ; bois fondu. L'umami des morilles durcit un rouge jeune. Alternative : blanc ample patiné (n°25, n°40, n°29, n°43). Cépages : Pinot noir évolué, Nebbiolo évolué, Sangiovese évolué, Tempranillo patiné ; en blanc : Chardonnay patiné. À éviter : rouge jeune tannique, vin très boisé (n°19, n°29). Service : 15-16 °C ; décanter brièvement (n°26, n°43). | D28: Plat principal | E28: 44 | F28: =INDEX('Matrice des notes'!$B$6:$B$81,MATCH(G28,'Matrice des notes'!$AD$6:$AD$81,0)) -> L-R03 · Moulin-à-Vent Les Michelons 2014 | G28: =MAX('Matrice des notes'!$AD$6:$AD$81) -> 5
A29: Filet pur de bœuf Simmental, sauce béarnaise, frites et salade | B29: • n°1 · Les points d'ancrage • n°24 · La sauce et la cuisson priment sur la protéine • n°3 · Acidité ↔ gras • n°10 · Œufs : difficiles partout, sauf l'œuf en meurette • n°21 · Le tanin aime le gras et le saignant de la viande rouge • n°35 · Un élément réfractaire plafonne l'accord | C29: Ancrages : sauce béarnaise (émulsion beurre-œuf, estragon, réduction vinaigrée), filet saignant tendre (n°1). Profil : rouge à trame acide vive, tanins souples, fruité, jeune à mi-évolué. L'acidité coupe le beurre de la béarnaise et répond à sa réduction vinaigrée ; l'émulsion à l'œuf durcit un tanin appuyé : tanins fins (n°24, n°3, n°10, n°21, n°35). Plafond : la béarnaise est une émulsion beurre-œuf, aucun vin ne dépasse 4 (n°35, n°10, question ouverte). Cépages : Cabernet franc, Pinot noir, Gamay, Blaufränkisch, Barbera. À éviter : rouge très tannique ou très boisé, rouge mou peu acide (n°19, n°21). Service : 14-16 °C (n°26). | D29: Plat principal | E29: 44 | F29: =INDEX('Matrice des notes'!$B$6:$B$81,MATCH(G29,'Matrice des notes'!$AE$6:$AE$81,0)) -> L-R01 · Chiroubles Domaine Piron 2024 | G29: =MAX('Matrice des notes'!$AE$6:$AE$81) -> 4
A30: Crème brûlée à la vanille de Madagascar | B30: • n°1 · Les points d'ancrage • n°22 · Le sucre du plat impose un vin au moins aussi sucré • n°14 · notes caramélisées - richesse alcoolique • n°25 · L'accord de miroir : faire résonner un arôme commun | C30: Ancrages : croûte caramélisée, crème vanillée, sucre (n°1). Profil : blanc liquoreux botrytisé ou vendanges tardives, acidité vive, notes d'abricot et de vanille ; un élevage en fût fait miroir à la vanille. Le vin doit être au moins aussi sucré que le dessert et porter une richesse alcoolique pour développer le caramel (n°22, n°14, n°25). Cépages : Sémillon, Chenin blanc, Petit manseng, Furmint, Muscat. À éviter : vin sec, effervescent brut, rouge (n°22). Service : 8-10 °C (n°26). | D30: Dessert | E30: 13 | F30: =INDEX('Matrice des notes'!$B$6:$B$81,MATCH(G30,'Matrice des notes'!$AF$6:$AF$81,0)) -> L-D01 · Sauternes Château Lange-Réglat (au verre) | G30: =MAX('Matrice des notes'!$AF$6:$AF$81) -> 5
A31: Traditionnelle dame blanche | B31: • n°1 · Les points d'ancrage • n°15 · Chocolat noir ↔ VDN par opposition • n°22 · Le sucre du plat impose un vin au moins aussi sucré • n°20 · L'équilibre des intensités : le vin pèse autant que le plat | C31: Ancrages : sauce au chocolat chaud, glace vanille (froid), chantilly (n°1). Profil : vin muté, rouge (fruit noir, cacao) ou oxydatif. L'amertume du chocolat trouve son opposition dans un muté ; le sucre du vin doit égaler celui du dessert. Le froid de la glace atténue les arômes : un vin expressif est préférable (n°15, n°22, n°20). La carte n'a aucun vin muté : pas d'accord au-delà de « médiocre » (n°15). Cépages : Grenache (muté), Touriga nacional (muté), Pedro Ximénez, Muscat (muté), Malvasia (mutée). À éviter : vin sec, effervescent brut, rouge tannique non muté (n°22). Service : 14-16 °C (n°26). | D31: Dessert | E31: 13 | F31: =INDEX('Matrice des notes'!$B$6:$B$81,MATCH(G31,'Matrice des notes'!$AG$6:$AG$81,0)) -> L-D01 · Sauternes Château Lange-Réglat (au verre) | G31: =MAX('Matrice des notes'!$AG$6:$AG$81) -> 2
A32: Moelleux au chocolat 70 %, glace vanille de Madagascar | B32: • n°1 · Les points d'ancrage • n°15 · Chocolat noir ↔ VDN par opposition • n°22 · Le sucre du plat impose un vin au moins aussi sucré • n°20 · L'équilibre des intensités : le vin pèse autant que le plat | C32: Ancrages : chocolat noir 70 % (amertume, cacao), cœur coulant, glace vanille (n°1). Profil : vin rouge muté, jeune et fruité ou légèrement oxydatif, de belle puissance. Accord d'opposition : amertume du cacao contre amertume de noix du muté, sucre du vin compensant la charge cacaotée. Dessert intense : vin intense (n°15, n°22, n°20). La carte n'a aucun vin muté : pas d'accord au-delà de « médiocre » (n°15). Cépages : Grenache (muté), Touriga nacional (muté), Pedro Ximénez, Muscat (muté), Tinta roriz (muté). À éviter : vin sec, effervescent brut, liquoreux blanc léger (écrasé) (n°22). Service : 14-16 °C (n°26). | D32: Dessert | E32: 14 | F32: =INDEX('Matrice des notes'!$B$6:$B$81,MATCH(G32,'Matrice des notes'!$AH$6:$AH$81,0)) -> L-D01 · Sauternes Château Lange-Réglat (au verre) | G32: =MAX('Matrice des notes'!$AH$6:$AH$81) -> 2
A33: Café glacé | B33: • n°1 · Les points d'ancrage • n°22 · Le sucre du plat impose un vin au moins aussi sucré • n°25 · L'accord de miroir : faire résonner un arôme commun • n°20 · L'équilibre des intensités : le vin pèse autant que le plat | C33: Ancrages : glace au café (torréfaction, amertume), chantilly, sucre (n°1). Profil : vin muté ou doux oxydatif, élevé longtemps, aux notes de café, noix et caramel (accord de miroir avec la torréfaction). Le sucre du vin doit égaler celui de la glace (n°22, n°25, n°20). La carte n'a aucun vin doux oxydatif ni muté (n°22). Cépages : Pedro Ximénez, Grenache (muté, style oxydatif), Malvasia (muté), Touriga nacional. À éviter : vin sec, effervescent, blanc liquoreux trop léger (n°22). Service : 12-14 °C (n°26). | D33: Dessert | E33: 12 | F33: =INDEX('Matrice des notes'!$B$6:$B$81,MATCH(G33,'Matrice des notes'!$AI$6:$AI$81,0)) -> L-D01 · Sauternes Château Lange-Réglat (au verre) | G33: =MAX('Matrice des notes'!$AI$6:$AI$81) -> 2
A34: Duo de sorbets de saison | B34: • n°1 · Les points d'ancrage • n°22 · Le sucre du plat impose un vin au moins aussi sucré • n°7 · Agrumes seuls = incompatibles, agrumes adoucis = possibles • n°20 · L'équilibre des intensités : le vin pèse autant que le plat | C34: Ancrages : fruit, acidité, froid, sucre (parfums non précisés) (n°1). Profil : effervescent doux, sucré-acidulé et peu alcoolisé, ou blanc moelleux léger et aromatique. Le vin doit être au moins aussi sucré que le sorbet ; si un parfum d'agrume est proposé, c'est le sucre du sorbet qui rend l'accord possible. Dessert léger : vin léger (n°22, n°7, n°20). Cépages : Muscat (effervescent doux), Chenin blanc (demi-sec), Riesling doux, Malvasia, Gewurztraminer. À éviter : vin sec, effervescent brut, rouge (n°22). Service : 8-10 °C (n°26). | D34: Dessert | E34: 12 | F34: =INDEX('Matrice des notes'!$B$6:$B$81,MATCH(G34,'Matrice des notes'!$AJ$6:$AJ$81,0)) -> L-D01 · Sauternes Château Lange-Réglat (au verre) | G34: =MAX('Matrice des notes'!$AJ$6:$AJ$81) -> 3
A35: Île flottante, crème vanille, amandes caramélisées | B35: • n°1 · Les points d'ancrage • n°22 · Le sucre du plat impose un vin au moins aussi sucré • n°14 · notes caramélisées - richesse alcoolique • n°25 · L'accord de miroir : faire résonner un arôme commun • n°20 · L'équilibre des intensités : le vin pèse autant que le plat | C35: Ancrages : crème anglaise vanillée, meringue aérienne, amandes caramélisées (n°1). Profil : blanc doux léger (vendanges tardives) ou muté blanc, notes de miel et d'amande. Le vin doit égaler le sucre de la crème ; ses notes d'amande font miroir aux amandes caramélisées, qu'une certaine richesse alcoolique met en valeur (n°22, n°14, n°25, n°20). Cépages : Muscat, Chenin blanc, Sémillon, Petit manseng, Malvasia. À éviter : vin sec, effervescent brut, rouge (n°22). Service : 8-10 °C (n°26). | D35: Dessert | E35: 13 | F35: =INDEX('Matrice des notes'!$B$6:$B$81,MATCH(G35,'Matrice des notes'!$AK$6:$AK$81,0)) -> L-D01 · Sauternes Château Lange-Réglat (au verre) | G35: =MAX('Matrice des notes'!$AK$6:$AK$81) -> 4
A36: Crumble de pommes caramélisées, glace vanille de Madagascar | B36: • n°1 · Les points d'ancrage • n°22 · Le sucre du plat impose un vin au moins aussi sucré • n°14 · notes caramélisées - richesse alcoolique • n°25 · L'accord de miroir : faire résonner un arôme commun • n°23 · L'acidité du plat impose l'acidité du vin | C36: Ancrages : pomme caramélisée (sucre et acidité), pâte beurrée croustillante, glace vanille (n°1). Profil : blanc liquoreux ou vendanges tardives, acidité vive, notes de pomme cuite et de coing (accord de miroir), richesse alcoolique qui développe le caramel. Le vin doit être au moins aussi sucré que le dessert (n°22, n°14, n°25, n°23). Cépages : Chenin blanc, Sémillon, Riesling (vendanges tardives), Furmint, Petit manseng. À éviter : vin sec, effervescent brut, rouge (n°22). Service : 8-10 °C (n°26). | D36: Dessert | E36: 15 | F36: =INDEX('Matrice des notes'!$B$6:$B$81,MATCH(G36,'Matrice des notes'!$AL$6:$AL$81,0)) -> L-D01 · Sauternes Château Lange-Réglat (au verre) | G36: =MAX('Matrice des notes'!$AL$6:$AL$81) -> 4
A37: Profiterole glace pistache, sauce Gianduja | B37: • n°1 · Les points d'ancrage • n°15 · Chocolat noir ↔ VDN par opposition • n°22 · Le sucre du plat impose un vin au moins aussi sucré • n°25 · L'accord de miroir : faire résonner un arôme commun | C37: Ancrages : sauce gianduja (chocolat et noisette), glace pistache, pâte à choux (n°1). Profil : vin muté oxydatif, élevé longtemps, aux notes de noisette, noix et caramel (miroir du gianduja) ; ou muté rouge tuilé. Le gianduja, moins amer qu'un chocolat noir, accepte un muté plus évolué ; le sucre du vin doit égaler celui du dessert (n°15, n°22, n°25). La carte n'a aucun vin muté oxydatif (n°15). Cépages : Grenache (muté tuilé), Malvasia (muté), Pedro Ximénez, Muscat, Touriga nacional. À éviter : vin sec, effervescent brut, rouge jeune non muté (n°22). Service : 12-14 °C (n°26). | D37: Dessert | E37: 14 | F37: =INDEX('Matrice des notes'!$B$6:$B$81,MATCH(G37,'Matrice des notes'!$AM$6:$AM$81,0)) -> L-D01 · Sauternes Château Lange-Réglat (au verre) | G37: =MAX('Matrice des notes'!$AM$6:$AM$81) -> 2
A38: Mille-feuille, crème pâtissière pralinée | B38: • n°1 · Les points d'ancrage • n°22 · Le sucre du plat impose un vin au moins aussi sucré • n°14 · notes caramélisées - richesse alcoolique • n°25 · L'accord de miroir : faire résonner un arôme commun | C38: Ancrages : praliné (noisette caramélisée), feuilletage beurré, crème pâtissière (n°1). Profil : blanc moelleux légèrement patiné ou vin doux oxydatif, notes de fruits secs et de caramel en miroir du praliné, richesse alcoolique modérée. Le vin doit égaler le sucre de la crème ; le feuilletage aime une acidité fraîche (n°22, n°14, n°25). Cépages : Chenin blanc (moelleux), Sémillon, Malvasia, Muscat, Pedro Ximénez. À éviter : vin sec, effervescent brut, rouge (n°22). Service : 10-12 °C (n°26). | D38: Dessert | E38: 16 | F38: =INDEX('Matrice des notes'!$B$6:$B$81,MATCH(G38,'Matrice des notes'!$AN$6:$AN$81,0)) -> L-D01 · Sauternes Château Lange-Réglat (au verre) | G38: =MAX('Matrice des notes'!$AN$6:$AN$81) -> 4
A39: Colonel, vodka Grey Goose | B39: • n°1 · Les points d'ancrage • n°7 · Agrumes seuls = incompatibles, agrumes adoucis = possibles • n°35 · Un élément réfractaire plafonne l'accord • n°22 · Le sucre du plat impose un vin au moins aussi sucré | C39: Ancrages : sorbet citron, vodka (n°1). Profil : accord déconseillé : le dessert contient déjà un spiritueux et un agrume. À annoncer comme tel. Si un vin est demandé, le moins exposé est un effervescent sucré-acidulé, peu alcoolisé, servi très frais : le sucre du sorbet adoucit l'agrume (n°7, n°35, n°22). Plafond : agrume et spiritueux, accord à déconseiller (n°35, n°7). Cépages : Muscat (effervescent doux), Chenin blanc (effervescent demi-sec), Riesling doux peu alcoolisé, Brachetto (effervescent doux), Clairette (effervescent doux). À éviter : vin sec, rouge, vin alcooleux (s'ajoute à la vodka) (n°22). Service : 6-8 °C (n°26). | D39: Dessert | E39: 15 | F39: =INDEX('Matrice des notes'!$B$6:$B$81,MATCH(G39,'Matrice des notes'!$AO$6:$AO$81,0)) -> L-E01 · Valdobbiadene Prosecco Superiore Col de l'Utia NM | G39: =MAX('Matrice des notes'!$AO$6:$AO$81) -> 2
A40: Assiette de 3 fromages | B40: • n°1 · Les points d'ancrage • n°5 · Le fromage repousse de facto le tanin • n°18 · Un vin pour plusieurs plats : partir du plat le plus fragile • n°4 · Sucre ↔ sel : l'accord d'opposition classique | C40: Ancrages : trois fromages non précisés (sel, gras, umami, éventuel bleu) (n°1). Profil : vin unique pour trois fromages : partir du fromage le plus fragile. Pas de rouge jeune tannique. Par défaut, un blanc tendu légèrement patiné ou un vin sec élevé sous voile ; un rouge évolué peu coloré sur une pâte pressée ; un vin doux botrytisé si un bleu est présent (opposition sucre ↔ sel). Si aucun vin unique ne tient (bleu + pâte fraîche, par exemple), proposer deux verres (n°5, n°18, n°4). Vin unique pour trois fromages : le plat le plus fragile décide (n°18) ; fromage principal, le n°5 s'applique pleinement. Cépages : Savagnin (sous voile), Chenin blanc, Riesling, Sémillon (botrytisé, sur bleu), Trousseau ou Poulsard (rouge évolué). À éviter : rouge jeune tannique, blanc boisé (n°19, n°5). Service : blanc 10-12 °C ; rouge évolué 14 °C ; doux 8-10 °C (n°26). | D40: Dessert | E40: 15 | F40: =INDEX('Matrice des notes'!$B$6:$B$81,MATCH(G40,'Matrice des notes'!$AP$6:$AP$81,0)) -> L-B20 · Bierzo La del Vivo 2023 | G40: =MAX('Matrice des notes'!$AP$6:$AP$81) -> 4

Sheet Notes analyse
A1: Lola — Notes de l'analyse
A2: Reprise des notes du menu, mises à jour pour ce fichier d'accords.
A4: Point | B4: Détail
A5: Source de la carte | B5: Lola_-_MENU-LOLA-FR-NEW-FALL-.pdf (carte d'automne, version française, 2 pages). Date d'édition non indiquée sur la carte ; fichier reçu le 29/09/2026.
A6: Restaurant | B6: Lola
A7: Lignes analysées | B7: 39 lignes : 13 entrées, 15 plats principaux (dont le filet pur décliné en trois sauces), 11 desserts (dont l'assiette de 3 fromages). 71 lignes de vins : 21 blancs, 40 rouges, 2 rosés, 7 bulles (dont deux demi-bouteilles de Ruinart), 1 liquoreux au verre.
A8: Référentiel utilisé | B8: principes_pat_V4.xlsx, onglet « Principes » : 43 principes, tous considérés comme validés (instructions du projet). La mention « (à valider) » du fichier menu, qui citait encore la V3, est donc retirée. Le fichier de Pat est lu, jamais modifié.
A9: Mise à jour par rapport au menu | B9: Colonne B : principes réécrits sous la forme « • n°X · Titre exact » ; le n°1 (points d'ancrage) y figure désormais, puisqu'il fonde chaque analyse, ainsi que les principes appliqués dans la matrice (plafonds n°35, fromage n°5 / n°37, climat n°42…). Colonne C : chaque ligne cite ses principes ; les lignes « Terroir » ne sont gardées que si le n°2 ou le n°42 s'applique ; les listes de cépages ont été ramenées à cinq (ravioles, vol-au-vent, dame blanche, moelleux, colonel).
A10: Méthode | B10: Le principe « Les points d'ancrage » (n°1) sert de méthode à chaque plat : la ligne « Ancrages » de chaque analyse en est l'application. Il n'est donc pas répété dans la colonne des principes. Pour chaque plat, 2 à 4 principes seulement ont été retenus. Dans ce fichier, le n°1 est cité en colonne B pour chaque plat.
A11: Formulation | B11: Les recommandations sont exprimées en cépages, profils, méthodes d'élaboration et principes, en palette internationale : aucune appellation, région, pays, producteur ni cuvée ne désigne un vin. Les noms de lieux présents dans l'intitulé des plats (Madagascar, Bourgogne, Utah Beach) décrivent uniquement le plat. Les températures de service suivent le principe « La température de service modifie l'accord ».
A12: Hypothèse – croquettes | B12: Croquettes au fromage (12 € / 22 €) et aux crevettes grises (15 € / 27 €) : une seule ligne par croquette, l'analyse étant identique pour 1 ou 2 pièces. Le prix est noté sous forme « 1 pièce / 2 pièces ».
A13: Hypothèse – filet pur | B13: « Sauce au choix » : trois lignes (poivre vert, morilles, béarnaise), l'accord changeant selon la sauce. Le prix de 44 € est supposé inclure une sauce ; les prix de la rubrique « Sauces » (5 € / 7 € / 5 €) sont considérés comme des suppléments. Il n'y a donc pas de groupe « Suppléments sauce » distinct dans la matrice : les trois lignes « filet + sauce » en tiennent lieu (sauce = premier point d'ancrage, n°24).
A14: Hypothèse – pièces | B14: Huîtres : 6 pièces ; moules au beurre d'ail : 12 pièces ; escargots : 6 pièces (mention « 6p » / « 12p » de la carte).
A15: Hypothèse – café glacé | B15: Interprété comme la coupe glacée au café (glace café, chantilly) de la tradition belge, puisqu'il figure dans les desserts, et non comme une boisson.
... A26: À vérifier auprès du restaurant – vins | B26: • Producteurs non indiqués : Puligny Champ Gain (L-B08), Puligny Folatières (L-B09), Chassagne Chenevottes (L-B10), Corton-Charlemagne « Quintessence » (L-B13), Pommard Grands Épenots « Dom Morey » (L-R06), Corton Clos du Roi (L-R08), Terres de Cure (L-R12), Crozes Millepertuis (L-R13) : profils estimés. • Millésimes : Gevrey Justice/Seuvrées (2018 ou 2019), Whispering Angel (2024 ou 2025), Sauternes au verre (non indiqué). • Cuvées : Prosecco Brut ou Extra Dry (change la note sur les nems et les sorbets), Sancerre blanc (cuvée classique supposée), Montagny Millebuis (cuvée exacte), Etna Bianco (cuvée exacte). • Bouteilles à goûter avant de les recommander : Le Pied des Nymphettes 2018, Clos des Mouches 2017, Folatières 2017, Meursault Tessons 2018, Moulin-à-Vent 2014, Fitapreta 2017, Elegancia 2018.

Sheet Matrice des notes
A1: Lola — Matrice des notes d'accord mets-vins (1 à 5)
A2: 1 = pas bon du tout · 2 = médiocre · 3 = correct · 4 = très bon · 5 = accord parfait. Survolez une note pour lire sa justification et les principes de Pat cités.
A3: Plats en colonnes, groupés par type ; vins en lignes, groupés par famille. Pas de supplément sauce séparé sur la carte : les sauces du filet pur sont traitées comme trois plats « filet + sauce ».
D4: Entrées | Q4: Plats | AF4: Desserts
A5: Famille | B5: Vin | C5: Prix (€) | D5: Carpaccio de bœuf Holstein, huile d'olive, parmesan, roquette | E5: Émincé de bar, huile d'olive, citron vert | F5: Scampis en tempura, sauce tartare | G5: Cuisses de grenouilles meunières à l'ail et au persil | H5: Assiette d'huîtres Utah Beach n°3, pain, beurre, échalote, vinaigre – 6 pièces | I5: Belles moules au beurre à l'ail et aux herbes – 12 pièces | J5: Croquettes au fromage, persil frit – 1 pièce / 2 pièces | K5: Croquettes aux crevettes grises, persil frit – 1 pièce / 2 pièces | L5: Escargots magnifiques de Bourgogne – 6 pièces | M5: Nems délicieux, salade, sauce aigre-douce | N5: Fraîcheur de tourteau, sucrine, Granny Smith, mayonnaise curry | O5: Belle tranche de foie gras de canard, brioche toastée | P5: Ravioles de homard, bisque crémeuse | Q5: Filet de bar rôti, légumes de saison, purée, sauce vierge | R5: Tataki de thon, broccolini, riz aux saveurs d'Asie | S5: Cabillaud, crevettes grises, purée, sauce mousseline | T5: Solettes meunière, épinards, purée | U5: Tartare de thon façon Américain, frites et salade | V5: Risotto aux champignons des bois, parmesan | W5: Belle assiette de légumes du marché laqués au miso | X5: Tagliolini, beurre sauge, citron et parmesan | Y5: Volaille, sauce morilles, chiconettes, purée | Z5: Vol-au-vent volaille et ris de veau, mousseline, frites | AA5: Ris de veau laqué, garniture automnale, purée | AB5: Tartare de bœuf préparé minute, frites | AC5: Filet pur de bœuf Simmental, sauce poivre vert, frites et salade | AD5: Filet pur de bœuf Simmental, sauce morilles, frites et salade | AE5: Filet pur de bœuf Simmental, sauce béarnaise, frites et salade | AF5: Crème brûlée à la vanille de Madagascar | AG5: Traditionnelle dame blanche | AH5: Moelleux au chocolat 70 %, glace vanille de Madagascar | AI5: Café glacé | AJ5: Duo de sorbets de saison | AK5: Île flottante, crème vanille, amandes caramélisées | AL5: Crumble de pommes caramélisées, glace vanille de Madagascar | AM5: Profiterole glace pistache, sauce Gianduja | AN5: Mille-feuille, crème pâtissière pralinée | AO5: Colonel, vodka Grey Goose | AP5: Assiette de 3 fromages | AQ5: Note moyenne du vin
A6: Blancs | B6: BLANCS
A7: Blancs | B7: L-B01 · IGP Val de Loire Sauvignon Le Petit Bourgeois 2024 | C7: 38 | D7: 3 | E7: 4 | F7: 4 | G7: 4 | H7: 4 | I7: 5 | J7: 4 | K7: 4 | L7: 4 | M7: 2 | N7: 4 | O7: 2 | P7: 3 | Q7: 4 | R7: 4 | S7: 4 | T7: 5 | U7: 4 | V7: 3 | W7: 2 | X7: 4 | Y7: 3 | Z7: 3 | AA7: 3 | AB7: 3 | AC7: 2 | AD7: 3 | AE7: 2 | AF7: 1 | AG7: 1 | AH7: 1 | AI7: 1 | AJ7: 1 | AK7: 1 | AL7: 1 | AM7: 1 | AN7: 1 | AO7: 1 | AP7: 3 | AQ7: =AVERAGE(D7:AP7) -> 2.7948718
A8: Blancs | B8: L-B02 · Sancerre Henri Bourgeois 2025 | C8: 58 | D8: 3 | E8: 4 | F8: 4 | G8: 4 | H8: 4 | I8: 5 | J8: 4 | K8: 4 | L8: 4 | M8: 2 | N8: 4 | O8: 2 | P8: 4 | Q8: 4 | R8: 4 | S8: 4 | T8: 5 | U8: 4 | V8: 4 | W8: 2 | X8: 4 | Y8: 4 | Z8: 4 | AA8: 4 | AB8: 3 | AC8: 2 | AD8: 3 | AE8: 2 | AF8: 1 | AG8: 1 | AH8: 1 | AI8: 1 | AJ8: 1 | AK8: 1 | AL8: 1 | AM8: 1 | AN8: 1 | AO8: 1 | AP8: 3 | AQ8: =AVERAGE(D8:AP8) -> 2.9230769
A9: Blancs | B9: L-B03 · Pouilly-Fumé de Ladoucette 2024 | C9: 80 | D9: 3 | E9: 4 | F9: 4 | G9: 5 | H9: 4 | I9: 5 | J9: 4 | K9: 4 | L9: 4 | M9: 2 | N9: 4 | O9: 2 | P9: 5 | Q9: 4 | R9: 4 | S9: 4 | T9: 5 | U9: 4 | V9: 4 | W9: 2 | X9: 4 | Y9: 4 | Z9: 5 | AA9: 4 | AB9: 3 | AC9: 2 | AD9: 3 | AE9: 2 | AF9: 1 | AG9: 1 | AH9: 1 | AI9: 1 | AJ9: 1 | AK9: 1 | AL9: 1 | AM9: 1 | AN9: 1 | AO9: 1 | AP9: 3 | AQ9: =AVERAGE(D9:AP9) -> 3
A10: Blancs | B10: L-B04 · Pessac-Léognan Château Carbonnieux blanc 2024 | C10: 120 | D10: 2 | E10: 2 | F10: 2 | G10: 2 | H10: 2 | I10: 2 | J10: 2 | K10: 2 | L10: 3 | M10: 1 | N10: 2 | O10: 2 | P10: 3 | Q10: 3 | R10: 3 | S10: 3 | T10: 2 | U10: 2 | V10: 4 | W10: 2 | X10: 3 | Y10: 4 | Z10: 3 | AA10: 4 | AB10: 3 | AC10: 2 | AD10: 3 | AE10: 2 | AF10: 1 | AG10: 1 | AH10: 1 | AI10: 1 | AJ10: 1 | AK10: 1 | AL10: 1 | AM10: 1 | AN10: 1 | AO10: 1 | AP10: 3 | AQ10: =AVERAGE(D10:AP10) -> 2.1282051
A11: Blancs | B11: L-B05 · Petit Chablis Pas Si Petit 2023 | C11: 46 | D11: 3 | E11: 4 | F11: 4 | G11: 5 | H11: 4 | I11: 5 | J11: 4 | K11: 4 | L11: 5 | M11: 2 | N11: 4 | O11: 2 | P11: 4 | Q11: 4 | R11: 4 | S11: 4 | T11: 5 | U11: 4 | V11: 3 | W11: 2 | X11: 4 | Y11: 3 | Z11: 4 | AA11: 3 | AB11: 3 | AC11: 2 | AD11: 3 | AE11: 2 | AF11: 1 | AG11: 1 | AH11: 1 | AI11: 1 | AJ11: 1 | AK11: 1 | AL11: 1 | AM11: 1 | AN11: 1 | AO11: 1 | AP11: 3 | AQ11: =AVERAGE(D11:AP11) -> 2.8974359
A12: Blancs | B12: L-B06 · Montagny Millebuis 2022 | C12: 48 | D12: 3 | E12: 2 | F12: 2 | G12: 2 | H12: 2 | I12: 2 | J12: 2 | K12: 2 | L12: 5 | M12: 2 | N12: 2 | O12: 2 | P12: 4 | Q12: 2 | R12: 4 | S12: 3 | T12: 2 | U12: 2 | V12: 4 | W12: 2 | X12: 2 | Y12: 4 | Z12: 4 | AA12: 4 | AB12: 3 | AC12: 2 | AD12: 3 | AE12: 2 | AF12: 1 | AG12: 1 | AH12: 1 | AI12: 1 | AJ12: 1 | AK12: 1 | AL12: 1 | AM12: 1 | AN12: 1 | AO12: 1 | AP12: 2 | AQ12: =AVERAGE(D12:AP12) -> 2.2307692
A13: Blancs | B13: L-B07 · Bourgogne Chardonnay Nuiton-Beaunoy 2023 | C13: 49 | D13: 3 | E13: 2 | F13: 2 | G13: 2 | H13: 2 | I13: 2 | J13: 2 | K13: 2 | L13: 5 | M13: 2 | N13: 2 | O13: 2 | P13: 3 | Q13: 2 | R13: 4 | S13: 3 | T13: 2 | U13: 2 | V13: 3 | W13: 2 | X13: 2 | Y13: 3 | Z13: 3 | AA13: 3 | AB13: 3 | AC13: 2 | AD13: 3 | AE13: 2 | AF13: 1 | AG13: 1 | AH13: 1 | AI13: 1 | AJ13: 1 | AK13: 1 | AL13: 1 | AM13: 1 | AN13: 1 | AO13: 1 | AP13: 2 | AQ13: =AVERAGE(D13:AP13) -> 2.1025641
A14: Blancs | B14: L-B08 · Puligny-Montrachet 1er Cru Champ Gain 2019 | C14: 195 | D14: 1 | E14: 1 | F14: 2 | G14: 2 | H14: 1 | I14: 2 | J14: 2 | K14: 2 | L14: 3 | M14: 1 | N14: 1 | O14: 3 | P14: 3 | Q14: 2 | R14: 3 | S14: 3 | T14: 2 | U14: 2 | V14: 5 | W14: 2 | X14: 2 | Y14: 5 | Z14: 3 | AA14: 4 | AB14: 3 | AC14: 2 | AD14: 3 | AE14: 2 | AF14: 1 | AG14: 1 | AH14: 1 | AI14: 1 | AJ14: 1 | AK14: 1 | AL14: 1 | AM14: 1 | AN14: 1 | AO14: 1 | AP14: 3 | AQ14: =AVERAGE(D14:AP14) -> 2.0512821
A15: Blancs | B15: L-B09 · Puligny-Montrachet 1er Cru Les Folatières 2017 | C15: 395 | D15: 1 | E15: 1 | F15: 2 | G15: 2 | H15: 1 | I15: 2 | J15: 2 | K15: 2 | L15: 3 | M15: 1 | N15: 1 | O15: 3 | P15: 3 | Q15: 2 | R15: 3 | S15: 3 | T15: 2 | U15: 2 | V15: 4 | W15: 2 | X15: 2 | Y15: 4 | Z15: 3 | AA15: 4 | AB15: 3 | AC15: 2 | AD15: 3 | AE15: 2 | AF15: 1 | AG15: 1 | AH15: 1 | AI15: 1 | AJ15: 1 | AK15: 1 | AL15: 1 | AM15: 1 | AN15: 1 | AO15: 1 | AP15: 3 | AQ15: =AVERAGE(D15:AP15) -> 2
A16: Blancs | B16: L-B10 · Chassagne-Montrachet 1er Cru Les Chenevottes 2020 | C16: 240 | D16: 1 | E16: 1 | F16: 1 | G16: 1 | H16: 1 | I16: 1 | J16: 1 | K16: 1 | L16: 3 | M16: 1 | N16: 1 | O16: 3 | P16: 3 | Q16: 1 | R16: 3 | S16: 2 | T16: 1 | U16: 1 | V16: 4 | W16: 2 | X16: 1 | Y16: 4 | Z16: 3 | AA16: 4 | AB16: 2 | AC16: 2 | AD16: 3 | AE16: 2 | AF16: 1 | AG16: 1 | AH16: 1 | AI16: 1 | AJ16: 1 | AK16: 1 | AL16: 1 | AM16: 1 | AN16: 1 | AO16: 1 | AP16: 2 | AQ16: =AVERAGE(D16:AP16) -> 1.6923077
A17: Blancs | B17: L-B11 · Beaune 1er Cru Clos des Mouches blanc 2017 | C17: 250 | D17: 1 | E17: 1 | F17: 1 | G17: 1 | H17: 1 | I17: 1 | J17: 1 | K17: 1 | L17: 3 | M17: 1 | N17: 1 | O17: 3 | P17: 3 | Q17: 1 | R17: 3 | S17: 2 | T17: 1 | U17: 1 | V17: 5 | W17: 2 | X17: 1 | Y17: 5 | Z17: 3 | AA17: 4 | AB17: 2 | AC17: 2 | AD17: 3 | AE17: 2 | AF17: 1 | AG17: 1 | AH17: 1 | AI17: 1 | AJ17: 1 | AK17: 1 | AL17: 1 | AM17: 1 | AN17: 1 | AO17: 1 | AP17: 3 | AQ17: =AVERAGE(D17:AP17) -> 1.7692308
A18: Blancs | B18: L-B12 · Meursault Les Tessons 2018 | C18: 285 | D18: 1 | E18: 1 | F18: 1 | G18: 1 | H18: 1 | I18: 1 | J18: 1 | K18: 1 | L18: 3 | M18: 1 | N18: 1 | O18: 3 | P18: 3 | Q18: 1 | R18: 3 | S18: 2 | T18: 1 | U18: 1 | V18: 5 | W18: 2 | X18: 1 | Y18: 5 | Z18: 3 | AA18: 4 | AB18: 2 | AC18: 2 | AD18: 3 | AE18: 2 | AF18: 1 | AG18: 1 | AH18: 1 | AI18: 1 | AJ18: 1 | AK18: 1 | AL18: 1 | AM18: 1 | AN18: 1 | AO18: 1 | AP18: 3 | AQ18: =AVERAGE(D18:AP18) -> 1.7692308
... A27: Blancs | B27: L-B21 · Chablis Saint-Pierre 2024 · 37,5 cl | C27: 28 | D27: 3 | E27: 4 | F27: 4 | G27: 4 | H27: 4 | I27: 5 | J27: 4 | K27: 4 | L27: 5 | M27: 2 | N27: 4 | O27: 2 | P27: 3 | Q27: 4 | R27: 4 | S27: 4 | T27: 5 | U27: 4 | V27: 3 | W27: 2 | X27: 4 | Y27: 3 | Z27: 3 | AA27: 3 | AB27: 3 | AC27: 2 | AD27: 3 | AE27: 2 | AF27: 1 | AG27: 1 | AH27: 1 | AI27: 1 | AJ27: 1 | AK27: 1 | AL27: 1 | AM27: 1 | AN27: 1 | AO27: 1 | AP27: 3 | AQ27: =AVERAGE(D27:AP27) -> 2.8205128
A28: Rouges | B28: ROUGES
A29: Rouges | B29: L-R01 · Chiroubles Domaine Piron 2024 | C29: 50 | D29: 5 | E29: 2 | F29: 2 | G29: 2 | H29: 2 | I29: 2 | J29: 2 | K29: 2 | L29: 4 | M29: 1 | N29: 2 | O29: 2 | P29: 2 | Q29: 4 | R29: 5 | S29: 2 | T29: 2 | U29: 3 | V29: 3 | W29: 2 | X29: 2 | Y29: 3 | Z29: 2 | AA29: 3 | AB29: 4 | AC29: 3 | AD29: 3 | AE29: 4 | AF29: 1 | AG29: 1 | AH29: 1 | AI29: 1 | AJ29: 1 | AK29: 1 | AL29: 1 | AM29: 1 | AN29: 1 | AO29: 1 | AP29: 2 | AQ29: =AVERAGE(D29:AP29) -> 2.2307692
A30: Rouges | B30: L-R02 · Saint-Amour Domaine Piron 2024 | C30: 54 | D30: 4 | E30: 1 | F30: 1 | G30: 1 | H30: 1 | I30: 1 | J30: 1 | K30: 1 | L30: 4 | M30: 1 | N30: 1 | O30: 2 | P30: 1 | Q30: 2 | R30: 4 | S30: 1 | T30: 1 | U30: 2 | V30: 4 | W30: 2 | X30: 1 | Y30: 4 | Z30: 1 | AA30: 4 | AB30: 3 | AC30: 4 | AD30: 4 | AE30: 3 | AF30: 1 | AG30: 1 | AH30: 1 | AI30: 1 | AJ30: 1 | AK30: 1 | AL30: 1 | AM30: 1 | AN30: 1 | AO30: 1 | AP30: 1 | AQ30: =AVERAGE(D30:AP30) -> 1.8205128
A31: Rouges | B31: L-R03 · Moulin-à-Vent Les Michelons 2014 | C31: 145 | D31: 2 | E31: 1 | F31: 1 | G31: 1 | H31: 1 | I31: 1 | J31: 1 | K31: 1 | L31: 4 | M31: 1 | N31: 1 | O31: 1 | P31: 1 | Q31: 1 | R31: 4 | S31: 1 | T31: 1 | U31: 1 | V31: 5 | W31: 1 | X31: 1 | Y31: 4 | Z31: 1 | AA31: 5 | AB31: 3 | AC31: 5 | AD31: 5 | AE31: 3 | AF31: 1 | AG31: 1 | AH31: 1 | AI31: 1 | AJ31: 1 | AK31: 1 | AL31: 1 | AM31: 1 | AN31: 1 | AO31: 1 | AP31: 3 | AQ31: =AVERAGE(D31:AP31) -> 1.8205128
A32: Rouges | B32: L-R04 · Bourgogne Pinot noir Nuiton-Beaunoy 2023 | C32: 49 | D32: 4 | E32: 2 | F32: 2 | G32: 2 | H32: 2 | I32: 2 | J32: 2 | K32: 2 | L32: 4 | M32: 1 | N32: 2 | O32: 2 | P32: 2 | Q32: 1 | R32: 4 | S32: 2 | T32: 2 | U32: 1 | V32: 3 | W32: 2 | X32: 2 | Y32: 3 | Z32: 2 | AA32: 3 | AB32: 3 | AC32: 3 | AD32: 3 | AE32: 2 | AF32: 1 | AG32: 1 | AH32: 1 | AI32: 1 | AJ32: 1 | AK32: 1 | AL32: 1 | AM32: 1 | AN32: 1 | AO32: 1 | AP32: 1 | AQ32: =AVERAGE(D32:AP32) -> 1.9487179
A33: Rouges | B33: L-R05 · Givry Millebuis 2023 | C33: 58 | D33: 3 | E33: 1 | F33: 1 | G33: 1 | H33: 1 | I33: 1 | J33: 1 | K33: 1 | L33: 4 | M33: 1 | N33: 1 | O33: 2 | P33: 1 | Q33: 1 | R33: 3 | S33: 1 | T33: 1 | U33: 1 | V33: 4 | W33: 2 | X33: 1 | Y33: 4 | Z33: 1 | AA33: 4 | AB33: 2 | AC33: 4 | AD33: 4 | AE33: 3 | AF33: 1 | AG33: 1 | AH33: 1 | AI33: 1 | AJ33: 1 | AK33: 1 | AL33: 1 | AM33: 1 | AN33: 1 | AO33: 1 | AP33: 1 | AQ33: =AVERAGE(D33:AP33) -> 1.6923077
A34: Rouges | B34: L-R06 · Pommard 1er Cru Les Grands Épenots 2018 | C34: 210 | D34: 1 | E34: 1 | F34: 1 | G34: 1 | H34: 1 | I34: 1 | J34: 1 | K34: 1 | L34: 3 | M34: 1 | N34: 1 | O34: 1 | P34: 1 | Q34: 1 | R34: 2 | S34: 1 | T34: 1 | U34: 1 | V34: 4 | W34: 1 | X34: 1 | Y34: 3 | Z34: 1 | AA34: 4 | AB34: 1 | AC34: 5 | AD34: 5 | AE34: 2 | AF34: 1 | AG34: 1 | AH34: 1 | AI34: 1 | AJ34: 1 | AK34: 1 | AL34: 1 | AM34: 1 | AN34: 1 | AO34: 1 | AP34: 1 | AQ34: =AVERAGE(D34:AP34) -> 1.5128205
A35: Rouges | B35: L-R07 · Beaune 1er Cru Clos des Fèves 2018 | C35: 320 | D35: 1 | E35: 1 | F35: 1 | G35: 1 | H35: 1 | I35: 1 | J35: 1 | K35: 1 | L35: 3 | M35: 1 | N35: 1 | O35: 1 | P35: 1 | Q35: 1 | R35: 2 | S35: 1 | T35: 1 | U35: 1 | V35: 3 | W35: 1 | X35: 1 | Y35: 3 | Z35: 1 | AA35: 4 | AB35: 1 | AC35: 5 | AD35: 4 | AE35: 2 | AF35: 1 | AG35: 1 | AH35: 1 | AI35: 1 | AJ35: 1 | AK35: 1 | AL35: 1 | AM35: 1 | AN35: 1 | AO35: 1 | AP35: 1 | AQ35: =AVERAGE(D35:AP35) -> 1.4615385
A36: Rouges | B36: L-R08 · Corton Grand Cru Clos du Roi 2018 | C36: 485 | D36: 1 | E36: 1 | F36: 1 | G36: 1 | H36: 1 | I36: 1 | J36: 1 | K36: 1 | L36: 2 | M36: 1 | N36: 1 | O36: 1 | P36: 1 | Q36: 1 | R36: 1 | S36: 1 | T36: 1 | U36: 1 | V36: 2 | W36: 1 | X36: 1 | Y36: 2 | Z36: 1 | AA36: 3 | AB36: 1 | AC36: 3 | AD36: 3 | AE36: 2 | AF36: 1 | AG36: 1 | AH36: 1 | AI36: 1 | AJ36: 1 | AK36: 1 | AL36: 1 | AM36: 1 | AN36: 1 | AO36: 1 | AP36: 1 | AQ36: =AVERAGE(D36:AP36) -> 1.2564103
A37: Rouges | B37: L-R09 · Gevrey-Chambertin Justice / Seuvrées 2018-2019 | C37: 560 | D37: 1 | E37: 1 | F37: 1 | G37: 1 | H37: 1 | I37: 1 | J37: 1 | K37: 1 | L37: 2 | M37: 1 | N37: 1 | O37: 1 | P37: 1 | Q37: 1 | R37: 1 | S37: 1 | T37: 1 | U37: 1 | V37: 2 | W37: 1 | X37: 1 | Y37: 2 | Z37: 1 | AA37: 3 | AB37: 1 | AC37: 4 | AD37: 3 | AE37: 2 | AF37: 1 | AG37: 1 | AH37: 1 | AI37: 1 | AJ37: 1 | AK37: 1 | AL37: 1 | AM37: 1 | AN37: 1 | AO37: 1 | AP37: 1 | AQ37: =AVERAGE(D37:AP37) -> 1.2820513
A38: Rouges | B38: L-R10 · Bourgueil Côte 50 2024 | C38: 45 | D38: 5 | E38: 2 | F38: 2 | G38: 2 | H38: 2 | I38: 2 | J38: 2 | K38: 2 | L38: 4 | M38: 1 | N38: 2 | O38: 2 | P38: 2 | Q38: 3 | R38: 5 | S38: 2 | T38: 2 | U38: 3 | V38: 3 | W38: 2 | X38: 2 | Y38: 3 | Z38: 2 | AA38: 3 | AB38: 4 | AC38: 3 | AD38: 3 | AE38: 4 | AF38: 1 | AG38: 1 | AH38: 1 | AI38: 1 | AJ38: 1 | AK38: 1 | AL38: 1 | AM38: 1 | AN38: 1 | AO38: 1 | AP38: 1 | AQ38: =AVERAGE(D38:AP38) -> 2.1794872
A39: Rouges | B39: L-R11 · Sancerre rouge Henri Bourgeois 2023 | C39: 48 | D39: 5 | E39: 2 | F39: 2 | G39: 2 | H39: 2 | I39: 2 | J39: 2 | K39: 2 | L39: 4 | M39: 1 | N39: 2 | O39: 2 | P39: 2 | Q39: 2 | R39: 5 | S39: 2 | T39: 2 | U39: 2 | V39: 3 | W39: 2 | X39: 2 | Y39: 3 | Z39: 2 | AA39: 3 | AB39: 4 | AC39: 3 | AD39: 3 | AE39: 4 | AF39: 1 | AG39: 1 | AH39: 1 | AI39: 1 | AJ39: 1 | AK39: 1 | AL39: 1 | AM39: 1 | AN39: 1 | AO39: 1 | AP39: 1 | AQ39: =AVERAGE(D39:AP39) -> 2.1282051
A40: Rouges | B40: L-R12 · Rhône Terres de Cure 2022 | C40: 45 | D40: 2 | E40: 1 | F40: 1 | G40: 1 | H40: 1 | I40: 1 | J40: 1 | K40: 1 | L40: 3 | M40: 1 | N40: 1 | O40: 1 | P40: 1 | Q40: 1 | R40: 3 | S40: 1 | T40: 1 | U40: 1 | V40: 3 | W40: 1 | X40: 1 | Y40: 3 | Z40: 1 | AA40: 3 | AB40: 2 | AC40: 3 | AD40: 3 | AE40: 2 | AF40: 1 | AG40: 1 | AH40: 1 | AI40: 1 | AJ40: 1 | AK40: 1 | AL40: 1 | AM40: 1 | AN40: 1 | AO40: 1 | AP40: 1 | AQ40: =AVERAGE(D40:AP40) -> 1.4358974
... A68: Rouges | B68: L-R40 · Saint-Estèphe Château Petit Bocq 2023 · 37,5 cl | C68: 32 | D68: 1 | E68: 1 | F68: 1 | G68: 1 | H68: 1 | I68: 1 | J68: 1 | K68: 1 | L68: 1 | M68: 1 | N68: 1 | O68: 1 | P68: 1 | Q68: 1 | R68: 1 | S68: 1 | T68: 1 | U68: 1 | V68: 2 | W68: 1 | X68: 1 | Y68: 2 | Z68: 1 | AA68: 2 | AB68: 1 | AC68: 2 | AD68: 2 | AE68: 2 | AF68: 1 | AG68: 1 | AH68: 1 | AI68: 1 | AJ68: 1 | AK68: 1 | AL68: 1 | AM68: 1 | AN68: 1 | AO68: 1 | AP68: 1 | AQ68: =AVERAGE(D68:AP68) -> 1.1538462
A69: Rosés | B69: ROSÉS
A70: Rosés | B70: L-P01 · Côtes de Provence Le Merle 2025 | C70: 42 | D70: 3 | E70: 3 | F70: 3 | G70: 3 | H70: 3 | I70: 3 | J70: 3 | K70: 3 | L70: 3 | M70: 2 | N70: 3 | O70: 2 | P70: 3 | Q70: 3 | R70: 4 | S70: 3 | T70: 3 | U70: 3 | V70: 3 | W70: 2 | X70: 3 | Y70: 3 | Z70: 3 | AA70: 3 | AB70: 3 | AC70: 2 | AD70: 2 | AE70: 2 | AF70: 1 | AG70: 1 | AH70: 1 | AI70: 1 | AJ70: 1 | AK70: 1 | AL70: 1 | AM70: 1 | AN70: 1 | AO70: 1 | AP70: 2 | AQ70: =AVERAGE(D70:AP70) -> 2.3333333
A71: Rosés | B71: L-P02 · Côtes de Provence Whispering Angel 2024-2025 | C71: 55 | D71: 3 | E71: 3 | F71: 3 | G71: 3 | H71: 3 | I71: 3 | J71: 3 | K71: 3 | L71: 3 | M71: 2 | N71: 3 | O71: 2 | P71: 3 | Q71: 3 | R71: 4 | S71: 3 | T71: 3 | U71: 3 | V71: 3 | W71: 2 | X71: 3 | Y71: 3 | Z71: 3 | AA71: 3 | AB71: 3 | AC71: 2 | AD71: 2 | AE71: 2 | AF71: 1 | AG71: 1 | AH71: 1 | AI71: 1 | AJ71: 1 | AK71: 1 | AL71: 1 | AM71: 1 | AN71: 1 | AO71: 1 | AP71: 2 | AQ71: =AVERAGE(D71:AP71) -> 2.3333333
A72: Bulles | B72: BULLES
A73: Bulles | B73: L-E01 · Valdobbiadene Prosecco Superiore Col de l'Utia NM | C73: 62 | D73: 3 | E73: 3 | F73: 3 | G73: 3 | H73: 3 | I73: 3 | J73: 3 | K73: 3 | L73: 3 | M73: 3 | N73: 3 | O73: 2 | P73: 3 | Q73: 3 | R73: 3 | S73: 3 | T73: 3 | U73: 3 | V73: 3 | W73: 2 | X73: 3 | Y73: 3 | Z73: 3 | AA73: 3 | AB73: 3 | AC73: 2 | AD73: 3 | AE73: 2 | AF73: 1 | AG73: 1 | AH73: 1 | AI73: 1 | AJ73: 2 | AK73: 1 | AL73: 1 | AM73: 1 | AN73: 1 | AO73: 2 | AP73: 2 | AQ73: =AVERAGE(D73:AP73) -> 2.4102564
A74: Bulles | B74: L-E02 · Champagne R de Ruinart Brut NM · 37,5 cl | C74: 58 | D74: 3 | E74: 4 | F74: 4 | G74: 4 | H74: 4 | I74: 4 | J74: 5 | K74: 5 | L74: 3 | M74: 2 | N74: 4 | O74: 2 | P74: 5 | Q74: 4 | R74: 3 | S74: 4 | T74: 4 | U74: 4 | V74: 3 | W74: 2 | X74: 4 | Y74: 4 | Z74: 5 | AA74: 3 | AB74: 3 | AC74: 2 | AD74: 3 | AE74: 2 | AF74: 1 | AG74: 1 | AH74: 1 | AI74: 1 | AJ74: 1 | AK74: 1 | AL74: 1 | AM74: 1 | AN74: 1 | AO74: 1 | AP74: 3 | AQ74: =AVERAGE(D74:AP74) -> 2.8717949
A75: Bulles | B75: L-E03 · Champagne R de Ruinart Brut NM | C75: 105 | D75: 3 | E75: 4 | F75: 4 | G75: 4 | H75: 4 | I75: 4 | J75: 5 | K75: 5 | L75: 3 | M75: 2 | N75: 4 | O75: 2 | P75: 5 | Q75: 4 | R75: 3 | S75: 4 | T75: 4 | U75: 4 | V75: 3 | W75: 2 | X75: 4 | Y75: 4 | Z75: 5 | AA75: 3 | AB75: 3 | AC75: 2 | AD75: 3 | AE75: 2 | AF75: 1 | AG75: 1 | AH75: 1 | AI75: 1 | AJ75: 1 | AK75: 1 | AL75: 1 | AM75: 1 | AN75: 1 | AO75: 1 | AP75: 3 | AQ75: =AVERAGE(D75:AP75) -> 2.8717949
A76: Bulles | B76: L-E04 · Champagne Laurent-Perrier Cuvée Rosé NM | C76: 168 | D76: 3 | E76: 2 | F76: 3 | G76: 2 | H76: 2 | I76: 2 | J76: 3 | K76: 3 | L76: 3 | M76: 2 | N76: 2 | O76: 2 | P76: 5 | Q76: 3 | R76: 3 | S76: 2 | T76: 2 | U76: 3 | V76: 3 | W76: 2 | X76: 2 | Y76: 4 | Z76: 4 | AA76: 3 | AB76: 3 | AC76: 2 | AD76: 3 | AE76: 2 | AF76: 1 | AG76: 1 | AH76: 1 | AI76: 1 | AJ76: 1 | AK76: 1 | AL76: 1 | AM76: 1 | AN76: 1 | AO76: 1 | AP76: 2 | AQ76: =AVERAGE(D76:AP76) -> 2.2307692
A77: Bulles | B77: L-E05 · Champagne Ruinart Blanc de Blancs NM · 37,5 cl | C77: 90 | D77: 3 | E77: 4 | F77: 4 | G77: 4 | H77: 4 | I77: 4 | J77: 5 | K77: 5 | L77: 3 | M77: 2 | N77: 4 | O77: 2 | P77: 3 | Q77: 4 | R77: 3 | S77: 4 | T77: 4 | U77: 4 | V77: 3 | W77: 2 | X77: 4 | Y77: 3 | Z77: 3 | AA77: 3 | AB77: 3 | AC77: 2 | AD77: 3 | AE77: 2 | AF77: 1 | AG77: 1 | AH77: 1 | AI77: 1 | AJ77: 1 | AK77: 1 | AL77: 1 | AM77: 1 | AN77: 1 | AO77: 1 | AP77: 3 | AQ77: =AVERAGE(D77:AP77) -> 2.7435897
A78: Bulles | B78: L-E06 · Champagne Ruinart Blanc de Blancs NM | C78: 175 | D78: 3 | E78: 4 | F78: 4 | G78: 4 | H78: 4 | I78: 4 | J78: 5 | K78: 5 | L78: 3 | M78: 2 | N78: 4 | O78: 2 | P78: 3 | Q78: 4 | R78: 3 | S78: 4 | T78: 4 | U78: 4 | V78: 3 | W78: 2 | X78: 4 | Y78: 3 | Z78: 3 | AA78: 3 | AB78: 3 | AC78: 2 | AD78: 3 | AE78: 2 | AF78: 1 | AG78: 1 | AH78: 1 | AI78: 1 | AJ78: 1 | AK78: 1 | AL78: 1 | AM78: 1 | AN78: 1 | AO78: 1 | AP78: 3 | AQ78: =AVERAGE(D78:AP78) -> 2.7435897
A79: Bulles | B79: L-E07 · Champagne Dom Pérignon Vintage 2017 | C79: 340 | D79: 3 | E79: 4 | F79: 4 | G79: 4 | H79: 4 | I79: 4 | J79: 5 | K79: 5 | L79: 3 | M79: 2 | N79: 3 | O79: 3 | P79: 5 | Q79: 4 | R79: 3 | S79: 4 | T79: 4 | U79: 4 | V79: 3 | W79: 2 | X79: 4 | Y79: 4 | Z79: 5 | AA79: 3 | AB79: 3 | AC79: 2 | AD79: 3 | AE79: 2 | AF79: 1 | AG79: 1 | AH79: 1 | AI79: 1 | AJ79: 1 | AK79: 1 | AL79: 1 | AM79: 1 | AN79: 1 | AO79: 1 | AP79: 3 | AQ79: =AVERAGE(D79:AP79) -> 2.8717949
A80: Doux | B80: DOUX
A81: Doux | B81: L-D01 · Sauternes Château Lange-Réglat (au verre) | C81: 15 | D81: 1 | E81: 1 | F81: 1 | G81: 1 | H81: 1 | I81: 1 | J81: 1 | K81: 1 | L81: 1 | M81: 3 | N81: 1 | O81: 5 | P81: 1 | Q81: 1 | R81: 1 | S81: 1 | T81: 1 | U81: 1 | V81: 1 | W81: 3 | X81: 1 | Y81: 1 | Z81: 1 | AA81: 1 | AB81: 1 | AC81: 1 | AD81: 1 | AE81: 1 | AF81: 5 | AG81: 2 | AH81: 2 | AI81: 2 | AJ81: 3 | AK81: 4 | AL81: 4 | AM81: 2 | AN81: 4 | AO81: 2 | AP81: 3 | AQ81: =AVERAGE(D81:AP81) -> 1.7692308
B82: Meilleure note du plat | D82: =MAX(D6:D81) -> 5 | E82: =MAX(E6:E81) -> 4 | F82: =MAX(F6:F81) -> 4 | G82: =MAX(G6:G81) -> 5 | H82: =MAX(H6:H81) -> 4 | I82: =MAX(I6:I81) -> 5 | J82: =MAX(J6:J81) -> 5 | K82: =MAX(K6:K81) -> 5 | ... AP82: =MAX(AP6:AP81) -> 4

Sheet Commentaires
A1: Lola — Commentaires d'accord (note, justification, principes)
A2: Même grille que « Matrice des notes ». Couleur = note au moment de la génération : si une note est modifiée dans la matrice, ajuster ce texte à la main.
A3: Plats en colonnes, groupés par type ; vins en lignes, groupés par famille. Pas de supplément sauce séparé sur la carte : les sauces du filet pur sont traitées comme trois plats « filet + sauce ».
D4: Entrées | Q4: Plats | AF4: Desserts
A5: Famille | B5: Vin | C5: Prix (€) | D5: Carpaccio de bœuf Holstein, huile d'olive, parmesan, roquette | E5: Émincé de bar, huile d'olive, citron vert | F5: Scampis en tempura, sauce tartare | G5: Cuisses de grenouilles meunières à l'ail et au persil | H5: Assiette d'huîtres Utah Beach n°3, pain, beurre, échalote, vinaigre – 6 pièces | I5: Belles moules au beurre à l'ail et aux herbes – 12 pièces | J5: Croquettes au fromage, persil frit – 1 pièce / 2 pièces | K5: Croquettes aux crevettes grises, persil frit – 1 pièce / 2 pièces | L5: Escargots magnifiques de Bourgogne – 6 pièces | M5: Nems délicieux, salade, sauce aigre-douce | N5: Fraîcheur de tourteau, sucrine, Granny Smith, mayonnaise curry | O5: Belle tranche de foie gras de canard, brioche toastée | P5: Ravioles de homard, bisque crémeuse | Q5: Filet de bar rôti, légumes de saison, purée, sauce vierge | R5: Tataki de thon, broccolini, riz aux saveurs d'Asie | S5: Cabillaud, crevettes grises, purée, sauce mousseline | T5: Solettes meunière, épinards, purée | U5: Tartare de thon façon Américain, frites et salade | V5: Risotto aux champignons des bois, parmesan | W5: Belle assiette de légumes du marché laqués au miso | X5: Tagliolini, beurre sauge, citron et parmesan | Y5: Volaille, sauce morilles, chiconettes, purée | Z5: Vol-au-vent volaille et ris de veau, mousseline, frites | AA5: Ris de veau laqué, garniture automnale, purée | AB5: Tartare de bœuf préparé minute, frites | AC5: Filet pur de bœuf Simmental, sauce poivre vert, frites et salade | AD5: Filet pur de bœuf Simmental, sauce morilles, frites et salade | AE5: Filet pur de bœuf Simmental, sauce béarnaise, frites et salade | AF5: Crème brûlée à la vanille de Madagascar | AG5: Traditionnelle dame blanche | AH5: Moelleux au chocolat 70 %, glace vanille de Madagascar | AI5: Café glacé | AJ5: Duo de sorbets de saison | AK5: Île flottante, crème vanille, amandes caramélisées | AL5: Crumble de pommes caramélisées, glace vanille de Madagascar | AM5: Profiterole glace pistache, sauce Gianduja | AN5: Mille-feuille, crème pâtissière pralinée | AO5: Colonel, vodka Grey Goose | AP5: Assiette de 3 fromages
A6: Blancs | B6: BLANCS
A7: Blancs | B7: L-B01 · IGP Val de Loire Sauvignon Le Petit Bourgeois 2024 | C7: 38 | D7: 3/5 — Blanc correct sur le bœuf cru, mais le sel du parmesan autorise et appelle un rouge léger (P28, P20). | E7: 4/5 — Le citron vert nature plafonne l'accord (P7, P35) ; tension saline d'un vin de bord d'eau sur le bar cru (P9). | F7: 4/5 — Blanc tendu, léger, sans bois : profil qui convient, sans point d'ancrage décisif (P20, P23) ; l'émulsion à l'œuf de la tartare plafonne l'accord (P10, P35). | G7: 4/5 — Blanc tendu, léger, sans bois : profil qui convient, sans point d'ancrage décisif (P20, P3). | H7: 4/5 — Le vinaigre à l'échalote plafonne l'accord (P11, P35) ; acidité littorale et salinité en écho à l'iode (P9). | I7: 5/5 — L'acidité coupe le beurre, la salinité répond à l'iode (P9, P3). | J7: 4/5 — Blanc tendu, léger, sans bois : profil qui convient, sans point d'ancrage décisif (P20, P34). | K7: 4/5 — Blanc tendu, léger, sans bois : profil qui convient, sans point d'ancrage décisif (P20, P34). | L7: 4/5 — Blanc tendu, léger, sans bois : profil qui convient, sans point d'ancrage décisif (P20, P3). | M7: 2/5 — Blanc sec qui paraît maigre et dur face à la sauce aigre-douce (P22). | N7: 4/5 — La mayonnaise plafonne l'accord (P10, P35) ; acidité et salinité à la hauteur de la pomme verte et du crabe (P23, P9). | O7: 2/5 — Blanc sec trop maigre face au gras (P20) ; sans le sucre qui répond au sel (P4). | P7: 3/5 — Trop léger, il disparaît derrière le plat (P20). | Q7: 4/5 — Le citron de la sauce vierge plafonne l'accord (P11, P35) ; notes d'herbes en miroir de la sauce vierge (P25). | R7: 4/5 — Blanc tendu, léger, sans bois : profil qui convient, sans point d'ancrage décisif (P20, P23). | S7: 4/5 — Blanc tendu, léger, sans bois : profil qui convient, sans point d'ancrage décisif (P20, P3) ; l'émulsion beurre-œuf-citron plafonne l'accord (P10, P35). | T7: 5/5 — Blanc septentrional tendu et sans bois : il coupe le beurre noisette et respecte la sole (P42, P3, P19). | U7: 4/5 — La base mayonnaise plafonne l'accord (P10, P35) ; blanc très tendu à la hauteur des condiments (P23). | V7: 3/5 — Trop léger, il disparaît derrière le plat (P20). | W7: 2/5 — Vin sec qui paraît maigre face à la laque sucrée (P22) ; umami qui durcit l'acidité (P29). | X7: 4/5 — La sauce au citron plafonne l'accord (P11, P35) ; notes herbacées en miroir de la sauge (P25). | Y7: 3/5 — Trop léger, il disparaît derrière le plat (P20). | Z7: 3/5 — Trop léger, il disparaît derrière le plat (P20). | AA7: 3/5 — Trop léger, il disparaît derrière le plat (P20). | AB7: 3/5 — Blanc sans la structure qu'appelle la viande (P21, P20). | AC7: 2/5 — Trop léger, il disparaît derrière le plat (P20). | AD7: 3/5 — Trop léger, il disparaît derrière le plat (P20). | AE7: 2/5 — Trop léger, il disparaît derrière le plat (P20). | AF7: 1/5 — Vin sec face au sucre du dessert : il paraît amer et maigre (P22). | AG7: 1/5 — Vin sec face au sucre du dessert : il paraît amer et maigre (P22, P15). | AH7: 1/5 — Vin sec face au sucre du dessert : il paraît amer et maigre (P22, P15). | AI7: 1/5 — Vin sec face au sucre du dessert : il paraît amer et maigre (P22). | AJ7: 1/5 — Vin sec face au sucre du dessert : il paraît amer et maigre (P22). | AK7: 1/5 — Vin sec face au sucre du dessert : il paraît amer et maigre (P22). | AL7: 1/5 — Vin sec face au sucre du dessert : il paraît amer et maigre (P22). | AM7: 1/5 — Vin sec face au sucre du dessert : il paraît amer et maigre (P22, P15). | AN7: 1/5 — Vin sec face au sucre du dessert : il paraît amer et maigre (P22). | AO7: 1/5 — Vin sec face au sucre du dessert : il paraît amer et maigre (P22, P7, P35). | AP7: 3/5 — Blanc tendu sans bois, sûr sur pâte fraîche ou pressée, sans garantie sur un bleu (P5, P18).
A8: Blancs | B8: L-B02 · Sancerre Henri Bourgeois 2025 | C8: 58 | D8: 3/5 — Blanc correct sur le bœuf cru, mais le sel du parmesan autorise et appelle un rouge léger (P28, P20). | E8: 4/5 — Le citron vert nature plafonne l'accord (P7, P35) ; tension saline d'un vin de bord d'eau sur le bar cru (P9). | F8: 4/5 — Blanc tendu, de poids moyen, sans bois : profil qui convient, sans point d'ancrage décisif (P20, P23) ; l'émulsion à l'œuf de la tartare plafonne l'accord (P10, P35). | G8: 4/5 — Blanc tendu, de poids moyen, sans bois : profil qui convient, sans point d'ancrage décisif (P20, P3). | H8: 4/5 — Le vinaigre à l'échalote plafonne l'accord (P11, P35) ; acidité littorale et salinité en écho à l'iode (P9). | I8: 5/5 — L'acidité coupe le beurre, la salinité répond à l'iode (P9, P3). | J8: 4/5 — Blanc tendu, de poids moyen, sans bois : profil qui convient, sans point d'ancrage décisif (P20, P34). | K8: 4/5 — Blanc tendu, de poids moyen, sans bois : profil qui convient, sans point d'ancrage décisif (P20, P34). | L8: 4/5 — Blanc tendu, de poids moyen, sans bois : profil qui convient, sans point d'ancrage décisif (P20, P3). | M8: 2/5 — Blanc sec qui paraît maigre et dur face à la sauce aigre-douce (P22). | N8: 4/5 — La mayonnaise plafonne l'accord (P10, P35) ; acidité et salinité à la hauteur de la pomme verte et du crabe (P23, P9). | O8: 2/5 — Blanc sec trop maigre face au gras (P20) ; sans le sucre qui répond au sel (P4). | P8: 4/5 — Blanc tendu, de poids moyen, sans bois : profil qui convient, sans point d'ancrage décisif (P20, P3). | Q8: 4/5 — Le citron de la sauce vierge plafonne l'accord (P11, P35) ; notes d'herbes en miroir de la sauce vierge (P25). | R8: 4/5 — Blanc tendu, de poids moyen, sans bois : profil qui convient, sans point d'ancrage décisif (P20, P23). | S8: 4/5 — Blanc tendu, de poids moyen, sans bois : profil qui convient, sans point d'ancrage décisif (P20, P3) ; l'émulsion beurre-œuf-citron plafonne l'accord (P10, P35). | T8: 5/5 — Blanc septentrional tendu et sans bois : il coupe le beurre noisette et respecte la sole (P42, P3, P19). | U8: 4/5 — La base mayonnaise plafonne l'accord (P10, P35) ; blanc très tendu à la hauteur des condiments (P23). | V8: 4/5 — Blanc tendu, de poids moyen, sans bois : profil qui convient, sans point d'ancrage décisif (P20, P3). | W8: 2/5 — Vin sec qui paraît maigre face à la laque sucrée (P22) ; umami qui durcit l'acidité (P29). | X8: 4/5 — La sauce au citron plafonne l'accord (P11, P35) ; notes herbacées en miroir de la sauge (P25). | Y8: 4/5 — Blanc tendu, de poids moyen, sans bois : profil qui convient, sans point d'ancrage décisif (P20, P3). | Z8: 4/5 — Blanc tendu, de poids moyen, sans bois : profil qui convient, sans point d'ancrage décisif (P20, P3). | AA8: 4/5 — Blanc tendu, de poids moyen, sans bois : profil qui convient, sans point d'ancrage décisif (P20, P3). | AB8: 3/5 — Blanc sans la structure qu'appelle la viande (P21, P20). | AC8: 2/5 — Blanc sans la structure qu'appelle la viande (P21, P20). | AD8: 3/5 — Blanc sans la structure qu'appelle la viande (P21, P20). | AE8: 2/5 — Blanc sans la structure qu'appelle la viande (P21, P20). | AF8: 1/5 — Vin sec face au sucre du dessert : il paraît amer et maigre (P22). | AG8: 1/5 — Vin sec face au sucre du dessert : il paraît amer et maigre (P22, P15). | AH8: 1/5 — Vin sec face au sucre du dessert : il paraît amer et maigre (P22, P15). | AI8: 1/5 — Vin sec face au sucre du dessert : il paraît amer et maigre (P22). | AJ8: 1/5 — Vin sec face au sucre du dessert : il paraît amer et maigre (P22). | AK8: 1/5 — Vin sec face au sucre du dessert : il paraît amer et maigre (P22). | AL8: 1/5 — Vin sec face au sucre du dessert : il paraît amer et maigre (P22). | AM8: 1/5 — Vin sec face au sucre du dessert : il paraît amer et maigre (P22, P15). | AN8: 1/5 — Vin sec face au sucre du dessert : il paraît amer et maigre (P22). | AO8: 1/5 — Vin sec face au sucre du dessert : il paraît amer et maigre (P22, P7, P35). | AP8: 3/5 — Blanc tendu sans bois, sûr sur pâte fraîche ou pressée, sans garantie sur un bleu (P5, P18).
A9: Blancs | B9: L-B03 · Pouilly-Fumé de Ladoucette 2024 | C9: 80 | D9: 3/5 — Blanc correct sur le bœuf cru, mais le sel du parmesan autorise et appelle un rouge léger (P28, P20). | E9: 4/5 — Le citron vert nature plafonne l'accord (P7, P35) ; tension saline d'un vin de bord d'eau sur le bar cru (P9). | F9: 4/5 — Blanc tendu, de poids moyen, sans bois : profil qui convient, sans point d'ancrage décisif (P20, P23) ; l'émulsion à l'œuf de la tartare plafonne l'accord (P10, P35). | G9: 5/5 — L'élevage sur lies donne la chair qui répond au beurre noisette, sans bois (P39, P3). | H9: 4/5 — Le vinaigre à l'échalote plafonne l'accord (P11, P35) ; acidité littorale et salinité en écho à l'iode (P9). | I9: 5/5 — L'acidité coupe le beurre, la salinité répond à l'iode (P9, P3). | J9: 4/5 — Blanc tendu, de poids moyen, sans bois : profil qui convient, sans point d'ancrage décisif (P20, P34). | K9: 4/5 — Blanc tendu, de poids moyen, sans bois : profil qui convient, sans point d'ancrage décisif (P20, P34). | L9: 4/5 — Blanc tendu, de poids moyen, sans bois : profil qui convient, sans point d'ancrage décisif (P20, P3). | M9: 2/5 — Blanc sec qui paraît maigre et dur face à la sauce aigre-douce (P22). | N9: 4/5 — La mayonnaise plafonne l'accord (P10, P35) ; acidité et salinité à la hauteur de la pomme verte et du crabe (P23, P9). | O9: 2/5 — Blanc sec trop maigre face au gras (P20) ; sans le sucre qui répond au sel (P4). | P9: 5/5 — Élevé sur lies : chair pour la bisque, acidité pour la crème (P39, P3). | Q9: 4/5 — Le citron de la sauce vierge plafonne l'accord (P11, P35) ; notes d'herbes en miroir de la sauce vierge (P25). | R9: 4/5 — Blanc tendu, de poids moyen, sans bois : profil qui convient, sans point d'ancrage décisif (P20, P23). | S9: 4/5 — L'émulsion beurre-œuf-citron plafonne l'accord (P10, P35) ; l'élevage sur lies donne la chair qui répond à la mousseline (P39). | T9: 5/5 — Blanc septentrional tendu et sans bois : il coupe le beurre noisette et respecte la sole (P42, P3, P19). | U9: 4/5 — La base mayonnaise plafonne l'accord (P10, P35) ; blanc très tendu à la hauteur des condiments (P23). | V9: 4/5 — Blanc tendu, de poids moyen, sans bois : profil qui convient, sans point d'ancrage décisif (P20, P3). | W9: 2/5 — Vin sec qui paraît maigre face à la laque sucrée (P22) ; umami qui durcit l'acidité (P29). | X9: 4/5 — La sauce au citron plafonne l'accord (P11, P35) ; notes herbacées en miroir de la sauge (P25). | Y9: 4/5 — Blanc tendu, de poids moyen, sans bois : profil qui convient, sans point d'ancrage décisif (P20, P3). | Z9: 5/5 — Élevage sur lies : chair et acidité pour la sauce crémée (P39, P42). | AA9: 4/5 — Blanc tendu, de poids moyen, sans bois : profil qui convient, sans point d'ancrage décisif (P20, P3). | AB9: 3/5 — Blanc sans la structure qu'appelle la viande (P21, P20). | AC9: 2/5 — Blanc sans la structure qu'appelle la viande (P21, P20). | AD9: 3/5 — Blanc sans la structure qu'appelle la viande (P21, P20). | AE9: 2/5 — Blanc sans la structure qu'appelle la viande (P21, P20). | AF9: 1/5 — Vin sec face au sucre du dessert : il paraît amer et maigre (P22). | AG9: 1/5 — Vin sec face au sucre du dessert : il paraît amer et maigre (P22, P15). | AH9: 1/5 — Vin sec face au sucre du dessert : il paraît amer et maigre (P22, P15). | AI9: 1/5 — Vin sec face au sucre du dessert : il paraît amer et maigre (P22). | AJ9: 1/5 — Vin sec face au sucre du dessert : il paraît amer et maigre (P22). | AK9: 1/5 — Vin sec face au sucre du dessert : il paraît amer et maigre (P22). | AL9: 1/5 — Vin sec face au sucre du dessert : il paraît amer et maigre (P22). | AM9: 1/5 — Vin sec face au sucre du dessert : il paraît amer et maigre (P22, P15). | AN9: 1/5 — Vin sec face au sucre du dessert : il paraît amer et maigre (P22). | AO9: 1/5 — Vin sec face au sucre du dessert : il paraît amer et maigre (P22, P7, P35). | AP9: 3/5 — Blanc tendu sans bois, sûr sur pâte fraîche ou pressée, sans garantie sur un bleu (P5, P18).
A10: Blancs | B10: L-B04 · Pessac-Léognan Château Carbonnieux blanc 2024 | C10: 120 | D10: 2/5 — Le bois couvre la finesse et amplifie l'amertume (P30). | E10: 2/5 — Le bois couvre la finesse et amplifie l'amertume (P19). | F10: 2/5 — Le bois couvre la finesse et amplifie l'amertume (P34). | G10: 2/5 — Le bois couvre la finesse et amplifie l'amertume (P19). | H10: 2/5 — Le bois couvre la finesse et amplifie l'amertume (P19). | I10: 2/5 — Le bois couvre la finesse et amplifie l'amertume (P19). | J10: 2/5 — Le bois couvre la finesse et amplifie l'amertume (P34). | K10: 2/5 — Le bois couvre la finesse et amplifie l'amertume (P34). | L10: 3/5 — Le bois couvre la finesse et amplifie l'amertume (P19). | M10: 1/5 — Vin sec, rond ou boisé, que le sucre rend amer et alcooleux (P22, P19). | N10: 2/5 — Le bois couvre la finesse et amplifie l'amertume (P19). | O10: 2/5 — Blanc sec trop maigre face au gras (P20) ; sans le sucre qui répond au sel (P4). | P10: 3/5 — Le bois couvre la finesse et amplifie l'amertume (P19). | Q10: 3/5 — Le bois couvre la finesse et amplifie l'amertume (P19). | R10: 3/5 — Le bois couvre la finesse et amplifie l'amertume (P19). | S10: 3/5 — Le bois couvre la finesse et amplifie l'amertume (P19). | T10: 2/5 — Le bois couvre la finesse et amplifie l'amertume (P19). | U10: 2/5 — Le bois couvre la finesse et amplifie l'amertume (P19). | V10: 4/5 — Blanc tendu, de poids moyen, boisé : profil qui convient, sans point d'ancrage décisif (P20, P3). | W10: 2/5 — Vin sec qui paraît maigre face à la laque sucrée (P22) ; umami qui durcit l'acidité (P29). | X10: 3/5 — Le bois couvre la finesse et amplifie l'amertume (P19). | Y10: 4/5 — Blanc tendu, de poids moyen, boisé : profil qui convient, sans point d'ancrage décisif (P20, P3). | Z10: 3/5 — Le bois couvre la finesse et amplifie l'amertume (P19). | AA10: 4/5 — Blanc tendu, de poids moyen, boisé : profil qui convient, sans point d'ancrage décisif (P20, P3). | AB10: 3/5 — Le bois couvre la finesse et amplifie l'amertume (P19). | AC10: 2/5 — Blanc sans la structure qu'appelle la viande (P21, P20). | AD10: 3/5 — Blanc sans la structure qu'appelle la viande (P21, P20). | AE10: 2/5 — Blanc sans la structure qu'appelle la viande (P21, P20). | AF10: 1/5 — Vin sec face au sucre du dessert : il paraît amer et maigre (P22). | AG10: 1/5 — Vin sec face au sucre du dessert : il paraît amer et maigre (P22, P15). | AH10: 1/5 — Vin sec face au sucre du dessert : il paraît amer et maigre (P22, P15). | AI10: 1/5 — Vin sec face au sucre du dessert : il paraît amer et maigre (P22). | AJ10: 1/5 — Vin sec face au sucre du dessert : il paraît amer et maigre (P22). | AK10: 1/5 — Vin sec face au sucre du dessert : il paraît amer et maigre (P22). | AL10: 1/5 — Vin sec face au sucre du dessert : il paraît amer et maigre (P22). | AM10: 1/5 — Vin sec face au sucre du dessert : il paraît amer et maigre (P22, P15). | AN10: 1/5 — Vin sec face au sucre du dessert : il paraît amer et maigre (P22). | AO10: 1/5 — Vin sec face au sucre du dessert : il paraît amer et maigre (P22, P7, P35). | AP10: 3/5 — Blanc tendu et patiné, bien sur pâte pressée ; son bois gêne sur un chèvre (P5, P19, P18).
A11: Blancs | B11: L-B05 · Petit Chablis Pas Si Petit 2023 | C11: 46 | D11: 3/5 — Blanc correct sur le bœuf cru, mais le sel du parmesan autorise et appelle un rouge léger (P28, P20). | E11: 4/5 — Le citron vert nature plafonne l'accord (P7, P35) ; tension saline d'un vin de bord d'eau sur le bar cru (P9). | F11: 4/5 — Blanc tendu, léger, sans bois : profil qui convient, sans point d'ancrage décisif (P20, P23) ; l'émulsion à l'œuf de la tartare plafonne l'accord (P10, P35). | G11: 5/5 — L'élevage sur lies donne la chair qui répond au beurre noisette, sans bois (P39, P3). | H11: 4/5 — Le vinaigre à l'échalote plafonne l'accord (P11, P35) ; acidité littorale et salinité en écho à l'iode (P9). | I11: 5/5 — L'acidité coupe le beurre, la salinité répond à l'iode (P9, P3). | J11: 4/5 — Blanc tendu, léger, sans bois : profil qui convient, sans point d'ancrage décisif (P20, P34). | K11: 4/5 — Blanc tendu, léger, sans bois : profil qui convient, sans point d'ancrage décisif (P20, P34). | L11: 5/5 — Même terroir que l'escargot (origine à confirmer) ; l'acidité coupe le beurre persillé (P2, P3). | M11: 2/5 — Blanc sec qui paraît maigre et dur face à la sauce aigre-douce (P22). | N11: 4/5 — La mayonnaise plafonne l'accord (P10, P35) ; acidité et salinité à la hauteur de la pomme verte et du crabe (P23, P9). | O11: 2/5 — Blanc sec trop maigre face au gras (P20) ; sans le sucre qui répond au sel (P4). | P11: 4/5 — Élevé sur lies : chair pour la bisque, acidité pour la crème (P39, P3) ; trop léger, il disparaît derrière le plat (P20). | Q11: 4/5 — Blanc tendu, léger, sans bois : profil qui convient, sans point d'ancrage décisif (P20, P23) ; le citron de la sauce vierge plafonne l'accord (P11, P35). | R11: 4/5 — Blanc tendu, léger, sans bois : profil qui convient, sans point d'ancrage décisif (P20, P23). | S11: 4/5 — L'émulsion beurre-œuf-citron plafonne l'accord (P10, P35) ; l'élevage sur lies donne la chair qui répond à la mousseline (P39). | T11: 5/5 — Blanc septentrional tendu et sans bois : il coupe le beurre noisette et respecte la sole (P42, P3, P19). | U11: 4/5 — La base mayonnaise plafonne l'accord (P10, P35) ; blanc très tendu à la hauteur des condiments (P23). | V11: 3/5 — Trop léger, il disparaît derrière le plat (P20). | W11: 2/5 — Vin sec qui paraît maigre face à la laque sucrée (P22) ; umami qui durcit l'acidité (P29). | X11: 4/5 — Blanc tendu, léger, sans bois : profil qui convient, sans point d'ancrage décisif (P20, P23) ; la sauce au citron plafonne l'accord (P11, P35). | Y11: 3/5 — Trop léger, il disparaît derrière le plat (P20). | Z11: 4/5 — Élevage sur lies : chair et acidité pour la sauce crémée (P39, P42) ; trop léger, il disparaît derrière le plat (P20). | AA11: 3/5 — Trop léger, il disparaît derrière le plat (P20). | AB11: 3/5 — Blanc sans la structure qu'appelle la viande (P21, P20). | AC11: 2/5 — Trop léger, il disparaît derrière le plat (P20). | AD11: 3/5 — Trop léger, il disparaît derrière le plat (P20). | AE11: 2/5 — Trop léger, il disparaît derrière le plat (P20). | AF11: 1/5 — Vin sec face au sucre du dessert : il paraît amer et maigre (P22). | AG11: 1/5 — Vin sec face au sucre du dessert : il paraît amer et maigre (P22, P15). | AH11: 1/5 — Vin sec face au sucre du dessert : il paraît amer et maigre (P22, P15). | AI11: 1/5 — Vin sec face au sucre du dessert : il paraît amer et maigre (P22). | AJ11: 1/5 — Vin sec face au sucre du dessert : il paraît amer et maigre (P22). | AK11: 1/5 — Vin sec face au sucre du dessert : il paraît amer et maigre (P22). | AL11: 1/5 — Vin sec face au sucre du dessert : il paraît amer et maigre (P22). | AM11: 1/5 — Vin sec face au sucre du dessert : il paraît amer et maigre (P22, P15). | AN11: 1/5 — Vin sec face au sucre du dessert : il paraît amer et maigre (P22). | AO11: 1/5 — Vin sec face au sucre du dessert : il paraît amer et maigre (P22, P7, P35). | AP11: 3/5 — Blanc tendu sans bois, sûr sur pâte fraîche ou pressée, sans garantie sur un bleu (P5, P18).
A12: Blancs | B12: L-B06 · Montagny Millebuis 2022 | C12: 48 | D12: 3/5 — Blanc correct sur le bœuf cru, mais le sel du parmesan autorise et appelle un rouge léger (P28, P20). | E12: 2/5 — Le bois couvre la finesse et amplifie l'amertume (P19) ; acidité trop faible face au citron vert (P23). | F12: 2/5 — Le bois couvre la finesse et amplifie l'amertume (P34) ; acidité trop faible face aux câpres et cornichons (P23). | G12: 2/5 — Le bois couvre la finesse et amplifie l'amertume (P19) ; acidité trop faible face au beurre noisette (P3). | H12: 2/5 — Le bois couvre la finesse et amplifie l'amertume (P19) ; acidité trop faible face à l'iode (P9). | I12: 2/5 — Le bois couvre la finesse et amplifie l'amertume (P19) ; acidité trop faible face au beurre à l'ail (P3). | J12: 2/5 — Le bois couvre la finesse et amplifie l'amertume (P34) ; acidité trop faible face à la friture et le fromage (P34). | K12: 2/5 — Le bois couvre la finesse et amplifie l'amertume (P34) ; acidité trop faible face à la friture (P34). | L12: 5/5 — Même terroir que l'escargot (origine à confirmer) ; l'acidité coupe le beurre persillé (P2, P3). | M12: 2/5 — Blanc sec qui paraît maigre et dur face à la sauce aigre-douce (P22). | N12: 2/5 — Le bois couvre la finesse et amplifie l'amertume (P19) ; acidité trop faible face à la Granny Smith (P23). | O12: 2/5 — Blanc sec trop maigre face au gras (P20) ; sans le sucre qui répond au sel (P4). | P12: 4/5 — Blanc souple, de poids moyen, peu boisé : profil qui convient, sans point d'ancrage décisif (P20, P3). | Q12: 2/5 — Le bois couvre la finesse et amplifie l'amertume (P19) ; acidité trop faible face à la tomate et le citron (P23). | R12: 4/5 — Blanc souple, de poids moyen, peu boisé : profil qui convient, sans point d'ancrage décisif (P20, P23). | S12: 3/5 — Acidité trop faible face à la mousseline (P3). | T12: 2/5 — Le bois couvre la finesse et amplifie l'amertume (P19) ; acidité trop faible face au beurre noisette (P3). | U12: 2/5 — Le bois couvre la finesse et amplifie l'amertume (P19) ; acidité trop faible face aux câpres et cornichons (P23). | V12: 4/5 — Blanc souple, de poids moyen, peu boisé : profil qui convient, sans point d'ancrage décisif (P20, P3). | W12: 2/5 — Vin sec qui paraît maigre face à la laque sucrée (P22) ; umami qui durcit l'acidité (P29). | X12: 2/5 — Le bois couvre la finesse et amplifie l'amertume (P19) ; acidité trop faible face au citron (P23). | Y12: 4/5 — Blanc souple, de poids moyen, peu boisé : profil qui convient, sans point d'ancrage décisif (P20, P3). | Z12: 4/5 — Blanc souple, de poids moyen, peu boisé : profil qui convient, sans point d'ancrage décisif (P20, P3). | AA12: 4/5 — Blanc souple, de poids moyen, peu boisé : profil qui convient, sans point d'ancrage décisif (P20, P3). | AB12: 3/5 — Acidité trop faible face aux condiments (P23). | AC12: 2/5 — Blanc sans la structure qu'appelle la viande (P21, P20). | AD12: 3/5 — Blanc sans la structure qu'appelle la viande (P21, P20). | AE12: 2/5 — Acidité trop faible face au beurre et la réduction vinaigrée (P3). | AF12: 1/5 — Vin sec face au sucre du dessert : il paraît amer et maigre (P22). | AG12: 1/5 — Vin sec face au sucre du dessert : il paraît amer et maigre (P22, P15). | AH12: 1/5 — Vin sec face au sucre du dessert : il paraît amer et maigre (P22, P15). | AI12: 1/5 — Vin sec face au sucre du dessert : il paraît amer et maigre (P22). | AJ12: 1/5 — Vin sec face au sucre du dessert : il paraît amer et maigre (P22). | AK12: 1/5 — Vin sec face au sucre du dessert : il paraît amer et maigre (P22). | AL12: 1/5 — Vin sec face au sucre du dessert : il paraît amer et maigre (P22). | AM12: 1/5 — Vin sec face au sucre du dessert : il paraît amer et maigre (P22, P15). | AN12: 1/5 — Vin sec face au sucre du dessert : il paraît amer et maigre (P22). | AO12: 1/5 — Vin sec face au sucre du dessert : il paraît amer et maigre (P22, P7, P35). | AP12: 2/5 — Blanc peu acide qui manque de tension face au sel et au gras (P5, P3).
A13: Blancs | B13: L-B07 · Bourgogne Chardonnay Nuiton-Beaunoy 2023 | C13: 49 | D13: 3/5 — Blanc correct sur le bœuf cru, mais le sel du parmesan autorise et appelle un rouge léger (P28, P20). | E13: 2/5 — Le bois couvre la finesse et amplifie l'amertume (P19) ; acidité trop faible face au citron vert (P23). | F13: 2/5 — Le bois couvre la finesse et amplifie l'amertume (P34) ; acidité trop faible face aux câpres et cornichons (P23). | G13: 2/5 — Le bois couvre la finesse et amplifie l'amertume (P19) ; acidité trop faible face au beurre noisette (P3). | H13: 2/5 — Le bois couvre la finesse et amplifie l'amertume (P19) ; acidité trop faible face à l'iode (P9). | I13: 2/5 — Le bois couvre la finesse et amplifie l'amertume (P19) ; acidité trop faible face au beurre à l'ail (P3). | J13: 2/5 — Le bois couvre la finesse et amplifie l'amertume (P34) ; acidité trop faible face à la friture et le fromage (P34). | K13: 2/5 — Le bois couvre la finesse et amplifie l'amertume (P34) ; acidité trop faible face à la friture (P34). | L13: 5/5 — Même terroir que l'escargot (origine à confirmer) ; l'acidité coupe le beurre persillé (P2, P3). | M13: 2/5 — Blanc sec qui paraît maigre et dur face à la sauce aigre-douce (P22). | N13: 2/5 — Le bois couvre la finesse et amplifie l'amertume (P19) ; acidité trop faible face à la Granny Smith (P23). | O13: 2/5 — Blanc sec trop maigre face au gras (P20) ; sans le sucre qui répond au sel (P4). | P13: 3/5 — Trop léger, il disparaît derrière le plat (P20). | Q13: 2/5 — Le bois couvre la finesse et amplifie l'amertume (P19) ; acidité trop faible face à la tomate et le citron (P23). | R13: 4/5 — Blanc souple, léger, peu boisé : profil qui convient, sans point d'ancrage décisif (P20, P23). | S13: 3/5 — Acidité trop faible face à la mousseline (P3). | T13: 2/5 — Le bois couvre la finesse et amplifie l'amertume (P19) ; acidité trop faible face au beurre noisette (P3). | U13: 2/5 — Le bois couvre la finesse et amplifie l'amertume (P19) ; acidité trop faible face aux câpres et cornichons (P23). | V13: 3/5 — Trop léger, il disparaît derrière le plat (P20). | W13: 2/5 — Vin sec qui paraît maigre face à la laque sucrée (P22) ; umami qui durcit l'acidité (P29). | X13: 2/5 — Le bois couvre la finesse et amplifie l'amertume (P19) ; acidité trop faible face au citron (P23). | Y13: 3/5 — Trop léger, il disparaît derrière le plat (P20). | Z13: 3/5 — Trop léger, il disparaît derrière le plat (P20). | AA13: 3/5 — Trop léger, il disparaît derrière le plat (P20). | AB13: 3/5 — Acidité trop faible face aux condiments (P23). | AC13: 2/5 — Trop léger, il disparaît derrière le plat (P20). | AD13: 3/5 — Trop léger, il disparaît derrière le plat (P20). | AE13: 2/5 — Acidité trop faible face au beurre et la réduction vinaigrée (P3) ; trop léger, il disparaît derrière le plat (P20). | AF13: 1/5 — Vin sec face au sucre du dessert : il paraît amer et maigre (P22). | AG13: 1/5 — Vin sec face au sucre du dessert : il paraît amer et maigre (P22, P15). | AH13: 1/5 — Vin sec face au sucre du dessert : il paraît amer et maigre (P22, P15). | AI13: 1/5 — Vin sec face au sucre du dessert : il paraît amer et maigre (P22). | AJ13: 1/5 — Vin sec face au sucre du dessert : il paraît amer et maigre (P22). | AK13: 1/5 — Vin sec face au sucre du dessert : il paraît amer et maigre (P22). | AL13: 1/5 — Vin sec face au sucre du dessert : il paraît amer et maigre (P22). | AM13: 1/5 — Vin sec face au sucre du dessert : il paraît amer et maigre (P22, P15). | AN13: 1/5 — Vin sec face au sucre du dessert : il paraît amer et maigre (P22). | AO13: 1/5 — Vin sec face au sucre du dessert : il paraît amer et maigre (P22, P7, P35). | AP13: 2/5 — Blanc peu acide qui manque de tension face au sel et au gras (P5, P3).
A14: Blancs | B14: L-B08 · Puligny-Montrachet 1er Cru Champ Gain 2019 | C14: 195 | D14: 1/5 — Le bois couvre la finesse et amplifie l'amertume (P30) ; trop puissant, il écrase le plat (P20). | E14: 1/5 — Le bois couvre la finesse et amplifie l'amertume (P19) ; trop puissant, il écrase le plat (P20). | F14: 2/5 — Le bois couvre la finesse et amplifie l'amertume (P34). | G14: 2/5 — Le bois couvre la finesse et amplifie l'amertume (P19). | H14: 1/5 — Le bois couvre la finesse et amplifie l'amertume (P19) ; trop puissant, il écrase le plat (P20). | I14: 2/5 — Le bois couvre la finesse et amplifie l'amertume (P19). | J14: 2/5 — Le bois couvre la finesse et amplifie l'amertume (P34). | K14: 2/5 — Le bois couvre la finesse et amplifie l'amertume (P34). | L14: 3/5 — Le bois couvre la finesse et amplifie l'amertume (P19). | M14: 1/5 — Vin sec, rond ou boisé, que le sucre rend amer et alcooleux (P22, P19). | N14: 1/5 — Le bois couvre la finesse et amplifie l'amertume (P19) ; trop puissant, il écrase le plat (P20). | O14: 3/5 — Blanc ample qui tient le gras (P20) ; mais sans le sucre qui ferait l'accord (P4). | P14: 3/5 — Le bois couvre la finesse et amplifie l'amertume (P19). | Q14: 2/5 — Le bois couvre la finesse et amplifie l'amertume (P19). | R14: 3/5 — Le bois couvre la finesse et amplifie l'amertume (P19). | S14: 3/5 — Le bois couvre la finesse et amplifie l'amertume (P19). | T14: 2/5 — Le bois couvre la finesse et amplifie l'amertume (P19). | U14: 2/5 — Le bois couvre la finesse et amplifie l'amertume (P19). | V14: 5/5 — Blanc ample et patiné qui répond à l'onctuosité et au sous-bois (P40, P25). | W14: 2/5 — Vin sec qui paraît maigre face à la laque sucrée (P22) ; umami qui durcit l'acidité (P29). | X14: 2/5 — Le bois couvre la finesse et amplifie l'amertume (P19). | Y14: 5/5 — Blanc ample et patiné en miroir des morilles ; bois fondu à sa place sur la crème (P25, P19). | Z14: 3/5 — Le bois couvre la finesse et amplifie l'amertume (P19). | AA14: 4/5 — Blanc tendu, ample, boisé, patiné : profil qui convient, sans point d'ancrage décisif (P20, P3). | AB14: 3/5 — Le bois couvre la finesse et amplifie l'amertume (P19). | AC14: 2/5 — Blanc sans la structure qu'appelle la viande (P21, P20). | AD14: 3/5 — Blanc sans la structure qu'appelle la viande (P21, P20). | AE14: 2/5 — Blanc sans la structure qu'appelle la viande (P21, P20). | AF14: 1/5 — Vin sec face au sucre du dessert : il paraît amer et maigre (P22). | AG14: 1/5 — Vin sec face au sucre du dessert : il paraît amer et maigre (P22, P15). | AH14: 1/5 — Vin sec face au sucre du dessert : il paraît amer et maigre (P22, P15). | AI14: 1/5 — Vin sec face au sucre du dessert : il paraît amer et maigre (P22). | AJ14: 1/5 — Vin sec face au sucre du dessert : il paraît amer et maigre (P22). | AK14: 1/5 — Vin sec face au sucre du dessert : il paraît amer et maigre (P22). | AL14: 1/5 — Vin sec face au sucre du dessert : il paraît amer et maigre (P22). | AM14: 1/5 — Vin sec face au sucre du dessert : il paraît amer et maigre (P22, P15). | AN14: 1/5 — Vin sec face au sucre du dessert : il paraît amer et maigre (P22). | AO14: 1/5 — Vin sec face au sucre du dessert : il paraît amer et maigre (P22, P7, P35). | AP14: 3/5 — Blanc tendu et patiné, bien sur pâte pressée ; son bois gêne sur un chèvre (P5, P19, P18).
A15: Blancs | B15: L-B09 · Puligny-Montrachet 1er Cru Les Folatières 2017 | C15: 395 | D15: 1/5 — Le bois couvre la finesse et amplifie l'amertume (P30) ; trop puissant, il écrase le plat (P20). | E15: 1/5 — Le bois couvre la finesse et amplifie l'amertume (P19) ; trop puissant, il écrase le plat (P20). | F15: 2/5 — Le bois couvre la finesse et amplifie l'amertume (P34). | G15: 2/5 — Le bois couvre la finesse et amplifie l'amertume (P19). | H15: 1/5 — Le bois couvre la finesse et amplifie l'amertume (P19) ; trop puissant, il écrase le plat (P20). | I15: 2/5 — Le bois couvre la finesse et amplifie l'amertume (P19). | J15: 2/5 — Le bois couvre la finesse et amplifie l'amertume (P34). | K15: 2/5 — Le bois couvre la finesse et amplifie l'amertume (P34). | L15: 3/5 — Le bois couvre la finesse et amplifie l'amertume (P19). | M15: 1/5 — Vin sec, rond ou boisé, que le sucre rend amer et alcooleux (P22, P19). | N15: 1/5 — Le bois couvre la finesse et amplifie l'amertume (P19) ; trop puissant, il écrase le plat (P20). | O15: 3/5 — Blanc ample qui tient le gras (P20) ; mais sans le sucre qui ferait l'accord (P4). | P15: 3/5 — Le bois couvre la finesse et amplifie l'amertume (P19). | Q15: 2/5 — Le bois couvre la finesse et amplifie l'amertume (P19). | R15: 3/5 — Le bois couvre la finesse et amplifie l'amertume (P19). | S15: 3/5 — Le bois couvre la finesse et amplifie l'amertume (P19). | T15: 2/5 — Le bois couvre la finesse et amplifie l'amertume (P19). | U15: 2/5 — Le bois couvre la finesse et amplifie l'amertume (P19). | V15: 4/5 — Blanc tendu, ample, boisé, patiné : profil qui convient, sans point d'ancrage décisif (P20, P3). | W15: 2/5 — Vin sec qui paraît maigre face à la laque sucrée (P22) ; umami qui durcit l'acidité (P29). | X15: 2/5 — Le bois couvre la finesse et amplifie l'amertume (P19). | Y15: 4/5 — Blanc tendu, ample, boisé, patiné : profil qui convient, sans point d'ancrage décisif (P20, P3). | Z15: 3/5 — Le bois couvre la finesse et amplifie l'amertume (P19). | AA15: 4/5 — Blanc tendu, ample, boisé, patiné : profil qui convient, sans point d'ancrage décisif (P20, P3). | AB15: 3/5 — Le bois couvre la finesse et amplifie l'amertume (P19). | AC15: 2/5 — Blanc sans la structure qu'appelle la viande (P21, P20). | AD15: 3/5 — Blanc sans la structure qu'appelle la viande (P21, P20). | AE15: 2/5 — Blanc sans la structure qu'appelle la viande (P21, P20). | AF15: 1/5 — Vin sec face au sucre du dessert : il paraît amer et maigre (P22). | AG15: 1/5 — Vin sec face au sucre du dessert : il paraît amer et maigre (P22, P15). | AH15: 1/5 — Vin sec face au sucre du dessert : il paraît amer et maigre (P22, P15). | AI15: 1/5 — Vin sec face au sucre du dessert : il paraît amer et maigre (P22). | AJ15: 1/5 — Vin sec face au sucre du dessert : il paraît amer et maigre (P22). | AK15: 1/5 — Vin sec face au sucre du dessert : il paraît amer et maigre (P22). | AL15: 1/5 — Vin sec face au sucre du dessert : il paraît amer et maigre (P22). | AM15: 1/5 — Vin sec face au sucre du dessert : il paraît amer et maigre (P22, P15). | AN15: 1/5 — Vin sec face au sucre du dessert : il paraît amer et maigre (P22). | AO15: 1/5 — Vin sec face au sucre du dessert : il paraît amer et maigre (P22, P7, P35). | AP15: 3/5 — Blanc tendu et patiné, bien sur pâte pressée ; son bois gêne sur un chèvre (P5, P19, P18).
A16: Blancs | B16: L-B10 · Chassagne-Montrachet 1er Cru Les Chenevottes 2020 | C16: 240 | D16: 1/5 — Le bois couvre la finesse et amplifie l'amertume (P30) ; trop puissant, il écrase le plat (P20). | E16: 1/5 — Le bois couvre la finesse et amplifie l'amertume (P19) ; acidité trop faible face au citron vert (P23) ; trop puissant, il écrase le plat (P20). | F16: 1/5 — Le bois couvre la finesse et amplifie l'amertume (P34) ; acidité trop faible face aux câpres et cornichons (P23). | G16: 1/5 — Le bois couvre la finesse et amplifie l'amertume (P19) ; acidité trop faible face au beurre noisette (P3). | H16: 1/5 — Le bois couvre la finesse et amplifie l'amertume (P19) ; acidité trop faible face à l'iode (P9) ; trop puissant, il écrase le plat (P20). | I16: 1/5 — Le bois couvre la finesse et amplifie l'amertume (P19) ; acidité trop faible face au beurre à l'ail (P3). | J16: 1/5 — Le bois couvre la finesse et amplifie l'amertume (P34) ; acidité trop faible face à la friture et le fromage (P34). | K16: 1/5 — Le bois couvre la finesse et amplifie l'amertume (P34) ; acidité trop faible face à la friture (P34). | L16: 3/5 — Le bois couvre la finesse et amplifie l'amertume (P19). | M16: 1/5 — Vin sec, rond ou boisé, que le sucre rend amer et alcooleux (P22, P19). | N16: 1/5 — Le bois couvre la finesse et amplifie l'amertume (P19) ; acidité trop faible face à la Granny Smith (P23) ; trop puissant, il écrase le plat (P20). | O16: 3/5 — Blanc ample qui tient le gras (P20) ; mais sans le sucre qui ferait l'accord (P4). | P16: 3/5 — Le bois couvre la finesse et amplifie l'amertume (P19). | Q16: 1/5 — Le bois couvre la finesse et amplifie l'amertume (P19) ; acidité trop faible face à la tomate et le citron (P23). | R16: 3/5 — Le bois couvre la finesse et amplifie l'amertume (P19). | S16: 2/5 — Le bois couvre la finesse et amplifie l'amertume (P19) ; acidité trop faible face à la mousseline (P3). | T16: 1/5 — Le bois couvre la finesse et amplifie l'amertume (P19) ; acidité trop faible face au beurre noisette (P3). | U16: 1/5 — Le bois couvre la finesse et amplifie l'amertume (P19) ; acidité trop faible face aux câpres et cornichons (P23). | V16: 4/5 — Blanc souple, ample, boisé : profil qui convient, sans point d'ancrage décisif (P20, P3). | W16: 2/5 — Vin sec qui paraît maigre face à la laque sucrée (P22) ; umami qui durcit l'acidité (P29). | X16: 1/5 — Le bois couvre la finesse et amplifie l'amertume (P19) ; acidité trop faible face au citron (P23). | Y16: 4/5 — Blanc souple, ample, boisé : profil qui convient, sans point d'ancrage décisif (P20, P3). | Z16: 3/5 — Le bois couvre la finesse et amplifie l'amertume (P19). | AA16: 4/5 — Blanc souple, ample, boisé : profil qui convient, sans point d'ancrage décisif (P20, P3). | AB16: 2/5 — Le bois couvre la finesse et amplifie l'amertume (P19) ; acidité trop faible face aux condiments (P23). | AC16: 2/5 — Blanc sans la structure qu'appelle la viande (P21, P20). | AD16: 3/5 — Blanc sans la structure qu'appelle la viande (P21, P20). | AE16: 2/5 — Acidité trop faible face au beurre et la réduction vinaigrée (P3). | AF16: 1/5 — Vin sec face au sucre du dessert : il paraît amer et maigre (P22). | AG16: 1/5 — Vin sec face au sucre du dessert : il paraît amer et maigre (P22, P15). | AH16: 1/5 — Vin sec face au sucre du dessert : il paraît amer et maigre (P22, P15). | AI16: 1/5 — Vin sec face au sucre du dessert : il paraît amer et maigre (P22). | AJ16: 1/5 — Vin sec face au sucre du dessert : il paraît amer et maigre (P22). | AK16: 1/5 — Vin sec face au sucre du dessert : il paraît amer et maigre (P22). | AL16: 1/5 — Vin sec face au sucre du dessert : il paraît amer et maigre (P22). | AM16: 1/5 — Vin sec face au sucre du dessert : il paraît amer et maigre (P22, P15). | AN16: 1/5 — Vin sec face au sucre du dessert : il paraît amer et maigre (P22). | AO16: 1/5 — Vin sec face au sucre du dessert : il paraît amer et maigre (P22, P7, P35). | AP16: 2/5 — Blanc peu acide qui manque de tension face au sel et au gras (P5, P3).
A17: Blancs | B17: L-B11 · Beaune 1er Cru Clos des Mouches blanc 2017 | C17: 250 | D17: 1/5 — Le bois couvre la finesse et amplifie l'amertume (P30) ; trop puissant, il écrase le plat (P20). | E17: 1/5 — Le bois couvre la finesse et amplifie l'amertume (P19) ; acidité trop faible face au citron vert (P23) ; trop puissant, il écrase le plat (P20). | F17: 1/5 — Le bois couvre la finesse et amplifie l'amertume (P34) ; acidité trop faible face aux câpres et cornichons (P23). | G17: 1/5 — Le bois couvre la finesse et amplifie l'amertume (P19) ; acidité trop faible face au beurre noisette (P3). | H17: 1/5 — Le bois couvre la finesse et amplifie l'amertume (P19) ; acidité trop faible face à l'iode (P9) ; trop puissant, il écrase le plat (P20). | I17: 1/5 — Le bois couvre la finesse et amplifie l'amertume (P19) ; acidité trop faible face au beurre à l'ail (P3). | J17: 1/5 — Le bois couvre la finesse et amplifie l'amertume (P34) ; acidité trop faible face à la friture et le fromage (P34). | K17: 1/5 — Le bois couvre la finesse et amplifie l'amertume (P34) ; acidité trop faible face à la friture (P34). | L17: 3/5 — Le bois couvre la finesse et amplifie l'amertume (P19). | M17: 1/5 — Vin sec, rond ou boisé, que le sucre rend amer et alcooleux (P22, P19). | N17: 1/5 — Le bois couvre la finesse et amplifie l'amertume (P19) ; acidité trop faible face à la Granny Smith (P23) ; trop puissant, il écrase le plat (P20). | O17: 3/5 — Blanc ample qui tient le gras (P20) ; mais sans le sucre qui ferait l'accord (P4). | P17: 3/5 — Le bois couvre la finesse et amplifie l'amertume (P19). | Q17: 1/5 — Le bois couvre la finesse et amplifie l'amertume (P19) ; acidité trop faible face à la tomate et le citron (P23). | R17: 3/5 — Le bois couvre la finesse et amplifie l'amertume (P19). | S17: 2/5 — Le bois couvre la finesse et amplifie l'amertume (P19) ; acidité trop faible face à la mousseline (P3). | T17: 1/5 — Le bois couvre la finesse et amplifie l'amertume (P19) ; acidité trop faible face au beurre noisette (P3). | U17: 1/5 — Le bois couvre la finesse et amplifie l'amertume (P19) ; acidité trop faible face aux câpres et cornichons (P23). | V17: 5/5 — Blanc ample et patiné qui répond à l'onctuosité et au sous-bois (P40, P25). | W17: 2/5 — Vin sec qui paraît maigre face à la laque sucrée (P22) ; umami qui durcit l'acidité (P29). | X17: 1/5 — Le bois couvre la finesse et amplifie l'amertume (P19) ; acidité trop faible face au citron (P23). | Y17: 5/5 — Blanc ample et patiné en miroir des morilles ; bois fondu à sa place sur la crème (P25, P19). | Z17: 3/5 — Le bois couvre la finesse et amplifie l'amertume (P19). | AA17: 4/5 — Blanc souple, ample, boisé, patiné : profil qui convient, sans point d'ancrage décisif (P20, P3). | AB17: 2/5 — Le bois couvre la finesse et amplifie l'amertume (P19) ; acidité trop faible face aux condiments (P23). | AC17: 2/5 — Blanc sans la structure qu'appelle la viande (P21, P20). | AD17: 3/5 — Blanc sans la structure qu'appelle la viande (P21, P20). | AE17: 2/5 — Acidité trop faible face au beurre et la réduction vinaigrée (P3). | AF17: 1/5 — Vin sec face au sucre du dessert : il paraît amer et maigre (P22). | AG17: 1/5 — Vin sec face au sucre du dessert : il paraît amer et maigre (P22, P15). | AH17: 1/5 — Vin sec face au sucre du dessert : il paraît amer et maigre (P22, P15). | AI17: 1/5 — Vin sec face au sucre du dessert : il paraît amer et maigre (P22). | AJ17: 1/5 — Vin sec face au sucre du dessert : il paraît amer et maigre (P22). | AK17: 1/5 — Vin sec face au sucre du dessert : il paraît amer et maigre (P22). | AL17: 1/5 — Vin sec face au sucre du dessert : il paraît amer et maigre (P22). | AM17: 1/5 — Vin sec face au sucre du dessert : il paraît amer et maigre (P22, P15). | AN17: 1/5 — Vin sec face au sucre du dessert : il paraît amer et maigre (P22). | AO17: 1/5 — Vin sec face au sucre du dessert : il paraît amer et maigre (P22, P7, P35). | AP17: 3/5 — Blanc ample et patiné, bien sur pâte pressée affinée, lourd sur pâte fraîche (P5, P18).
A18: Blancs | B18: L-B12 · Meursault Les Tessons 2018 | C18: 285 | D18: 1/5 — Le bois couvre la finesse et amplifie l'amertume (P30) ; trop puissant, il écrase le plat (P20). | E18: 1/5 — Le bois couvre la finesse et amplifie l'amertume (P19) ; acidité trop faible face au citron vert (P23) ; trop puissant, il écrase le plat (P20). | F18: 1/5 — Le bois couvre la finesse et amplifie l'amertume (P34) ; acidité trop faible face aux câpres et cornichons (P23). | G18: 1/5 — Le bois couvre la finesse et amplifie l'amertume (P19) ; acidité trop faible face au beurre noisette (P3). | H18: 1/5 — Le bois couvre la finesse et amplifie l'amertume (P19) ; acidité trop faible face à l'iode (P9) ; trop puissant, il écrase le plat (P20). | I18: 1/5 — Le bois couvre la finesse et amplifie l'amertume (P19) ; acidité trop faible face au beurre à l'ail (P3). | J18: 1/5 — Le bois couvre la finesse et amplifie l'amertume (P34) ; acidité trop faible face à la friture et le fromage (P34). | K18: 1/5 — Le bois couvre la finesse et amplifie l'amertume (P34) ; acidité trop faible face à la friture (P34). | L18: 3/5 — Le bois couvre la finesse et amplifie l'amertume (P19). | M18: 1/5 — Vin sec, rond ou boisé, que le sucre rend amer et alcooleux (P22, P19). | N18: 1/5 — Le bois couvre la finesse et amplifie l'amertume (P19) ; acidité trop faible face à la Granny Smith (P23) ; trop puissant, il écrase le plat (P20). | O18: 3/5 — Blanc ample qui tient le gras (P20) ; mais sans le sucre qui ferait l'accord (P4). | P18: 3/5 — Le bois couvre la finesse et amplifie l'amertume (P19). | Q18: 1/5 — Le bois couvre la finesse et amplifie l'amertume (P19) ; acidité trop faible face à la tomate et le citron (P23). | R18: 3/5 — Le bois couvre la finesse et amplifie l'amertume (P19). | S18: 2/5 — Le bois couvre la finesse et amplifie l'amertume (P19) ; acidité trop faible face à la mousseline (P3). | T18: 1/5 — Le bois couvre la finesse et amplifie l'amertume (P19) ; acidité trop faible face au beurre noisette (P3). | U18: 1/5 — Le bois couvre la finesse et amplifie l'amertume (P19) ; acidité trop faible face aux câpres et cornichons (P23). | V18: 5/5 — Blanc ample et patiné qui répond à l'onctuosité et au sous-bois (P40, P25). | W18: 2/5 — Vin sec qui paraît maigre face à la laque sucrée (P22) ; umami qui durcit l'acidité (P29). | X18: 1/5 — Le bois couvre la finesse et amplifie l'amertume (P19) ; acidité trop faible face au citron (P23). | Y18: 5/5 — Blanc ample et patiné en miroir des morilles ; bois fondu à sa place sur la crème (P25, P19). | Z18: 3/5 — Le bois couvre la finesse et amplifie l'amertume (P19). | AA18: 4/5 — Blanc souple, ample, boisé, patiné : profil qui convient, sans point d'ancrage décisif (P20, P3). | AB18: 2/5 — Le bois couvre la finesse et amplifie l'amertume (P19) ; acidité trop faible face aux condiments (P23). | AC18: 2/5 — Blanc sans la structure qu'appelle la viande (P21, P20). | AD18: 3/5 — Blanc sans la structure qu'appelle la viande (P21, P20). | AE18: 2/5 — Acidité trop faible face au beurre et la réduction vinaigrée (P3). | AF18: 1/5 — Vin sec face au sucre du dessert : il paraît amer et maigre (P22). | AG18: 1/5 — Vin sec face au sucre du dessert : il paraît amer et maigre (P22, P15). | AH18: 1/5 — Vin sec face au sucre du dessert : il paraît amer et maigre (P22, P15). | AI18: 1/5 — Vin sec face au sucre du dessert : il paraît amer et maigre (P22). | AJ18: 1/5 — Vin sec face au sucre du dessert : il paraît amer et maigre (P22). | AK18: 1/5 — Vin sec face au sucre du dessert : il paraît amer et maigre (P22). | AL18: 1/5 — Vin sec face au sucre du dessert : il paraît amer et maigre (P22). | AM18: 1/5 — Vin sec face au sucre du dessert : il paraît amer et maigre (P22, P15). | AN18: 1/5 — Vin sec face au sucre du dessert : il paraît amer et maigre (P22). | AO18: 1/5 — Vin sec face au sucre du dessert : il paraît amer et maigre (P22, P7, P35). | AP18: 3/5 — Blanc ample et patiné, bien sur pâte pressée affinée, lourd sur pâte fraîche (P5, P18).
... A27: Blancs | B27: L-B21 · Chablis Saint-Pierre 2024 · 37,5 cl | C27: 28 | D27: 3/5 — Blanc correct sur le bœuf cru, mais le sel du parmesan autorise et appelle un rouge léger (P28, P20). | E27: 4/5 — Le citron vert nature plafonne l'accord (P7, P35) ; tension saline d'un vin de bord d'eau sur le bar cru (P9). | F27: 4/5 — Blanc tendu, léger, sans bois : profil qui convient, sans point d'ancrage décisif (P20, P23) ; l'émulsion à l'œuf de la tartare plafonne l'accord (P10, P35). | G27: 4/5 — Blanc tendu, léger, sans bois : profil qui convient, sans point d'ancrage décisif (P20, P3). | H27: 4/5 — Le vinaigre à l'échalote plafonne l'accord (P11, P35) ; acidité littorale et salinité en écho à l'iode (P9). | I27: 5/5 — L'acidité coupe le beurre, la salinité répond à l'iode (P9, P3). | J27: 4/5 — Blanc tendu, léger, sans bois : profil qui convient, sans point d'ancrage décisif (P20, P34). | K27: 4/5 — Blanc tendu, léger, sans bois : profil qui convient, sans point d'ancrage décisif (P20, P34). | L27: 5/5 — Même terroir que l'escargot (origine à confirmer) ; l'acidité coupe le beurre persillé (P2, P3). | M27: 2/5 — Blanc sec qui paraît maigre et dur face à la sauce aigre-douce (P22). | N27: 4/5 — La mayonnaise plafonne l'accord (P10, P35) ; acidité et salinité à la hauteur de la pomme verte et du crabe (P23, P9). | O27: 2/5 — Blanc sec trop maigre face au gras (P20) ; sans le sucre qui répond au sel (P4). | P27: 3/5 — Trop léger, il disparaît derrière le plat (P20). | Q27: 4/5 — Blanc tendu, léger, sans bois : profil qui convient, sans point d'ancrage décisif (P20, P23) ; le citron de la sauce vierge plafonne l'accord (P11, P35). | R27: 4/5 — Blanc tendu, léger, sans bois : profil qui convient, sans point d'ancrage décisif (P20, P23). | S27: 4/5 — Blanc tendu, léger, sans bois : profil qui convient, sans point d'ancrage décisif (P20, P3) ; l'émulsion beurre-œuf-citron plafonne l'accord (P10, P35). | T27: 5/5 — Blanc septentrional tendu et sans bois : il coupe le beurre noisette et respecte la sole (P42, P3, P19). | U27: 4/5 — La base mayonnaise plafonne l'accord (P10, P35) ; blanc très tendu à la hauteur des condiments (P23). | V27: 3/5 — Trop léger, il disparaît derrière le plat (P20). | W27: 2/5 — Vin sec qui paraît maigre face à la laque sucrée (P22) ; umami qui durcit l'acidité (P29). | X27: 4/5 — Blanc tendu, léger, sans bois : profil qui convient, sans point d'ancrage décisif (P20, P23) ; la sauce au citron plafonne l'accord (P11, P35). | Y27: 3/5 — Trop léger, il disparaît derrière le plat (P20). | Z27: 3/5 — Trop léger, il disparaît derrière le plat (P20). | AA27: 3/5 — Trop léger, il disparaît derrière le plat (P20). | AB27: 3/5 — Blanc sans la structure qu'appelle la viande (P21, P20). | AC27: 2/5 — Trop léger, il disparaît derrière le plat (P20). | AD27: 3/5 — Trop léger, il disparaît derrière le plat (P20). | AE27: 2/5 — Trop léger, il disparaît derrière le plat (P20). | AF27: 1/5 — Vin sec face au sucre du dessert : il paraît amer et maigre (P22). | AG27: 1/5 — Vin sec face au sucre du dessert : il paraît amer et maigre (P22, P15). | AH27: 1/5 — Vin sec face au sucre du dessert : il paraît amer et maigre (P22, P15). | AI27: 1/5 — Vin sec face au sucre du dessert : il paraît amer et maigre (P22). | AJ27: 1/5 — Vin sec face au sucre du dessert : il paraît amer et maigre (P22). | AK27: 1/5 — Vin sec face au sucre du dessert : il paraît amer et maigre (P22). | AL27: 1/5 — Vin sec face au sucre du dessert : il paraît amer et maigre (P22). | AM27: 1/5 — Vin sec face au sucre du dessert : il paraît amer et maigre (P22, P15). | AN27: 1/5 — Vin sec face au sucre du dessert : il paraît amer et maigre (P22). | AO27: 1/5 — Vin sec face au sucre du dessert : il paraît amer et maigre (P22, P7, P35). | AP27: 3/5 — Blanc tendu sans bois, sûr sur pâte fraîche ou pressée, sans garantie sur un bleu (P5, P18).
A28: Rouges | B28: ROUGES
A29: Rouges | B29: L-R01 · Chiroubles Domaine Piron 2024 | C29: 50 | D29: 5/5 — Rouge léger, vif et peu tannique : il épouse le bœuf cru sans durcir sur la roquette (P30, P28, P37). | E29: 2/5 — Rouge : son tanin durcit au contact du poisson cru (P27) ; seule sa légèreté limite les dégâts (P20). | F29: 2/5 — Rouge : son tanin durcit au contact de la panure (P34) ; seule sa légèreté limite les dégâts (P20). | G29: 2/5 — Rouge : son tanin durcit au contact de la chair fine (P24) ; seule sa légèreté limite les dégâts (P20). | H29: 2/5 — Rouge : son tanin durcit au contact de l'iode (goût métallique) (P27) ; seule sa légèreté limite les dégâts (P20). | I29: 2/5 — Rouge : son tanin durcit au contact de l'iode (P27) ; seule sa légèreté limite les dégâts (P20). | J29: 2/5 — Rouge : son tanin durcit au contact du fromage, ingrédient principal (P5) ; seule sa légèreté limite les dégâts (P20). | K29: 2/5 — Rouge : son tanin durcit au contact de la panure et l'iode (P34) ; seule sa légèreté limite les dégâts (P20). | L29: 4/5 — Rouge léger très peu tannique : profil qui convient, sans point d'ancrage décisif (P20, P29). | M29: 1/5 — Tanin durci par le sucre et le vinaigre de la sauce (P22, P23). | N29: 2/5 — Rouge : son tanin durcit au contact du curry (P6) ; seule sa légèreté limite les dégâts (P20). | O29: 2/5 — Rouge sec sans le sucre qui répond au sel (P4) ; tanin léger, mais fruit perdu sur le gras (P20). | P29: 2/5 — Rouge : son tanin durcit au contact du homard (P27) ; seule sa légèreté limite les dégâts (P20). | Q29: 4/5 — Rouge léger très peu tannique : profil qui convient, sans point d'ancrage décisif (P20, P27) ; le citron de la sauce vierge plafonne l'accord (P11, P35). | R29: 5/5 — Rouge léger servi frais sur un thon charnu, tanin discret face à l'umami (P27, P26). | S29: 2/5 — Rouge : son tanin durcit au contact du cabillaud et les crevettes (P27) ; seule sa légèreté limite les dégâts (P20). | T29: 2/5 — Rouge : son tanin durcit au contact de la sole (P27) ; seule sa légèreté limite les dégâts (P20). | U29: 3/5 — Rouge léger très peu tannique : profil qui convient, sans point d'ancrage décisif (P20, P27). | V29: 3/5 — Trop léger, il disparaît derrière le plat (P20). | W29: 2/5 — Tanin léger, mais durci par l'umami et le sucre (P29, P22). | X29: 2/5 — Rouge : son tanin durcit au contact du beurre et le citron (P3) ; seule sa légèreté limite les dégâts (P20). | Y29: 3/5 — Trop léger, il disparaît derrière le plat (P20). | Z29: 2/5 — Rouge : son tanin durcit au contact de la sauce blanche (P24) ; seule sa légèreté limite les dégâts (P20). | AA29: 3/5 — Trop léger, il disparaît derrière le plat (P20). | AB29: 4/5 — L'émulsion à l'œuf plafonne l'accord (P10, P35) ; rouge juteux et vif, tanins fins pour la viande crue (P21, P23). | AC29: 3/5 — Trop léger, il disparaît derrière le plat (P20). | AD29: 3/5 — Trop léger, il disparaît derrière le plat (P20). | AE29: 4/5 — Trame acide et tanins souples face à la béarnaise (P3, P21) ; trop léger, il disparaît derrière le plat (P20). | AF29: 1/5 — Vin sec face au sucre du dessert : il paraît amer et maigre (P22). | AG29: 1/5 — Vin sec face au sucre du dessert : il paraît amer et maigre (P22, P15). | AH29: 1/5 — Vin sec face au sucre du dessert : il paraît amer et maigre (P22, P15). | AI29: 1/5 — Vin sec face au sucre du dessert : il paraît amer et maigre (P22). | AJ29: 1/5 — Vin sec face au sucre du dessert : il paraît amer et maigre (P22). | AK29: 1/5 — Vin sec face au sucre du dessert : il paraît amer et maigre (P22). | AL29: 1/5 — Vin sec face au sucre du dessert : il paraît amer et maigre (P22). | AM29: 1/5 — Vin sec face au sucre du dessert : il paraît amer et maigre (P22, P15). | AN29: 1/5 — Vin sec face au sucre du dessert : il paraît amer et maigre (P22). | AO29: 1/5 — Vin sec face au sucre du dessert : il paraît amer et maigre (P22, P7, P35). | AP29: 2/5 — Rouge léger, mais le fromage repousse le tanin (P5).
A30: Rouges | B30: L-R02 · Saint-Amour Domaine Piron 2024 | C30: 54 | D30: 4/5 — Rouge de poids moyen aux tanins fins : profil qui convient, sans point d'ancrage décisif (P20, P30). | E30: 1/5 — Rouge : son tanin durcit au contact du poisson cru (P27). | F30: 1/5 — Rouge : son tanin durcit au contact de la panure (P34). | G30: 1/5 — Rouge : son tanin durcit au contact de la chair fine (P24). | H30: 1/5 — Rouge : son tanin durcit au contact de l'iode (goût métallique) (P27). | I30: 1/5 — Rouge : son tanin durcit au contact de l'iode (P27). | J30: 1/5 — Rouge : son tanin durcit au contact du fromage, ingrédient principal (P5). | K30: 1/5 — Rouge : son tanin durcit au contact de la panure et l'iode (P34). | L30: 4/5 — Rouge de poids moyen aux tanins fins : profil qui convient, sans point d'ancrage décisif (P20, P29). | M30: 1/5 — Tanin durci par le sucre et le vinaigre de la sauce (P22, P23). | N30: 1/5 — Rouge : son tanin durcit au contact du curry (P6). | O30: 2/5 — Rouge sec sans le sucre qui répond au sel (P4) ; tanin léger, mais fruit perdu sur le gras (P20). | P30: 1/5 — Rouge : son tanin durcit au contact du homard (P27). | Q30: 2/5 — Tanin trop présent pour la chair iodée et la tomate (P27) ; acidité trop faible face à la tomate et le citron (P23). | R30: 4/5 — Rouge de poids moyen aux tanins fins : profil qui convient, sans point d'ancrage décisif (P20, P29). | S30: 1/5 — Rouge : son tanin durcit au contact du cabillaud et les crevettes (P27). | T30: 1/5 — Rouge : son tanin durcit au contact de la sole (P27). | U30: 2/5 — Tanin trop présent pour le thon cru (P27) ; acidité trop faible face aux câpres et cornichons (P23). | V30: 4/5 — Rouge de poids moyen aux tanins fins : profil qui convient, sans point d'ancrage décisif (P20, P29). | W30: 2/5 — Tanin léger, mais durci par l'umami et le sucre (P29, P22). | X30: 1/5 — Rouge : son tanin durcit au contact du beurre et le citron (P3). | Y30: 4/5 — Rouge de poids moyen aux tanins fins : profil qui convient, sans point d'ancrage décisif (P20, P30). | Z30: 1/5 — Rouge : son tanin durcit au contact de la sauce blanche (P24). | AA30: 4/5 — Rouge de poids moyen aux tanins fins : profil qui convient, sans point d'ancrage décisif (P20, P40). | AB30: 3/5 — Acidité trop faible face aux condiments (P23). | AC30: 4/5 — Rouge de poids moyen aux tanins fins : profil qui convient, sans point d'ancrage décisif (P20, P13). | AD30: 4/5 — Rouge de poids moyen aux tanins fins : profil qui convient, sans point d'ancrage décisif (P20, P29). | AE30: 3/5 — Acidité trop faible face au beurre et la réduction vinaigrée (P3). | AF30: 1/5 — Vin sec face au sucre du dessert : il paraît amer et maigre (P22). | AG30: 1/5 — Vin sec face au sucre du dessert : il paraît amer et maigre (P22, P15). | AH30: 1/5 — Vin sec face au sucre du dessert : il paraît amer et maigre (P22, P15). | AI30: 1/5 — Vin sec face au sucre du dessert : il paraît amer et maigre (P22). | AJ30: 1/5 — Vin sec face au sucre du dessert : il paraît amer et maigre (P22). | AK30: 1/5 — Vin sec face au sucre du dessert : il paraît amer et maigre (P22). | AL30: 1/5 — Vin sec face au sucre du dessert : il paraît amer et maigre (P22). | AM30: 1/5 — Vin sec face au sucre du dessert : il paraît amer et maigre (P22, P15). | AN30: 1/5 — Vin sec face au sucre du dessert : il paraît amer et maigre (P22). | AO30: 1/5 — Vin sec face au sucre du dessert : il paraît amer et maigre (P22, P7, P35). | AP30: 1/5 — Rouge jeune tannique, durci par le fromage (P5, P29).
A31: Rouges | B31: L-R03 · Moulin-à-Vent Les Michelons 2014 | C31: 145 | D31: 2/5 — Le bois couvre la finesse et amplifie l'amertume (P30) ; trop puissant, il écrase le plat (P20). | E31: 1/5 — Rouge : son tanin durcit au contact du poisson cru (P27). | F31: 1/5 — Rouge : son tanin durcit au contact de la panure (P34). | G31: 1/5 — Rouge : son tanin durcit au contact de la chair fine (P24). | H31: 1/5 — Rouge : son tanin durcit au contact de l'iode (goût métallique) (P27). | I31: 1/5 — Rouge : son tanin durcit au contact de l'iode (P27). | J31: 1/5 — Rouge : son tanin durcit au contact du fromage, ingrédient principal (P5). | K31: 1/5 — Rouge : son tanin durcit au contact de la panure et l'iode (P34). | L31: 4/5 — Rouge puissant aux tanins fondus, patiné : profil qui convient, sans point d'ancrage décisif (P20, P29). | M31: 1/5 — Tanin durci par le sucre et le vinaigre de la sauce (P22, P23). | N31: 1/5 — Rouge : son tanin durcit au contact du curry (P6). | O31: 1/5 — Tanin qui heurte le gras fondant, sans l'opposition du sucre (P4, P20). | P31: 1/5 — Rouge : son tanin durcit au contact du homard (P27). | Q31: 1/5 — Tanin trop présent pour la chair iodée et la tomate (P27) ; le bois couvre la finesse et amplifie l'amertume (P19). | R31: 4/5 — Rouge puissant aux tanins fondus, patiné : profil qui convient, sans point d'ancrage décisif (P20, P29). | S31: 1/5 — Rouge : son tanin durcit au contact du cabillaud et les crevettes (P27). | T31: 1/5 — Rouge : son tanin durcit au contact de la sole (P27). | U31: 1/5 — Tanin trop présent pour le thon cru (P27) ; le bois couvre la finesse et amplifie l'amertume (P19) ; acidité trop faible face aux câpres et cornichons (P23). | V31: 5/5 — Notes tertiaires de sous-bois en miroir des champignons, tanins fondus que le parmesan ne durcit pas (P25, P40, P37). | W31: 1/5 — Tanin durci par l'umami et le sucre de la laque (P29, P22). | X31: 1/5 — Rouge : son tanin durcit au contact du beurre et le citron (P3). | Y31: 4/5 — Rouge puissant aux tanins fondus, patiné : profil qui convient, sans point d'ancrage décisif (P20, P30). | Z31: 1/5 — Rouge : son tanin durcit au contact de la sauce blanche (P24). | AA31: 5/5 — Rouge patiné aux tanins fondus sur la laque caramélisée (P40, P14). | AB31: 3/5 — Acidité trop faible face aux condiments (P23). | AC31: 5/5 — Tanins fondus et trame acide : la passerelle entre la crème et le poivre (P13, P21). | AD31: 5/5 — Notes tertiaires en miroir des morilles, tanins fondus (P25, P40). | AE31: 3/5 — Acidité trop faible face au beurre et la réduction vinaigrée (P3). | AF31: 1/5 — Vin sec face au sucre du dessert : il paraît amer et maigre (P22). | AG31: 1/5 — Vin sec face au sucre du dessert : il paraît amer et maigre (P22, P15). | AH31: 1/5 — Vin sec face au sucre du dessert : il paraît amer et maigre (P22, P15). | AI31: 1/5 — Vin sec face au sucre du dessert : il paraît amer et maigre (P22). | AJ31: 1/5 — Vin sec face au sucre du dessert : il paraît amer et maigre (P22). | AK31: 1/5 — Vin sec face au sucre du dessert : il paraît amer et maigre (P22). | AL31: 1/5 — Vin sec face au sucre du dessert : il paraît amer et maigre (P22). | AM31: 1/5 — Vin sec face au sucre du dessert : il paraît amer et maigre (P22, P15). | AN31: 1/5 — Vin sec face au sucre du dessert : il paraît amer et maigre (P22). | AO31: 1/5 — Vin sec face au sucre du dessert : il paraît amer et maigre (P22, P7, P35). | AP31: 3/5 — Rouge évolué aux tanins fondus, bien sur pâte pressée, risqué sur pâte fraîche (P5, P18).
A32: Rouges | B32: L-R04 · Bourgogne Pinot noir Nuiton-Beaunoy 2023 | C32: 49 | D32: 4/5 — Rouge léger aux tanins fins : profil qui convient, sans point d'ancrage décisif (P20, P30). | E32: 2/5 — Rouge : son tanin durcit au contact du poisson cru (P27) ; seule sa légèreté limite les dégâts (P20). | F32: 2/5 — Rouge : son tanin durcit au contact de la panure (P34) ; seule sa légèreté limite les dégâts (P20). | G32: 2/5 — Rouge : son tanin durcit au contact de la chair fine (P24) ; seule sa légèreté limite les dégâts (P20). | H32: 2/5 — Rouge : son tanin durcit au contact de l'iode (goût métallique) (P27) ; seule sa légèreté limite les dégâts (P20). | I32: 2/5 — Rouge : son tanin durcit au contact de l'iode (P27) ; seule sa légèreté limite les dégâts (P20). | J32: 2/5 — Rouge : son tanin durcit au contact du fromage, ingrédient principal (P5) ; seule sa légèreté limite les dégâts (P20). | K32: 2/5 — Rouge : son tanin durcit au contact de la panure et l'iode (P34) ; seule sa légèreté limite les dégâts (P20). | L32: 4/5 — Même terroir que l'escargot (origine à confirmer), rouge léger possible (P2). | M32: 1/5 — Tanin durci par le sucre et le vinaigre de la sauce (P22, P23). | N32: 2/5 — Rouge : son tanin durcit au contact du curry (P6) ; seule sa légèreté limite les dégâts (P20). | O32: 2/5 — Rouge sec sans le sucre qui répond au sel (P4) ; tanin léger, mais fruit perdu sur le gras (P20). | P32: 2/5 — Rouge : son tanin durcit au contact du homard (P27) ; seule sa légèreté limite les dégâts (P20). | Q32: 1/5 — Tanin trop présent pour la chair iodée et la tomate (P27) ; le bois couvre la finesse et amplifie l'amertume (P19). | R32: 4/5 — Rouge léger aux tanins fins : profil qui convient, sans point d'ancrage décisif (P20, P29). | S32: 2/5 — Rouge : son tanin durcit au contact du cabillaud et les crevettes (P27) ; seule sa légèreté limite les dégâts (P20). | T32: 2/5 — Rouge : son tanin durcit au contact de la sole (P27) ; seule sa légèreté limite les dégâts (P20). | U32: 1/5 — Tanin trop présent pour le thon cru (P27) ; le bois couvre la finesse et amplifie l'amertume (P19) ; acidité trop faible face aux câpres et cornichons (P23). | V32: 3/5 — Trop léger, il disparaît derrière le plat (P20). | W32: 2/5 — Tanin léger, mais durci par l'umami et le sucre (P29, P22). | X32: 2/5 — Rouge : son tanin durcit au contact du beurre et le citron (P3) ; seule sa légèreté limite les dégâts (P20). | Y32: 3/5 — Trop léger, il disparaît derrière le plat (P20). | Z32: 2/5 — Rouge : son tanin durcit au contact de la sauce blanche (P24) ; seule sa légèreté limite les dégâts (P20). | AA32: 3/5 — Trop léger, il disparaît derrière le plat (P20). | AB32: 3/5 — Acidité trop faible face aux condiments (P23). | AC32: 3/5 — Trop léger, il disparaît derrière le plat (P20). | AD32: 3/5 — Trop léger, il disparaît derrière le plat (P20). | AE32: 2/5 — Acidité trop faible face au beurre et la réduction vinaigrée (P3) ; trop léger, il disparaît derrière le plat (P20). | AF32: 1/5 — Vin sec face au sucre du dessert : il paraît amer et maigre (P22). | AG32: 1/5 — Vin sec face au sucre du dessert : il paraît amer et maigre (P22, P15). | AH32: 1/5 — Vin sec face au sucre du dessert : il paraît amer et maigre (P22, P15). | AI32: 1/5 — Vin sec face au sucre du dessert : il paraît amer et maigre (P22). | AJ32: 1/5 — Vin sec face au sucre du dessert : il paraît amer et maigre (P22). | AK32: 1/5 — Vin sec face au sucre du dessert : il paraît amer et maigre (P22). | AL32: 1/5 — Vin sec face au sucre du dessert : il paraît amer et maigre (P22). | AM32: 1/5 — Vin sec face au sucre du dessert : il paraît amer et maigre (P22, P15). | AN32: 1/5 — Vin sec face au sucre du dessert : il paraît amer et maigre (P22). | AO32: 1/5 — Vin sec face au sucre du dessert : il paraît amer et maigre (P22, P7, P35). | AP32: 1/5 — Rouge jeune tannique, durci par le fromage (P5, P29).
A33: Rouges | B33: L-R05 · Givry Millebuis 2023 | C33: 58 | D33: 3/5 — Le bois couvre la finesse et amplifie l'amertume (P30). | E33: 1/5 — Rouge : son tanin durcit au contact du poisson cru (P27). | F33: 1/5 — Rouge : son tanin durcit au contact de la panure (P34). | G33: 1/5 — Rouge : son tanin durcit au contact de la chair fine (P24). | H33: 1/5 — Rouge : son tanin durcit au contact de l'iode (goût métallique) (P27). | I33: 1/5 — Rouge : son tanin durcit au contact de l'iode (P27). | J33: 1/5 — Rouge : son tanin durcit au contact du fromage, ingrédient principal (P5). | K33: 1/5 — Rouge : son tanin durcit au contact de la panure et l'iode (P34). | L33: 4/5 — Même terroir que l'escargot (origine à confirmer), rouge léger possible (P2) ; le bois couvre la finesse et amplifie l'amertume (P19). | M33: 1/5 — Tanin durci par le sucre et le vinaigre de la sauce (P22, P23). | N33: 1/5 — Rouge : son tanin durcit au contact du curry (P6). | O33: 2/5 — Rouge sec sans le sucre qui répond au sel (P4) ; tanin léger, mais fruit perdu sur le gras (P20). | P33: 1/5 — Rouge : son tanin durcit au contact du homard (P27). | Q33: 1/5 — Le bois couvre la finesse et amplifie l'amertume (P19) ; tanin trop présent pour la chair iodée et la tomate (P27). | R33: 3/5 — Le bois couvre la finesse et amplifie l'amertume (P19). | S33: 1/5 — Rouge : son tanin durcit au contact du cabillaud et les crevettes (P27). | T33: 1/5 — Rouge : son tanin durcit au contact de la sole (P27). | U33: 1/5 — Le bois couvre la finesse et amplifie l'amertume (P19) ; tanin trop présent pour le thon cru (P27) ; acidité trop faible face aux câpres et cornichons (P23). | V33: 4/5 — Rouge de poids moyen aux tanins fins : profil qui convient, sans point d'ancrage décisif (P20, P29). | W33: 2/5 — Tanin léger, mais durci par l'umami et le sucre (P29, P22). | X33: 1/5 — Rouge : son tanin durcit au contact du beurre et le citron (P3). | Y33: 4/5 — Rouge de poids moyen aux tanins fins : profil qui convient, sans point d'ancrage décisif (P20, P30). | Z33: 1/5 — Rouge : son tanin durcit au contact de la sauce blanche (P24). | AA33: 4/5 — Rouge de poids moyen aux tanins fins : profil qui convient, sans point d'ancrage décisif (P20, P40). | AB33: 2/5 — Le bois couvre la finesse et amplifie l'amertume (P19) ; acidité trop faible face aux condiments (P23). | AC33: 4/5 — Rouge de poids moyen aux tanins fins : profil qui convient, sans point d'ancrage décisif (P20, P13). | AD33: 4/5 — Rouge de poids moyen aux tanins fins : profil qui convient, sans point d'ancrage décisif (P20, P29). | AE33: 3/5 — Acidité trop faible face au beurre et la réduction vinaigrée (P3). | AF33: 1/5 — Vin sec face au sucre du dessert : il paraît amer et maigre (P22). | AG33: 1/5 — Vin sec face au sucre du dessert : il paraît amer et maigre (P22, P15). | AH33: 1/5 — Vin sec face au sucre du dessert : il paraît amer et maigre (P22, P15). | AI33: 1/5 — Vin sec face au sucre du dessert : il paraît amer et maigre (P22). | AJ33: 1/5 — Vin sec face au sucre du dessert : il paraît amer et maigre (P22). | AK33: 1/5 — Vin sec face au sucre du dessert : il paraît amer et maigre (P22). | AL33: 1/5 — Vin sec face au sucre du dessert : il paraît amer et maigre (P22). | AM33: 1/5 — Vin sec face au sucre du dessert : il paraît amer et maigre (P22, P15). | AN33: 1/5 — Vin sec face au sucre du dessert : il paraît amer et maigre (P22). | AO33: 1/5 — Vin sec face au sucre du dessert : il paraît amer et maigre (P22, P7, P35). | AP33: 1/5 — Rouge jeune tannique, durci par le fromage (P5, P29).
A34: Rouges | B34: L-R06 · Pommard 1er Cru Les Grands Épenots 2018 | C34: 210 | D34: 1/5 — Le bois couvre la finesse et amplifie l'amertume (P30) ; tanin trop présent pour l'amertume de la roquette (P30) ; trop puissant, il écrase le plat (P20). | E34: 1/5 — Rouge : son tanin durcit au contact du poisson cru (P27). | F34: 1/5 — Rouge : son tanin durcit au contact de la panure (P34). | G34: 1/5 — Rouge : son tanin durcit au contact de la chair fine (P24). | H34: 1/5 — Rouge : son tanin durcit au contact de l'iode (goût métallique) (P27). | I34: 1/5 — Rouge : son tanin durcit au contact de l'iode (P27). | J34: 1/5 — Rouge : son tanin durcit au contact du fromage, ingrédient principal (P5). | K34: 1/5 — Rouge : son tanin durcit au contact de la panure et l'iode (P34). | L34: 3/5 — Tanin trop présent pour l'umami de l'escargot (P29) ; le bois couvre la finesse et amplifie l'amertume (P19). | M34: 1/5 — Tanin durci par le sucre et le vinaigre de la sauce (P22, P23). | N34: 1/5 — Rouge : son tanin durcit au contact du curry (P6). | O34: 1/5 — Tanin qui heurte le gras fondant, sans l'opposition du sucre (P4, P20). | P34: 1/5 — Rouge : son tanin durcit au contact du homard (P27). | Q34: 1/5 — Tanin trop présent pour la chair iodée et la tomate (P27) ; le bois couvre la finesse et amplifie l'amertume (P19). | R34: 2/5 — Tanin trop présent pour l'umami et l'amertume du broccolini (P29) ; le bois couvre la finesse et amplifie l'amertume (P19). | S34: 1/5 — Rouge : son tanin durcit au contact du cabillaud et les crevettes (P27). | T34: 1/5 — Rouge : son tanin durcit au contact de la sole (P27). | U34: 1/5 — Tanin trop présent pour le thon cru (P27) ; le bois couvre la finesse et amplifie l'amertume (P19) ; acidité trop faible face aux câpres et cornichons (P23). | V34: 4/5 — Notes tertiaires de sous-bois en miroir des champignons, tanins fondus que le parmesan ne durcit pas (P25, P40, P37). | W34: 1/5 — Tanin durci par l'umami et le sucre de la laque (P29, P22). | X34: 1/5 — Rouge : son tanin durcit au contact du beurre et le citron (P3). | Y34: 3/5 — Tanin trop présent pour l'amertume des chiconettes (P30). | Z34: 1/5 — Rouge : son tanin durcit au contact de la sauce blanche (P24). | AA34: 4/5 — Rouge patiné aux tanins fondus sur la laque caramélisée (P40, P14) ; tanin trop présent pour la viande blanche fondante (P40). | AB34: 1/5 — Tanin trop présent pour la viande crue et maigre (P21) ; le bois couvre la finesse et amplifie l'amertume (P19) ; acidité trop faible face aux condiments (P23). | AC34: 5/5 — Tanins fondus et trame acide : la passerelle entre la crème et le poivre (P13, P21). | AD34: 5/5 — Notes tertiaires en miroir des morilles, tanins fondus (P25, P40). | AE34: 2/5 — Tanin trop présent pour l'émulsion (P10) ; acidité trop faible face au beurre et la réduction vinaigrée (P3). | AF34: 1/5 — Vin sec face au sucre du dessert : il paraît amer et maigre (P22). | AG34: 1/5 — Vin sec face au sucre du dessert : il paraît amer et maigre (P22, P15). | AH34: 1/5 — Vin sec face au sucre du dessert : il paraît amer et maigre (P22, P15). | AI34: 1/5 — Vin sec face au sucre du dessert : il paraît amer et maigre (P22). | AJ34: 1/5 — Vin sec face au sucre du dessert : il paraît amer et maigre (P22). | AK34: 1/5 — Vin sec face au sucre du dessert : il paraît amer et maigre (P22). | AL34: 1/5 — Vin sec face au sucre du dessert : il paraît amer et maigre (P22). | AM34: 1/5 — Vin sec face au sucre du dessert : il paraît amer et maigre (P22, P15). | AN34: 1/5 — Vin sec face au sucre du dessert : il paraît amer et maigre (P22). | AO34: 1/5 — Vin sec face au sucre du dessert : il paraît amer et maigre (P22, P7, P35). | AP34: 1/5 — Rouge jeune tannique, durci par le fromage (P5, P29).
A35: Rouges | B35: L-R07 · Beaune 1er Cru Clos des Fèves 2018 | C35: 320 | D35: 1/5 — Le bois couvre la finesse et amplifie l'amertume (P30) ; tanin trop présent pour l'amertume de la roquette (P30). | E35: 1/5 — Rouge : son tanin durcit au contact du poisson cru (P27). | F35: 1/5 — Rouge : son tanin durcit au contact de la panure (P34). | G35: 1/5 — Rouge : son tanin durcit au contact de la chair fine (P24). | H35: 1/5 — Rouge : son tanin durcit au contact de l'iode (goût métallique) (P27). | I35: 1/5 — Rouge : son tanin durcit au contact de l'iode (P27). | J35: 1/5 — Rouge : son tanin durcit au contact du fromage, ingrédient principal (P5). | K35: 1/5 — Rouge : son tanin durcit au contact de la panure et l'iode (P34). | L35: 3/5 — Tanin trop présent pour l'umami de l'escargot (P29) ; le bois couvre la finesse et amplifie l'amertume (P19). | M35: 1/5 — Tanin durci par le sucre et le vinaigre de la sauce (P22, P23). | N35: 1/5 — Rouge : son tanin durcit au contact du curry (P6). | O35: 1/5 — Tanin qui heurte le gras fondant, sans l'opposition du sucre (P4, P20). | P35: 1/5 — Rouge : son tanin durcit au contact du homard (P27). | Q35: 1/5 — Tanin trop présent pour la chair iodée et la tomate (P27) ; le bois couvre la finesse et amplifie l'amertume (P19). | R35: 2/5 — Tanin trop présent pour l'umami et l'amertume du broccolini (P29) ; le bois couvre la finesse et amplifie l'amertume (P19). | S35: 1/5 — Rouge : son tanin durcit au contact du cabillaud et les crevettes (P27). | T35: 1/5 — Rouge : son tanin durcit au contact de la sole (P27). | U35: 1/5 — Tanin trop présent pour le thon cru (P27) ; le bois couvre la finesse et amplifie l'amertume (P19) ; acidité trop faible face aux câpres et cornichons (P23). | V35: 3/5 — Tanin trop présent pour l'umami des champignons et du parmesan (P29). | W35: 1/5 — Tanin durci par l'umami et le sucre de la laque (P29, P22). | X35: 1/5 — Rouge : son tanin durcit au contact du beurre et le citron (P3). | Y35: 3/5 — Tanin trop présent pour l'amertume des chiconettes (P30). | Z35: 1/5 — Rouge : son tanin durcit au contact de la sauce blanche (P24). | AA35: 4/5 — Rouge patiné aux tanins fondus sur la laque caramélisée (P40, P14) ; tanin trop présent pour la viande blanche fondante (P40). | AB35: 1/5 — Tanin trop présent pour la viande crue et maigre (P21) ; le bois couvre la finesse et amplifie l'amertume (P19) ; acidité trop faible face aux condiments (P23). | AC35: 5/5 — Tanins fondus et trame acide : la passerelle entre la crème et le poivre (P13, P21). | AD35: 4/5 — Rouge de poids moyen aux tanins présents : profil qui convient, sans point d'ancrage décisif (P20, P29). | AE35: 2/5 — Tanin trop présent pour l'émulsion (P10) ; acidité trop faible face au beurre et la réduction vinaigrée (P3). | AF35: 1/5 — Vin sec face au sucre du dessert : il paraît amer et maigre (P22). | AG35: 1/5 — Vin sec face au sucre du dessert : il paraît amer et maigre (P22, P15). | AH35: 1/5 — Vin sec face au sucre du dessert : il paraît amer et maigre (P22, P15). | AI35: 1/5 — Vin sec face au sucre du dessert : il paraît amer et maigre (P22). | AJ35: 1/5 — Vin sec face au sucre du dessert : il paraît amer et maigre (P22). | AK35: 1/5 — Vin sec face au sucre du dessert : il paraît amer et maigre (P22). | AL35: 1/5 — Vin sec face au sucre du dessert : il paraît amer et maigre (P22). | AM35: 1/5 — Vin sec face au sucre du dessert : il paraît amer et maigre (P22, P15). | AN35: 1/5 — Vin sec face au sucre du dessert : il paraît amer et maigre (P22). | AO35: 1/5 — Vin sec face au sucre du dessert : il paraît amer et maigre (P22, P7, P35). | AP35: 1/5 — Rouge jeune tannique, durci par le fromage (P5, P29).
A36: Rouges | B36: L-R08 · Corton Grand Cru Clos du Roi 2018 | C36: 485 | D36: 1/5 — Tanin trop présent pour l'amertume de la roquette (P30) ; le bois couvre la finesse et amplifie l'amertume (P30) ; trop puissant, il écrase le plat (P20). | E36: 1/5 — Rouge : son tanin durcit au contact du poisson cru (P27). | F36: 1/5 — Rouge : son tanin durcit au contact de la panure (P34). | G36: 1/5 — Rouge : son tanin durcit au contact de la chair fine (P24). | H36: 1/5 — Rouge : son tanin durcit au contact de l'iode (goût métallique) (P27). | I36: 1/5 — Rouge : son tanin durcit au contact de l'iode (P27). | J36: 1/5 — Rouge : son tanin durcit au contact du fromage, ingrédient principal (P5). | K36: 1/5 — Rouge : son tanin durcit au contact de la panure et l'iode (P34). | L36: 2/5 — Tanin trop présent pour l'umami de l'escargot (P29) ; le bois couvre la finesse et amplifie l'amertume (P19). | M36: 1/5 — Tanin durci par le sucre et le vinaigre de la sauce (P22, P23). | N36: 1/5 — Rouge : son tanin durcit au contact du curry (P6). | O36: 1/5 — Tanin qui heurte le gras fondant, sans l'opposition du sucre (P4, P20). | P36: 1/5 — Rouge : son tanin durcit au contact du homard (P27). | Q36: 1/5 — Tanin trop présent pour la chair iodée et la tomate (P27) ; le bois couvre la finesse et amplifie l'amertume (P19). | R36: 1/5 — Tanin trop présent pour l'umami et l'amertume du broccolini (P29) ; le bois couvre la finesse et amplifie l'amertume (P19). | S36: 1/5 — Rouge : son tanin durcit au contact du cabillaud et les crevettes (P27). | T36: 1/5 — Rouge : son tanin durcit au contact de la sole (P27). | U36: 1/5 — Tanin trop présent pour le thon cru (P27) ; le bois couvre la finesse et amplifie l'amertume (P19) ; acidité trop faible face aux câpres et cornichons (P23). | V36: 2/5 — Tanin trop présent pour l'umami des champignons et du parmesan (P29). | W36: 1/5 — Tanin durci par l'umami et le sucre de la laque (P29, P22). | X36: 1/5 — Rouge : son tanin durcit au contact du beurre et le citron (P3). | Y36: 2/5 — Tanin trop présent pour l'amertume des chiconettes (P30). | Z36: 1/5 — Rouge : son tanin durcit au contact de la sauce blanche (P24). | AA36: 3/5 — Tanin trop présent pour la viande blanche fondante (P40). | AB36: 1/5 — Tanin trop présent pour la viande crue et maigre (P21) ; le bois couvre la finesse et amplifie l'amertume (P19) ; acidité trop faible face aux condiments (P23). | AC36: 3/5 — Tanin trop présent pour le poivre (P13). | AD36: 3/5 — Tanin trop présent pour l'umami des morilles (P29). | AE36: 2/5 — Tanin trop présent pour l'émulsion (P10) ; acidité trop faible face au beurre et la réduction vinaigrée (P3). | AF36: 1/5 — Vin sec face au sucre du dessert : il paraît amer et maigre (P22). | AG36: 1/5 — Vin sec face au sucre du dessert : il paraît amer et maigre (P22, P15). | AH36: 1/5 — Vin sec face au sucre du dessert : il paraît amer et maigre (P22, P15). | AI36: 1/5 — Vin sec face au sucre du dessert : il paraît amer et maigre (P22). | AJ36: 1/5 — Vin sec face au sucre du dessert : il paraît amer et maigre (P22). | AK36: 1/5 — Vin sec face au sucre du dessert : il paraît amer et maigre (P22). | AL36: 1/5 — Vin sec face au sucre du dessert : il paraît amer et maigre (P22). | AM36: 1/5 — Vin sec face au sucre du dessert : il paraît amer et maigre (P22, P15). | AN36: 1/5 — Vin sec face au sucre du dessert : il paraît amer et maigre (P22). | AO36: 1/5 — Vin sec face au sucre du dessert : il paraît amer et maigre (P22, P7, P35). | AP36: 1/5 — Rouge jeune tannique, durci par le fromage (P5, P29).
A37: Rouges | B37: L-R09 · Gevrey-Chambertin Justice / Seuvrées 2018-2019 | C37: 560 | D37: 1/5 — Le bois couvre la finesse et amplifie l'amertume (P30) ; tanin trop présent pour l'amertume de la roquette (P30) ; trop puissant, il écrase le plat (P20). | E37: 1/5 — Rouge : son tanin durcit au contact du poisson cru (P27). | F37: 1/5 — Rouge : son tanin durcit au contact de la panure (P34). | G37: 1/5 — Rouge : son tanin durcit au contact de la chair fine (P24). | H37: 1/5 — Rouge : son tanin durcit au contact de l'iode (goût métallique) (P27). | I37: 1/5 — Rouge : son tanin durcit au contact de l'iode (P27). | J37: 1/5 — Rouge : son tanin durcit au contact du fromage, ingrédient principal (P5). | K37: 1/5 — Rouge : son tanin durcit au contact de la panure et l'iode (P34). | L37: 2/5 — Le bois couvre la finesse et amplifie l'amertume (P19) ; tanin trop présent pour l'umami de l'escargot (P29). | M37: 1/5 — Tanin durci par le sucre et le vinaigre de la sauce (P22, P23). | N37: 1/5 — Rouge : son tanin durcit au contact du curry (P6). | O37: 1/5 — Tanin qui heurte le gras fondant, sans l'opposition du sucre (P4, P20). | P37: 1/5 — Rouge : son tanin durcit au contact du homard (P27). | Q37: 1/5 — Le bois couvre la finesse et amplifie l'amertume (P19) ; tanin trop présent pour la chair iodée et la tomate (P27). | R37: 1/5 — Le bois couvre la finesse et amplifie l'amertume (P19) ; tanin trop présent pour l'umami et l'amertume du broccolini (P29). | S37: 1/5 — Rouge : son tanin durcit au contact du cabillaud et les crevettes (P27). | T37: 1/5 — Rouge : son tanin durcit au contact de la sole (P27). | U37: 1/5 — Le bois couvre la finesse et amplifie l'amertume (P19) ; tanin trop présent pour le thon cru (P27) ; acidité trop faible face aux câpres et cornichons (P23). | V37: 2/5 — Tanin trop présent pour l'umami des champignons et du parmesan (P29) ; le bois couvre la finesse et amplifie l'amertume (P19). | W37: 1/5 — Tanin durci par l'umami et le sucre de la laque (P29, P22). | X37: 1/5 — Rouge : son tanin durcit au contact du beurre et le citron (P3). | Y37: 2/5 — Tanin trop présent pour l'amertume des chiconettes (P30) ; le bois couvre la finesse et amplifie l'amertume (P19). | Z37: 1/5 — Rouge : son tanin durcit au contact de la sauce blanche (P24). | AA37: 3/5 — Tanin trop présent pour la viande blanche fondante (P40) ; le bois couvre la finesse et amplifie l'amertume (P19). | AB37: 1/5 — Le bois couvre la finesse et amplifie l'amertume (P19) ; tanin trop présent pour la viande crue et maigre (P21) ; acidité trop faible face aux condiments (P23). | AC37: 4/5 — Tanins fondus et trame acide : la passerelle entre la crème et le poivre (P13, P21) ; le bois couvre la finesse et amplifie l'amertume (P19). | AD37: 3/5 — Le bois couvre la finesse et amplifie l'amertume (P19). | AE37: 2/5 — Tanin trop présent pour l'émulsion (P10) ; le bois couvre la finesse et amplifie l'amertume (P19) ; acidité trop faible face au beurre et la réduction vinaigrée (P3). | AF37: 1/5 — Vin sec face au sucre du dessert : il paraît amer et maigre (P22). | AG37: 1/5 — Vin sec face au sucre du dessert : il paraît amer et maigre (P22, P15). | AH37: 1/5 — Vin sec face au sucre du dessert : il paraît amer et maigre (P22, P15). | AI37: 1/5 — Vin sec face au sucre du dessert : il paraît amer et maigre (P22). | AJ37: 1/5 — Vin sec face au sucre du dessert : il paraît amer et maigre (P22). | AK37: 1/5 — Vin sec face au sucre du dessert : il paraît amer et maigre (P22). | AL37: 1/5 — Vin sec face au sucre du dessert : il paraît amer et maigre (P22). | AM37: 1/5 — Vin sec face au sucre du dessert : il paraît amer et maigre (P22, P15). | AN37: 1/5 — Vin sec face au sucre du dessert : il paraît amer et maigre (P22). | AO37: 1/5 — Vin sec face au sucre du dessert : il paraît amer et maigre (P22, P7, P35). | AP37: 1/5 — Rouge jeune tannique, durci par le fromage (P5, P29).
A38: Rouges | B38: L-R10 · Bourgueil Côte 50 2024 | C38: 45 | D38: 5/5 — Rouge léger, vif et peu tannique : il épouse le bœuf cru sans durcir sur la roquette (P30, P28, P37). | E38: 2/5 — Rouge : son tanin durcit au contact du poisson cru (P27) ; seule sa légèreté limite les dégâts (P20). | F38: 2/5 — Rouge : son tanin durcit au contact de la panure (P34) ; seule sa légèreté limite les dégâts (P20). | G38: 2/5 — Rouge : son tanin durcit au contact de la chair fine (P24) ; seule sa légèreté limite les dégâts (P20). | H38: 2/5 — Rouge : son tanin durcit au contact de l'iode (goût métallique) (P27) ; seule sa légèreté limite les dégâts (P20). | I38: 2/5 — Rouge : son tanin durcit au contact de l'iode (P27) ; seule sa légèreté limite les dégâts (P20). | J38: 2/5 — Rouge : son tanin durcit au contact du fromage, ingrédient principal (P5) ; seule sa légèreté limite les dégâts (P20). | K38: 2/5 — Rouge : son tanin durcit au contact de la panure et l'iode (P34) ; seule sa légèreté limite les dégâts (P20). | L38: 4/5 — Rouge léger aux tanins fins : profil qui convient, sans point d'ancrage décisif (P20, P29). | M38: 1/5 — Tanin durci par le sucre et le vinaigre de la sauce (P22, P23). | N38: 2/5 — Rouge : son tanin durcit au contact du curry (P6) ; seule sa légèreté limite les dégâts (P20). | O38: 2/5 — Rouge sec sans le sucre qui répond au sel (P4) ; tanin léger, mais fruit perdu sur le gras (P20). | P38: 2/5 — Rouge : son tanin durcit au contact du homard (P27) ; seule sa légèreté limite les dégâts (P20). | Q38: 3/5 — Tanin trop présent pour la chair iodée et la tomate (P27). | R38: 5/5 — Rouge léger servi frais sur un thon charnu, tanin discret face à l'umami (P27, P26). | S38: 2/5 — Rouge : son tanin durcit au contact du cabillaud et les crevettes (P27) ; seule sa légèreté limite les dégâts (P20). | T38: 2/5 — Rouge : son tanin durcit au contact de la sole (P27) ; seule sa légèreté limite les dégâts (P20). | U38: 3/5 — Tanin trop présent pour le thon cru (P27). | V38: 3/5 — Trop léger, il disparaît derrière le plat (P20). | W38: 2/5 — Tanin léger, mais durci par l'umami et le sucre (P29, P22). | X38: 2/5 — Rouge : son tanin durcit au contact du beurre et le citron (P3) ; seule sa légèreté limite les dégâts (P20). | Y38: 3/5 — Trop léger, il disparaît derrière le plat (P20). | Z38: 2/5 — Rouge : son tanin durcit au contact de la sauce blanche (P24) ; seule sa légèreté limite les dégâts (P20). | AA38: 3/5 — Trop léger, il disparaît derrière le plat (P20). | AB38: 4/5 — L'émulsion à l'œuf plafonne l'accord (P10, P35) ; rouge juteux et vif, tanins fins pour la viande crue (P21, P23). | AC38: 3/5 — Trop léger, il disparaît derrière le plat (P20). | AD38: 3/5 — Trop léger, il disparaît derrière le plat (P20). | AE38: 4/5 — Trame acide et tanins souples face à la béarnaise (P3, P21) ; trop léger, il disparaît derrière le plat (P20). | AF38: 1/5 — Vin sec face au sucre du dessert : il paraît amer et maigre (P22). | AG38: 1/5 — Vin sec face au sucre du dessert : il paraît amer et maigre (P22, P15). | AH38: 1/5 — Vin sec face au sucre du dessert : il paraît amer et maigre (P22, P15). | AI38: 1/5 — Vin sec face au sucre du dessert : il paraît amer et maigre (P22). | AJ38: 1/5 — Vin sec face au sucre du dessert : il paraît amer et maigre (P22). | AK38: 1/5 — Vin sec face au sucre du dessert : il paraît amer et maigre (P22). | AL38: 1/5 — Vin sec face au sucre du dessert : il paraît amer et maigre (P22). | AM38: 1/5 — Vin sec face au sucre du dessert : il paraît amer et maigre (P22, P15). | AN38: 1/5 — Vin sec face au sucre du dessert : il paraît amer et maigre (P22). | AO38: 1/5 — Vin sec face au sucre du dessert : il paraît amer et maigre (P22, P7, P35). | AP38: 1/5 — Rouge jeune tannique, durci par le fromage (P5, P29).
A39: Rouges | B39: L-R11 · Sancerre rouge Henri Bourgeois 2023 | C39: 48 | D39: 5/5 — Rouge léger, vif et peu tannique : il épouse le bœuf cru sans durcir sur la roquette (P30, P28, P37). | E39: 2/5 — Rouge : son tanin durcit au contact du poisson cru (P27) ; seule sa légèreté limite les dégâts (P20). | F39: 2/5 — Rouge : son tanin durcit au contact de la panure (P34) ; seule sa légèreté limite les dégâts (P20). | G39: 2/5 — Rouge : son tanin durcit au contact de la chair fine (P24) ; seule sa légèreté limite les dégâts (P20). | H39: 2/5 — Rouge : son tanin durcit au contact de l'iode (goût métallique) (P27) ; seule sa légèreté limite les dégâts (P20). | I39: 2/5 — Rouge : son tanin durcit au contact de l'iode (P27) ; seule sa légèreté limite les dégâts (P20). | J39: 2/5 — Rouge : son tanin durcit au contact du fromage, ingrédient principal (P5) ; seule sa légèreté limite les dégâts (P20). | K39: 2/5 — Rouge : son tanin durcit au contact de la panure et l'iode (P34) ; seule sa légèreté limite les dégâts (P20). | L39: 4/5 — Rouge léger aux tanins fins : profil qui convient, sans point d'ancrage décisif (P20, P29). | M39: 1/5 — Tanin durci par le sucre et le vinaigre de la sauce (P22, P23). | N39: 2/5 — Rouge : son tanin durcit au contact du curry (P6) ; seule sa légèreté limite les dégâts (P20). | O39: 2/5 — Rouge sec sans le sucre qui répond au sel (P4) ; tanin léger, mais fruit perdu sur le gras (P20). | P39: 2/5 — Rouge : son tanin durcit au contact du homard (P27) ; seule sa légèreté limite les dégâts (P20). | Q39: 2/5 — Tanin trop présent pour la chair iodée et la tomate (P27) ; le bois couvre la finesse et amplifie l'amertume (P19). | R39: 5/5 — Rouge léger servi frais sur un thon charnu, tanin discret face à l'umami (P27, P26). | S39: 2/5 — Rouge : son tanin durcit au contact du cabillaud et les crevettes (P27) ; seule sa légèreté limite les dégâts (P20). | T39: 2/5 — Rouge : son tanin durcit au contact de la sole (P27) ; seule sa légèreté limite les dégâts (P20). | U39: 2/5 — Tanin trop présent pour le thon cru (P27) ; le bois couvre la finesse et amplifie l'amertume (P19). | V39: 3/5 — Trop léger, il disparaît derrière le plat (P20). | W39: 2/5 — Tanin léger, mais durci par l'umami et le sucre (P29, P22). | X39: 2/5 — Rouge : son tanin durcit au contact du beurre et le citron (P3) ; seule sa légèreté limite les dégâts (P20). | Y39: 3/5 — Trop léger, il disparaît derrière le plat (P20). | Z39: 2/5 — Rouge : son tanin durcit au contact de la sauce blanche (P24) ; seule sa légèreté limite les dégâts (P20). | AA39: 3/5 — Trop léger, il disparaît derrière le plat (P20). | AB39: 4/5 — L'émulsion à l'œuf plafonne l'accord (P10, P35) ; rouge juteux et vif, tanins fins pour la viande crue (P21, P23). | AC39: 3/5 — Trop léger, il disparaît derrière le plat (P20). | AD39: 3/5 — Trop léger, il disparaît derrière le plat (P20). | AE39: 4/5 — Trame acide et tanins souples face à la béarnaise (P3, P21) ; trop léger, il disparaît derrière le plat (P20). | AF39: 1/5 — Vin sec face au sucre du dessert : il paraît amer et maigre (P22). | AG39: 1/5 — Vin sec face au sucre du dessert : il paraît amer et maigre (P22, P15). | AH39: 1/5 — Vin sec face au sucre du dessert : il paraît amer et maigre (P22, P15). | AI39: 1/5 — Vin sec face au sucre du dessert : il paraît amer et maigre (P22). | AJ39: 1/5 — Vin sec face au sucre du dessert : il paraît amer et maigre (P22). | AK39: 1/5 — Vin sec face au sucre du dessert : il paraît amer et maigre (P22). | AL39: 1/5 — Vin sec face au sucre du dessert : il paraît amer et maigre (P22). | AM39: 1/5 — Vin sec face au sucre du dessert : il paraît amer et maigre (P22, P15). | AN39: 1/5 — Vin sec face au sucre du dessert : il paraît amer et maigre (P22). | AO39: 1/5 — Vin sec face au sucre du dessert : il paraît amer et maigre (P22, P7, P35). | AP39: 1/5 — Rouge jeune tannique, durci par le fromage (P5, P29).
A40: Rouges | B40: L-R12 · Rhône Terres de Cure 2022 | C40: 45 | D40: 2/5 — Tanin trop présent pour l'amertume de la roquette (P30) ; le bois couvre la finesse et amplifie l'amertume (P30). | E40: 1/5 — Rouge : son tanin durcit au contact du poisson cru (P27). | F40: 1/5 — Rouge : son tanin durcit au contact de la panure (P34). | G40: 1/5 — Rouge : son tanin durcit au contact de la chair fine (P24). | H40: 1/5 — Rouge : son tanin durcit au contact de l'iode (goût métallique) (P27). | I40: 1/5 — Rouge : son tanin durcit au contact de l'iode (P27). | J40: 1/5 — Rouge : son tanin durcit au contact du fromage, ingrédient principal (P5). | K40: 1/5 — Rouge : son tanin durcit au contact de la panure et l'iode (P34). | L40: 3/5 — Tanin trop présent pour l'umami de l'escargot (P29). | M40: 1/5 — Tanin durci par le sucre et le vinaigre de la sauce (P22, P23). | N40: 1/5 — Rouge : son tanin durcit au contact du curry (P6). | O40: 1/5 — Tanin qui heurte le gras fondant, sans l'opposition du sucre (P4, P20). | P40: 1/5 — Rouge : son tanin durcit au contact du homard (P27). | Q40: 1/5 — Tanin trop présent pour la chair iodée et la tomate (P27) ; le bois couvre la finesse et amplifie l'amertume (P19). | R40: 3/5 — Tanin trop présent pour l'umami et l'amertume du broccolini (P29). | S40: 1/5 — Rouge : son tanin durcit au contact du cabillaud et les crevettes (P27). | T40: 1/5 — Rouge : son tanin durcit au contact de la sole (P27). | U40: 1/5 — Tanin trop présent pour le thon cru (P27) ; le bois couvre la finesse et amplifie l'amertume (P19) ; acidité trop faible face aux câpres et cornichons (P23). | V40: 3/5 — Tanin trop présent pour l'umami des champignons et du parmesan (P29). | W40: 1/5 — Tanin durci par l'umami et le sucre de la laque (P29, P22). | X40: 1/5 — Rouge : son tanin durcit au contact du beurre et le citron (P3). | Y40: 3/5 — Tanin trop présent pour l'amertume des chiconettes (P30). | Z40: 1/5 — Rouge : son tanin durcit au contact de la sauce blanche (P24). | AA40: 3/5 — Tanin trop présent pour la viande blanche fondante (P40). | AB40: 2/5 — Tanin trop présent pour la viande crue et maigre (P21) ; acidité trop faible face aux condiments (P23). | AC40: 3/5 — Tanins jeunes durcis par le poivre ; carafer (P13, P43). | AD40: 3/5 — L'umami des morilles durcit ce rouge jeune ; carafer (P29, P43). | AE40: 2/5 — Tanin trop présent pour l'émulsion (P10) ; acidité trop faible face au beurre et la réduction vinaigrée (P3). | AF40: 1/5 — Vin sec face au sucre du dessert : il paraît amer et maigre (P22). | AG40: 1/5 — Vin sec face au sucre du dessert : il paraît amer et maigre (P22, P15). | AH40: 1/5 — Vin sec face au sucre du dessert : il paraît amer et maigre (P22, P15). | AI40: 1/5 — Vin sec face au sucre du dessert : il paraît amer et maigre (P22). | AJ40: 1/5 — Vin sec face au sucre du dessert : il paraît amer et maigre (P22). | AK40: 1/5 — Vin sec face au sucre du dessert : il paraît amer et maigre (P22). | AL40: 1/5 — Vin sec face au sucre du dessert : il paraît amer et maigre (P22). | AM40: 1/5 — Vin sec face au sucre du dessert : il paraît amer et maigre (P22, P15). | AN40: 1/5 — Vin sec face au sucre du dessert : il paraît amer et maigre (P22). | AO40: 1/5 — Vin sec face au sucre du dessert : il paraît amer et maigre (P22, P7, P35). | AP40: 1/5 — Rouge jeune tannique, durci par le fromage (P5, P29).
... A68: Rouges | B68: L-R40 · Saint-Estèphe Château Petit Bocq 2023 · 37,5 cl | C68: 32 | D68: 1/5 — Tanin trop présent pour l'amertume de la roquette (P30) ; le bois couvre la finesse et amplifie l'amertume (P30) ; trop puissant, il écrase le plat (P20). | E68: 1/5 — Rouge : son tanin durcit au contact du poisson cru (P27). | F68: 1/5 — Rouge : son tanin durcit au contact de la panure (P34). | G68: 1/5 — Rouge : son tanin durcit au contact de la chair fine (P24). | H68: 1/5 — Rouge : son tanin durcit au contact de l'iode (goût métallique) (P27). | I68: 1/5 — Rouge : son tanin durcit au contact de l'iode (P27). | J68: 1/5 — Rouge : son tanin durcit au contact du fromage, ingrédient principal (P5). | K68: 1/5 — Rouge : son tanin durcit au contact de la panure et l'iode (P34). | L68: 1/5 — Tanin trop présent pour l'umami de l'escargot (P29) ; le bois couvre la finesse et amplifie l'amertume (P19). | M68: 1/5 — Tanin durci par le sucre et le vinaigre de la sauce (P22, P23). | N68: 1/5 — Rouge : son tanin durcit au contact du curry (P6). | O68: 1/5 — Tanin qui heurte le gras fondant, sans l'opposition du sucre (P4, P20). | P68: 1/5 — Rouge : son tanin durcit au contact du homard (P27). | Q68: 1/5 — Tanin trop présent pour la chair iodée et la tomate (P27) ; le bois couvre la finesse et amplifie l'amertume (P19). | R68: 1/5 — Tanin trop présent pour l'umami et l'amertume du broccolini (P29) ; le bois couvre la finesse et amplifie l'amertume (P19). | S68: 1/5 — Rouge : son tanin durcit au contact du cabillaud et les crevettes (P27). | T68: 1/5 — Rouge : son tanin durcit au contact de la sole (P27). | U68: 1/5 — Tanin trop présent pour le thon cru (P27) ; le bois couvre la finesse et amplifie l'amertume (P19) ; acidité trop faible face aux câpres et cornichons (P23). | V68: 2/5 — Tanin trop présent pour l'umami des champignons et du parmesan (P29). | W68: 1/5 — Tanin durci par l'umami et le sucre de la laque (P29, P22). | X68: 1/5 — Rouge : son tanin durcit au contact du beurre et le citron (P3). | Y68: 2/5 — Tanin trop présent pour l'amertume des chiconettes (P30). | Z68: 1/5 — Rouge : son tanin durcit au contact de la sauce blanche (P24). | AA68: 2/5 — Tanin trop présent pour la viande blanche fondante (P40). | AB68: 1/5 — Tanin trop présent pour la viande crue et maigre (P21) ; le bois couvre la finesse et amplifie l'amertume (P19) ; acidité trop faible face aux condiments (P23). | AC68: 2/5 — Tanin trop présent pour le poivre (P13) ; tanins jeunes durcis par le poivre ; carafer (P13, P43). | AD68: 2/5 — Tanin trop présent pour l'umami des morilles (P29) ; l'umami des morilles durcit ce rouge jeune ; carafer (P29, P43). | AE68: 2/5 — Tanin trop présent pour l'émulsion (P10) ; acidité trop faible face au beurre et la réduction vinaigrée (P3). | AF68: 1/5 — Vin sec face au sucre du dessert : il paraît amer et maigre (P22). | AG68: 1/5 — Vin sec face au sucre du dessert : il paraît amer et maigre (P22, P15). | AH68: 1/5 — Vin sec face au sucre du dessert : il paraît amer et maigre (P22, P15). | AI68: 1/5 — Vin sec face au sucre du dessert : il paraît amer et maigre (P22). | AJ68: 1/5 — Vin sec face au sucre du dessert : il paraît amer et maigre (P22). | AK68: 1/5 — Vin sec face au sucre du dessert : il paraît amer et maigre (P22). | AL68: 1/5 — Vin sec face au sucre du dessert : il paraît amer et maigre (P22). | AM68: 1/5 — Vin sec face au sucre du dessert : il paraît amer et maigre (P22, P15). | AN68: 1/5 — Vin sec face au sucre du dessert : il paraît amer et maigre (P22). | AO68: 1/5 — Vin sec face au sucre du dessert : il paraît amer et maigre (P22, P7, P35). | AP68: 1/5 — Rouge jeune tannique, durci par le fromage (P5, P29).
A69: Rosés | B69: ROSÉS
A70: Rosés | B70: L-P01 · Côtes de Provence Le Merle 2025 | C70: 42 | D70: 3/5 — Blanc correct sur le bœuf cru, mais le sel du parmesan autorise et appelle un rouge léger (P28, P20). | E70: 3/5 — Acidité trop faible face au citron vert (P23). | F70: 3/5 — Acidité trop faible face aux câpres et cornichons (P23). | G70: 3/5 — Acidité trop faible face au beurre noisette (P3). | H70: 3/5 — Acidité trop faible face à l'iode (P9). | I70: 3/5 — Acidité trop faible face au beurre à l'ail (P3). | J70: 3/5 — Acidité trop faible face à la friture et le fromage (P34). | K70: 3/5 — Acidité trop faible face à la friture (P34). | L70: 3/5 — Rosé souple, léger, sans bois : profil qui convient, sans point d'ancrage décisif (P20, P3). | M70: 2/5 — Blanc sec qui paraît maigre et dur face à la sauce aigre-douce (P22). | N70: 3/5 — Acidité trop faible face à la Granny Smith (P23). | O70: 2/5 — Blanc sec trop maigre face au gras (P20) ; sans le sucre qui répond au sel (P4). | P70: 3/5 — Trop léger, il disparaît derrière le plat (P20). | Q70: 3/5 — Acidité trop faible face à la tomate et le citron (P23). | R70: 4/5 — Rosé souple, léger, sans bois : profil qui convient, sans point d'ancrage décisif (P20, P23). | S70: 3/5 — Acidité trop faible face à la mousseline (P3). | T70: 3/5 — Acidité trop faible face au beurre noisette (P3). | U70: 3/5 — Acidité trop faible face aux câpres et cornichons (P23). | V70: 3/5 — Trop léger, il disparaît derrière le plat (P20). | W70: 2/5 — Vin sec qui paraît maigre face à la laque sucrée (P22) ; umami qui durcit l'acidité (P29). | X70: 3/5 — Acidité trop faible face au citron (P23). | Y70: 3/5 — Trop léger, il disparaît derrière le plat (P20). | Z70: 3/5 — Trop léger, il disparaît derrière le plat (P20). | AA70: 3/5 — Trop léger, il disparaît derrière le plat (P20). | AB70: 3/5 — Acidité trop faible face aux condiments (P23). | AC70: 2/5 — Trop léger, il disparaît derrière le plat (P20). | AD70: 2/5 — Trop léger, il disparaît derrière le plat (P20). | AE70: 2/5 — Acidité trop faible face au beurre et la réduction vinaigrée (P3) ; trop léger, il disparaît derrière le plat (P20). | AF70: 1/5 — Vin sec face au sucre du dessert : il paraît amer et maigre (P22). | AG70: 1/5 — Vin sec face au sucre du dessert : il paraît amer et maigre (P22, P15). | AH70: 1/5 — Vin sec face au sucre du dessert : il paraît amer et maigre (P22, P15). | AI70: 1/5 — Vin sec face au sucre du dessert : il paraît amer et maigre (P22). | AJ70: 1/5 — Vin sec face au sucre du dessert : il paraît amer et maigre (P22). | AK70: 1/5 — Vin sec face au sucre du dessert : il paraît amer et maigre (P22). | AL70: 1/5 — Vin sec face au sucre du dessert : il paraît amer et maigre (P22). | AM70: 1/5 — Vin sec face au sucre du dessert : il paraît amer et maigre (P22, P15). | AN70: 1/5 — Vin sec face au sucre du dessert : il paraît amer et maigre (P22). | AO70: 1/5 — Vin sec face au sucre du dessert : il paraît amer et maigre (P22, P7, P35). | AP70: 2/5 — Rosé léger, sans la tension ni la patine qu'appellent trois fromages (P5, P20).
A71: Rosés | B71: L-P02 · Côtes de Provence Whispering Angel 2024-2025 | C71: 55 | D71: 3/5 — Blanc correct sur le bœuf cru, mais le sel du parmesan autorise et appelle un rouge léger (P28, P20). | E71: 3/5 — Acidité trop faible face au citron vert (P23). | F71: 3/5 — Acidité trop faible face aux câpres et cornichons (P23). | G71: 3/5 — Acidité trop faible face au beurre noisette (P3). | H71: 3/5 — Acidité trop faible face à l'iode (P9). | I71: 3/5 — Acidité trop faible face au beurre à l'ail (P3). | J71: 3/5 — Acidité trop faible face à la friture et le fromage (P34). | K71: 3/5 — Acidité trop faible face à la friture (P34). | L71: 3/5 — Rosé souple, léger, sans bois : profil qui convient, sans point d'ancrage décisif (P20, P3). | M71: 2/5 — Blanc sec qui paraît maigre et dur face à la sauce aigre-douce (P22). | N71: 3/5 — Acidité trop faible face à la Granny Smith (P23). | O71: 2/5 — Blanc sec trop maigre face au gras (P20) ; sans le sucre qui répond au sel (P4). | P71: 3/5 — Trop léger, il disparaît derrière le plat (P20). | Q71: 3/5 — Acidité trop faible face à la tomate et le citron (P23). | R71: 4/5 — Rosé souple, léger, sans bois : profil qui convient, sans point d'ancrage décisif (P20, P23). | S71: 3/5 — Acidité trop faible face à la mousseline (P3). | T71: 3/5 — Acidité trop faible face au beurre noisette (P3). | U71: 3/5 — Acidité trop faible face aux câpres et cornichons (P23). | V71: 3/5 — Trop léger, il disparaît derrière le plat (P20). | W71: 2/5 — Vin sec qui paraît maigre face à la laque sucrée (P22) ; umami qui durcit l'acidité (P29). | X71: 3/5 — Acidité trop faible face au citron (P23). | Y71: 3/5 — Trop léger, il disparaît derrière le plat (P20). | Z71: 3/5 — Trop léger, il disparaît derrière le plat (P20). | AA71: 3/5 — Trop léger, il disparaît derrière le plat (P20). | AB71: 3/5 — Acidité trop faible face aux condiments (P23). | AC71: 2/5 — Trop léger, il disparaît derrière le plat (P20). | AD71: 2/5 — Trop léger, il disparaît derrière le plat (P20). | AE71: 2/5 — Acidité trop faible face au beurre et la réduction vinaigrée (P3) ; trop léger, il disparaît derrière le plat (P20). | AF71: 1/5 — Vin sec face au sucre du dessert : il paraît amer et maigre (P22). | AG71: 1/5 — Vin sec face au sucre du dessert : il paraît amer et maigre (P22, P15). | AH71: 1/5 — Vin sec face au sucre du dessert : il paraît amer et maigre (P22, P15). | AI71: 1/5 — Vin sec face au sucre du dessert : il paraît amer et maigre (P22). | AJ71: 1/5 — Vin sec face au sucre du dessert : il paraît amer et maigre (P22). | AK71: 1/5 — Vin sec face au sucre du dessert : il paraît amer et maigre (P22). | AL71: 1/5 — Vin sec face au sucre du dessert : il paraît amer et maigre (P22). | AM71: 1/5 — Vin sec face au sucre du dessert : il paraît amer et maigre (P22, P15). | AN71: 1/5 — Vin sec face au sucre du dessert : il paraît amer et maigre (P22). | AO71: 1/5 — Vin sec face au sucre du dessert : il paraît amer et maigre (P22, P7, P35). | AP71: 2/5 — Rosé léger, sans la tension ni la patine qu'appellent trois fromages (P5, P20).
A72: Bulles | B72: BULLES
A73: Bulles | B73: L-E01 · Valdobbiadene Prosecco Superiore Col de l'Utia NM | C73: 62 | D73: 3/5 — Blanc correct sur le bœuf cru, mais le sel du parmesan autorise et appelle un rouge léger (P28, P20). | E73: 3/5 — Acidité trop faible face au citron vert (P23). | F73: 3/5 — Acidité trop faible face aux câpres et cornichons (P23). | G73: 3/5 — Acidité trop faible face au beurre noisette (P3). | H73: 3/5 — Acidité trop faible face à l'iode (P9). | I73: 3/5 — Acidité trop faible face au beurre à l'ail (P3). | J73: 3/5 — Acidité trop faible face à la friture et le fromage (P34). | K73: 3/5 — Acidité trop faible face à la friture (P34). | L73: 3/5 — La bulle ne trouve pas d'ancrage dans le beurre d'escargot (P41). | M73: 3/5 — Bulle sur la friture (P34) ; dosage peut-être Extra Dry, mais moins sucré que la sauce (à confirmer) (P22). | N73: 3/5 — Acidité trop faible face à la Granny Smith (P23). | O73: 2/5 — Blanc sec trop maigre face au gras (P20) ; sans le sucre qui répond au sel (P4). | P73: 3/5 — Trop léger, il disparaît derrière le plat (P20). | Q73: 3/5 — Acidité trop faible face à la tomate et le citron (P23). | R73: 3/5 — La bulle ne trouve pas d'ancrage sur le thon et l'umami (P41). | S73: 3/5 — Acidité trop faible face à la mousseline (P3). | T73: 3/5 — Acidité trop faible face au beurre noisette (P3). | U73: 3/5 — Acidité trop faible face aux câpres et cornichons (P23). | V73: 3/5 — Effervescent trop vif pour l'onctuosité et le sous-bois (P41, P20) ; trop léger, il disparaît derrière le plat (P20). | W73: 2/5 — Vin sec qui paraît maigre face à la laque sucrée (P22) ; umami qui durcit l'acidité (P29). | X73: 3/5 — Acidité trop faible face au citron (P23). | Y73: 3/5 — Blanc de blancs trop fin pour la crème aux morilles (P41, P20) ; trop léger, il disparaît derrière le plat (P20). | Z73: 3/5 — Trop léger, il disparaît derrière le plat (P20). | AA73: 3/5 — Bulle sans l'ampleur ni la richesse qu'appelle la laque (P14, P20) ; trop léger, il disparaît derrière le plat (P20). | AB73: 3/5 — Acidité trop faible face aux condiments (P23). | AC73: 2/5 — Trop léger, il disparaît derrière le plat (P20). | AD73: 3/5 — Trop léger, il disparaît derrière le plat (P20). | AE73: 2/5 — Acidité trop faible face au beurre et la réduction vinaigrée (P3) ; trop léger, il disparaît derrière le plat (P20). | AF73: 1/5 — Vin sec face au sucre du dessert : il paraît amer et maigre (P22). | AG73: 1/5 — Vin sec face au sucre du dessert : il paraît amer et maigre (P22, P15). | AH73: 1/5 — Vin sec face au sucre du dessert : il paraît amer et maigre (P22, P15). | AI73: 1/5 — Vin sec face au sucre du dessert : il paraît amer et maigre (P22). | AJ73: 2/5 — Bulle légère et peu alcoolisée, mais moins sucrée que le sorbet (P22, P20). | AK73: 1/5 — Vin sec face au sucre du dessert : il paraît amer et maigre (P22). | AL73: 1/5 — Vin sec face au sucre du dessert : il paraît amer et maigre (P22). | AM73: 1/5 — Vin sec face au sucre du dessert : il paraît amer et maigre (P22, P15). | AN73: 1/5 — Vin sec face au sucre du dessert : il paraît amer et maigre (P22). | AO73: 2/5 — Bulle légère et peu d'alcool, mais moins sucrée que le sorbet ; agrume et vodka plafonnent (P22, P35, P7). | AP73: 2/5 — Blanc peu acide qui manque de tension face au sel et au gras (P5, P3).
A74: Bulles | B74: L-E02 · Champagne R de Ruinart Brut NM · 37,5 cl | C74: 58 | D74: 3/5 — Blanc correct sur le bœuf cru, mais le sel du parmesan autorise et appelle un rouge léger (P28, P20). | E74: 4/5 — Effervescent vineux : profil qui convient, sans point d'ancrage décisif (P20, P23) ; le citron vert nature plafonne l'accord (P7, P35). | F74: 4/5 — L'émulsion à l'œuf de la tartare plafonne l'accord (P10, P35) ; la bulle et l'acidité nettoient la friture (P34). | G74: 4/5 — Effervescent vineux : profil qui convient, sans point d'ancrage décisif (P20, P3). | H74: 4/5 — Effervescent vineux : profil qui convient, sans point d'ancrage décisif (P20, P9) ; le vinaigre à l'échalote plafonne l'accord (P11, P35). | I74: 4/5 — Effervescent vineux : profil qui convient, sans point d'ancrage décisif (P20, P3). | J74: 5/5 — La bulle et l'acidité coupent la friture et le fromage (P34, P3). | K74: 5/5 — Bulle septentrionale qui nettoie la friture et répond à l'iode de la crevette (P34, P42, P41). | L74: 3/5 — La bulle ne trouve pas d'ancrage dans le beurre d'escargot (P41). | M74: 2/5 — La bulle nettoie la friture (P34) ; mais un brut paraît maigre face au sucre (P22). | N74: 4/5 — Effervescent vineux : profil qui convient, sans point d'ancrage décisif (P20, P23) ; la mayonnaise plafonne l'accord (P10, P35). | O74: 2/5 — Blanc sec trop maigre face au gras (P20) ; sans le sucre qui répond au sel (P4). | P74: 5/5 — Effervescent vineux : la bulle coupe la crème, les pinots répondent à la bisque (P41, P3). | Q74: 4/5 — Effervescent vineux : profil qui convient, sans point d'ancrage décisif (P20, P23) ; le citron de la sauce vierge plafonne l'accord (P11, P35). | R74: 3/5 — La bulle ne trouve pas d'ancrage sur le thon et l'umami (P41). | S74: 4/5 — Effervescent vineux : profil qui convient, sans point d'ancrage décisif (P20, P3) ; l'émulsion beurre-œuf-citron plafonne l'accord (P10, P35). | T74: 4/5 — Effervescent vineux : profil qui convient, sans point d'ancrage décisif (P20, P3). | U74: 4/5 — Effervescent vineux : profil qui convient, sans point d'ancrage décisif (P20, P23) ; la base mayonnaise plafonne l'accord (P10, P35). | V74: 3/5 — Effervescent trop vif pour l'onctuosité et le sous-bois (P41, P20). | W74: 2/5 — Vin sec qui paraît maigre face à la laque sucrée (P22) ; umami qui durcit l'acidité (P29). | X74: 4/5 — Effervescent vineux : profil qui convient, sans point d'ancrage décisif (P20, P23) ; la sauce au citron plafonne l'accord (P11, P35). | Y74: 4/5 — Effervescent vineux qui tient la volaille et la crème, sans miroir des morilles (P41, P25). | Z74: 5/5 — Effervescent vineux, taillé pour la crème et les plats de brasserie (P41, P42). | AA74: 3/5 — Bulle sans l'ampleur ni la richesse qu'appelle la laque (P14, P20). | AB74: 3/5 — Blanc sans la structure qu'appelle la viande (P21, P20). | AC74: 2/5 — Blanc sans la structure qu'appelle la viande (P21, P20). | AD74: 3/5 — Blanc sans la structure qu'appelle la viande (P21, P20). | AE74: 2/5 — Blanc sans la structure qu'appelle la viande (P21, P20). | AF74: 1/5 — Vin sec face au sucre du dessert : il paraît amer et maigre (P22). | AG74: 1/5 — Vin sec face au sucre du dessert : il paraît amer et maigre (P22, P15). | AH74: 1/5 — Vin sec face au sucre du dessert : il paraît amer et maigre (P22, P15). | AI74: 1/5 — Vin sec face au sucre du dessert : il paraît amer et maigre (P22). | AJ74: 1/5 — Vin sec face au sucre du dessert : il paraît amer et maigre (P22). | AK74: 1/5 — Vin sec face au sucre du dessert : il paraît amer et maigre (P22). | AL74: 1/5 — Vin sec face au sucre du dessert : il paraît amer et maigre (P22). | AM74: 1/5 — Vin sec face au sucre du dessert : il paraît amer et maigre (P22, P15). | AN74: 1/5 — Vin sec face au sucre du dessert : il paraît amer et maigre (P22). | AO74: 1/5 — Vin sec face au sucre du dessert : il paraît amer et maigre (P22, P7, P35). | AP74: 3/5 — Blanc tendu sans bois, sûr sur pâte fraîche ou pressée, sans garantie sur un bleu (P5, P18).
A75: Bulles | B75: L-E03 · Champagne R de Ruinart Brut NM | C75: 105 | D75: 3/5 — Blanc correct sur le bœuf cru, mais le sel du parmesan autorise et appelle un rouge léger (P28, P20). | E75: 4/5 — Effervescent vineux : profil qui convient, sans point d'ancrage décisif (P20, P23) ; le citron vert nature plafonne l'accord (P7, P35). | F75: 4/5 — L'émulsion à l'œuf de la tartare plafonne l'accord (P10, P35) ; la bulle et l'acidité nettoient la friture (P34). | G75: 4/5 — Effervescent vineux : profil qui convient, sans point d'ancrage décisif (P20, P3). | H75: 4/5 — Effervescent vineux : profil qui convient, sans point d'ancrage décisif (P20, P9) ; le vinaigre à l'échalote plafonne l'accord (P11, P35). | I75: 4/5 — Effervescent vineux : profil qui convient, sans point d'ancrage décisif (P20, P3). | J75: 5/5 — La bulle et l'acidité coupent la friture et le fromage (P34, P3). | K75: 5/5 — Bulle septentrionale qui nettoie la friture et répond à l'iode de la crevette (P34, P42, P41). | L75: 3/5 — La bulle ne trouve pas d'ancrage dans le beurre d'escargot (P41). | M75: 2/5 — La bulle nettoie la friture (P34) ; mais un brut paraît maigre face au sucre (P22). | N75: 4/5 — Effervescent vineux : profil qui convient, sans point d'ancrage décisif (P20, P23) ; la mayonnaise plafonne l'accord (P10, P35). | O75: 2/5 — Blanc sec trop maigre face au gras (P20) ; sans le sucre qui répond au sel (P4). | P75: 5/5 — Effervescent vineux : la bulle coupe la crème, les pinots répondent à la bisque (P41, P3). | Q75: 4/5 — Effervescent vineux : profil qui convient, sans point d'ancrage décisif (P20, P23) ; le citron de la sauce vierge plafonne l'accord (P11, P35). | R75: 3/5 — La bulle ne trouve pas d'ancrage sur le thon et l'umami (P41). | S75: 4/5 — Effervescent vineux : profil qui convient, sans point d'ancrage décisif (P20, P3) ; l'émulsion beurre-œuf-citron plafonne l'accord (P10, P35). | T75: 4/5 — Effervescent vineux : profil qui convient, sans point d'ancrage décisif (P20, P3). | U75: 4/5 — Effervescent vineux : profil qui convient, sans point d'ancrage décisif (P20, P23) ; la base mayonnaise plafonne l'accord (P10, P35). | V75: 3/5 — Effervescent trop vif pour l'onctuosité et le sous-bois (P41, P20). | W75: 2/5 — Vin sec qui paraît maigre face à la laque sucrée (P22) ; umami qui durcit l'acidité (P29). | X75: 4/5 — Effervescent vineux : profil qui convient, sans point d'ancrage décisif (P20, P23) ; la sauce au citron plafonne l'accord (P11, P35). | Y75: 4/5 — Effervescent vineux qui tient la volaille et la crème, sans miroir des morilles (P41, P25). | Z75: 5/5 — Effervescent vineux, taillé pour la crème et les plats de brasserie (P41, P42). | AA75: 3/5 — Bulle sans l'ampleur ni la richesse qu'appelle la laque (P14, P20). | AB75: 3/5 — Blanc sans la structure qu'appelle la viande (P21, P20). | AC75: 2/5 — Blanc sans la structure qu'appelle la viande (P21, P20). | AD75: 3/5 — Blanc sans la structure qu'appelle la viande (P21, P20). | AE75: 2/5 — Blanc sans la structure qu'appelle la viande (P21, P20). | AF75: 1/5 — Vin sec face au sucre du dessert : il paraît amer et maigre (P22). | AG75: 1/5 — Vin sec face au sucre du dessert : il paraît amer et maigre (P22, P15). | AH75: 1/5 — Vin sec face au sucre du dessert : il paraît amer et maigre (P22, P15). | AI75: 1/5 — Vin sec face au sucre du dessert : il paraît amer et maigre (P22). | AJ75: 1/5 — Vin sec face au sucre du dessert : il paraît amer et maigre (P22). | AK75: 1/5 — Vin sec face au sucre du dessert : il paraît amer et maigre (P22). | AL75: 1/5 — Vin sec face au sucre du dessert : il paraît amer et maigre (P22). | AM75: 1/5 — Vin sec face au sucre du dessert : il paraît amer et maigre (P22, P15). | AN75: 1/5 — Vin sec face au sucre du dessert : il paraît amer et maigre (P22). | AO75: 1/5 — Vin sec face au sucre du dessert : il paraît amer et maigre (P22, P7, P35). | AP75: 3/5 — Blanc tendu sans bois, sûr sur pâte fraîche ou pressée, sans garantie sur un bleu (P5, P18).
A76: Bulles | B76: L-E04 · Champagne Laurent-Perrier Cuvée Rosé NM | C76: 168 | D76: 3/5 — Blanc correct sur le bœuf cru, mais le sel du parmesan autorise et appelle un rouge léger (P28, P20). | E76: 2/5 — Tanin trop présent pour le poisson cru (P27) ; acidité trop faible face au citron vert (P23). | F76: 3/5 — Tanin trop présent pour la panure (P34) ; acidité trop faible face aux câpres et cornichons (P23). | G76: 2/5 — Tanin trop présent pour la chair fine (P24) ; acidité trop faible face au beurre noisette (P3). | H76: 2/5 — Tanin trop présent pour l'iode (goût métallique) (P27) ; acidité trop faible face à l'iode (P9). | I76: 2/5 — Tanin trop présent pour l'iode (P27) ; acidité trop faible face au beurre à l'ail (P3). | J76: 3/5 — Tanin trop présent pour le fromage, ingrédient principal (P5) ; acidité trop faible face à la friture et le fromage (P34). | K76: 3/5 — Tanin trop présent pour la panure et l'iode (P34) ; acidité trop faible face à la friture (P34). | L76: 3/5 — La bulle ne trouve pas d'ancrage dans le beurre d'escargot (P41). | M76: 2/5 — La bulle nettoie la friture (P34) ; mais un brut paraît maigre face au sucre (P22). | N76: 2/5 — Tanin trop présent pour le curry (P6) ; acidité trop faible face à la Granny Smith (P23). | O76: 2/5 — Blanc sec trop maigre face au gras (P20) ; sans le sucre qui répond au sel (P4). | P76: 5/5 — Effervescent vineux : la bulle coupe la crème, les pinots répondent à la bisque (P41, P3). | Q76: 3/5 — Acidité trop faible face à la tomate et le citron (P23). | R76: 3/5 — La bulle ne trouve pas d'ancrage sur le thon et l'umami (P41). | S76: 2/5 — Tanin trop présent pour le cabillaud et les crevettes (P27) ; acidité trop faible face à la mousseline (P3). | T76: 2/5 — Tanin trop présent pour la sole (P27) ; acidité trop faible face au beurre noisette (P3). | U76: 3/5 — Acidité trop faible face aux câpres et cornichons (P23). | V76: 3/5 — Effervescent trop vif pour l'onctuosité et le sous-bois (P41, P20). | W76: 2/5 — Vin sec qui paraît maigre face à la laque sucrée (P22) ; umami qui durcit l'acidité (P29). | X76: 2/5 — Tanin trop présent pour le beurre et le citron (P3) ; acidité trop faible face au citron (P23). | Y76: 4/5 — Effervescent vineux qui tient la volaille et la crème, sans miroir des morilles (P41, P25). | Z76: 4/5 — Effervescent rosé vineux : profil qui convient, sans point d'ancrage décisif (P20, P3). | AA76: 3/5 — Bulle sans l'ampleur ni la richesse qu'appelle la laque (P14, P20). | AB76: 3/5 — Acidité trop faible face aux condiments (P23). | AC76: 2/5 — Blanc sans la structure qu'appelle la viande (P21, P20). | AD76: 3/5 — Blanc sans la structure qu'appelle la viande (P21, P20). | AE76: 2/5 — Acidité trop faible face au beurre et la réduction vinaigrée (P3). | AF76: 1/5 — Vin sec face au sucre du dessert : il paraît amer et maigre (P22). | AG76: 1/5 — Vin sec face au sucre du dessert : il paraît amer et maigre (P22, P15). | AH76: 1/5 — Vin sec face au sucre du dessert : il paraît amer et maigre (P22, P15). | AI76: 1/5 — Vin sec face au sucre du dessert : il paraît amer et maigre (P22). | AJ76: 1/5 — Vin sec face au sucre du dessert : il paraît amer et maigre (P22). | AK76: 1/5 — Vin sec face au sucre du dessert : il paraît amer et maigre (P22). | AL76: 1/5 — Vin sec face au sucre du dessert : il paraît amer et maigre (P22). | AM76: 1/5 — Vin sec face au sucre du dessert : il paraît amer et maigre (P22, P15). | AN76: 1/5 — Vin sec face au sucre du dessert : il paraît amer et maigre (P22). | AO76: 1/5 — Vin sec face au sucre du dessert : il paraît amer et maigre (P22, P7, P35). | AP76: 2/5 — Blanc peu acide qui manque de tension face au sel et au gras (P5, P3).
A77: Bulles | B77: L-E05 · Champagne Ruinart Blanc de Blancs NM · 37,5 cl | C77: 90 | D77: 3/5 — Blanc correct sur le bœuf cru, mais le sel du parmesan autorise et appelle un rouge léger (P28, P20). | E77: 4/5 — Le citron vert nature plafonne l'accord (P7, P35) ; blanc de blancs tendu, fait pour le poisson cru (P41). | F77: 4/5 — L'émulsion à l'œuf de la tartare plafonne l'accord (P10, P35) ; la bulle et l'acidité nettoient la friture (P34). | G77: 4/5 — Effervescent blanc de blancs : profil qui convient, sans point d'ancrage décisif (P20, P3). | H77: 4/5 — Le vinaigre à l'échalote plafonne l'accord (P11, P35) ; blanc de blancs tendu sur l'iode (P41). | I77: 4/5 — Effervescent blanc de blancs : profil qui convient, sans point d'ancrage décisif (P20, P3). | J77: 5/5 — La bulle et l'acidité coupent la friture et le fromage (P34, P3). | K77: 5/5 — Bulle septentrionale qui nettoie la friture et répond à l'iode de la crevette (P34, P42, P41). | L77: 3/5 — La bulle ne trouve pas d'ancrage dans le beurre d'escargot (P41). | M77: 2/5 — La bulle nettoie la friture (P34) ; mais un brut paraît maigre face au sucre (P22). | N77: 4/5 — Effervescent blanc de blancs : profil qui convient, sans point d'ancrage décisif (P20, P23) ; la mayonnaise plafonne l'accord (P10, P35). | O77: 2/5 — Blanc sec trop maigre face au gras (P20) ; sans le sucre qui répond au sel (P4). | P77: 3/5 — Trop léger, il disparaît derrière le plat (P20). | Q77: 4/5 — Effervescent blanc de blancs : profil qui convient, sans point d'ancrage décisif (P20, P23) ; le citron de la sauce vierge plafonne l'accord (P11, P35). | R77: 3/5 — La bulle ne trouve pas d'ancrage sur le thon et l'umami (P41). | S77: 4/5 — Effervescent blanc de blancs : profil qui convient, sans point d'ancrage décisif (P20, P3) ; l'émulsion beurre-œuf-citron plafonne l'accord (P10, P35). | T77: 4/5 — Effervescent blanc de blancs : profil qui convient, sans point d'ancrage décisif (P20, P3). | U77: 4/5 — Effervescent blanc de blancs : profil qui convient, sans point d'ancrage décisif (P20, P23) ; la base mayonnaise plafonne l'accord (P10, P35). | V77: 3/5 — Effervescent trop vif pour l'onctuosité et le sous-bois (P41, P20) ; trop léger, il disparaît derrière le plat (P20). | W77: 2/5 — Vin sec qui paraît maigre face à la laque sucrée (P22) ; umami qui durcit l'acidité (P29). | X77: 4/5 — Effervescent blanc de blancs : profil qui convient, sans point d'ancrage décisif (P20, P23) ; la sauce au citron plafonne l'accord (P11, P35). | Y77: 3/5 — Blanc de blancs trop fin pour la crème aux morilles (P41, P20) ; trop léger, il disparaît derrière le plat (P20). | Z77: 3/5 — Trop léger, il disparaît derrière le plat (P20). | AA77: 3/5 — Bulle sans l'ampleur ni la richesse qu'appelle la laque (P14, P20) ; trop léger, il disparaît derrière le plat (P20). | AB77: 3/5 — Blanc sans la structure qu'appelle la viande (P21, P20). | AC77: 2/5 — Trop léger, il disparaît derrière le plat (P20). | AD77: 3/5 — Trop léger, il disparaît derrière le plat (P20). | AE77: 2/5 — Trop léger, il disparaît derrière le plat (P20). | AF77: 1/5 — Vin sec face au sucre du dessert : il paraît amer et maigre (P22). | AG77: 1/5 — Vin sec face au sucre du dessert : il paraît amer et maigre (P22, P15). | AH77: 1/5 — Vin sec face au sucre du dessert : il paraît amer et maigre (P22, P15). | AI77: 1/5 — Vin sec face au sucre du dessert : il paraît amer et maigre (P22). | AJ77: 1/5 — Vin sec face au sucre du dessert : il paraît amer et maigre (P22). | AK77: 1/5 — Vin sec face au sucre du dessert : il paraît amer et maigre (P22). | AL77: 1/5 — Vin sec face au sucre du dessert : il paraît amer et maigre (P22). | AM77: 1/5 — Vin sec face au sucre du dessert : il paraît amer et maigre (P22, P15). | AN77: 1/5 — Vin sec face au sucre du dessert : il paraît amer et maigre (P22). | AO77: 1/5 — Vin sec face au sucre du dessert : il paraît amer et maigre (P22, P7, P35). | AP77: 3/5 — Blanc tendu sans bois, sûr sur pâte fraîche ou pressée, sans garantie sur un bleu (P5, P18).
